Workbook

Sheet Inhoudsopgave
A1: Inhoudsopgave | B1: Pagina
A4: T01 bestuur en ondersteuning | B4: 1
A5: T02 burgerzaken | B5: 8
A6: T03 beheer overige gebouwen en gronden | B6: 19
A7: T04 bedrijf | B7: 24
A8: T04 loon | B8: 34
A9: T04 werf | B9: 48
A10: T05 Treasury | B10: 54
A11: T06 1 OZB Woningen | B11: 56
A12: T06 2 OZB Niet-Woningen | B12: 60
A13: T06 4 Belastingen overig | B13: 63
A14: T07 Gemeentefonds en overige rijksuitkeringen | B14: 65
A15: T08 Overige baten en lasten | B15: 68
... A78: T83 wonen en bouwen | B78: 250

Sheet Inlees CODA
A1: Inleesbestand CODA
A2: Element 2 | B2: Element 3 | C2: Element 4 | D2: Element 5 | E2: 2025 | F2: 2026 | G2: 2027 | H2: 2028 | I2: 2029 | J2: Taakveld | K2: Toelichting
A3: 601001 | B3: 43819 | E3: 9573 | F3: 9822 | G3: 10038 | H3: 10259 | I3: 10485 | J3: T01
A4: 601001 | B4: 43812 | E4: 87915 | F4: 94864 | G4: 86556 | H4: 88285 | I4: 90051 | J4: T01
A5: 601001 | B5: 43812 | E5: 7716.168 | F5: 7916.7884 | G5: 8090.9577 | H5: 8268.9588 | I5: 8450.8759 | J5: T01
A6: 601001 | B6: 43812 | E6: 17077 | F6: 17522 | G6: 17907 | H6: 18302 | I6: 18705 | J6: T01
A7: 601001 | B7: 43812 | E7: 4085 | F7: 4191 | G7: 4283 | H7: 4377 | I7: 4473 | J7: T01
A8: 601002 | B8: 43819 | E8: 11538 | F8: 12121 | G8: 12387 | H8: 12660 | I8: 12938 | J8: T01
A9: 601002 | B9: 43812 | E9: 11401 | F9: 11801 | G9: 12149 | H9: 12504 | I9: 12867 | J9: T01
A10: 601003 | B10: 43812 | E10: 41778 | F10: 43712 | G10: 45231 | H10: 47118 | I10: 48879.5 | J10: T01
A11: 601004 | B11: 43812 | E11: 69833 | F11: 70000 | G11: 71540 | H11: 73114 | I11: 74723 | J11: T01
A12: 601005 | B12: 43812 | E12: 1684.892 | F12: 1728.6992 | G12: 1766.7306 | H12: 1805.5986 | I12: 1845.3218 | J12: T01
A13: 601901 | B13: 41000 | E13: 0 | F13: 0 | G13: 0 | H13: 0 | I13: 0 | J13: T01
A14: 601007 | B14: 41101 | E14: 88189 | F14: 117492 | G14: 119842 | H14: 50933 | I14: 0 | J14: T01
... A212: 604056 | B212: 43812 | E212: 1633 | F212: 1675 | G212: 1712 | H212: 1750 | I212: 1789 | J212: T04L
A213: #REF! | B213: 43812 | E213: 20000 | F213: 31806 | G213: 20971 | H213: 42894 | I213: 21904 | J213: T04L
A214: 604057 | B214: 43819 | E214: 78963 | F214: 103802 | G214: 106086 | H214: 108420 | I214: 110805 | J214: T04L
A215: 604057 | B215: 43812 | E215: 27992 | F215: 28719 | G215: 29351 | H215: 29998 | I215: 30659 | J215: T04L
A216: 604062 | B216: 43812 | E216: 154451 | F216: 158003 | G216: 96232 | H216: 98445 | I216: 100611 | J216: T04L
A217: 604043 | B217: 43511 | E217: 0 | F217: 0 | G217: 0 | H217: 0 | I217: 0 | J217: T04L
A218: 604901 | B218: 41100 | E218: 9206076.2 | F218: 9137962 | G218: 9562142 | H218: 9929614 | I218: 10395576 | J218: T04L
A219: 604901 | B219: 43511 | E219: 107000 | F219: 0 | G219: 0 | H219: 0 | I219: 0 | J219: T04L
A220: 604901 | B220: 47300 | E220: 0 | F220: 0 | G220: 0 | H220: 0 | I220: 0 | J220: T04L
A221: 604901 | B221: 47501 | E221: -341698.03 | F221: -352192.4 | G221: -359406.36 | H221: -377737.77 | I221: -396946.97 | J221: T04L
A222: 604901 | B222: 47501 | E222: -268835.37 | F222: -251701.74 | G222: -256858.3 | H222: -269956.82 | I222: -283685.95 | J222: T04L
A223: 604901 | B223: 47501 | E223: -198502 | F223: -186350 | G223: -190170 | H223: -199866 | I223: -210031 | J223: T04L
A224: 604901 | B224: 41100 | E224: 8931 | F224: 8918 | G224: 9328 | H224: 9757 | I224: 10206 | J224: T04L
A225: 604901 | B225: 41100 | E225: 10369.98 | F225: 12280.7 | G225: 12846 | H225: 13437 | I225: 14055 | J225: T04L
... A645: 629005 | B645: 44380 | E645: 133617 | F645: 0 | G645: 0 | H645: 0 | I645: 0 | J645: T51
A646: 629006 | B646: 44380 | F646: 461877 | G646: 466014 | H646: 470345 | I646: 474854 | J646: T51
A647: 629901 | B647: 41100 | E647: 118700.44 | F647: 140596.75 | G647: 147065 | H647: 153830 | I647: 160907 | J647: T51
A648: 629004 | B648: 84310 | E648: -19408 | F648: -14923 | G648: -14923 | H648: -14924 | I648: -14924 | J648: T51
A649: 629005 | B649: 84310 | E649: -133617 | F649: -129081 | G649: -129081 | H649: -129080 | I649: -129080 | J649: T51
A650: 630001 | B650: 42100 | E650: 7092 | F650: 7276 | G650: 7436 | H650: 7600 | I650: 7767 | J650: T52
A651: 630001 | B651: 43806 | E651: 1155 | F651: 1185 | G651: 1211 | H651: 1238 | I651: 1265 | J651: T52
A652: 630005 | B652: 42100 | E652: 1589 | F652: 1630 | G652: 1666 | H652: 1703 | I652: 1740 | J652: T52
A653: 630005 | B653: 43511 | E653: 1010.8 | F653: 1031.2 | G653: 1078.8 | H653: 1156.61 | I653: 1156.61 | J653: T52
A654: 630005 | B654: 43806 | E654: 517 | F654: 530 | G654: 542 | H654: 554 | I654: 566 | J654: T52
A655: 630005 | B655: 43812 | E655: 955 | F655: 980 | G655: 1002 | H655: 1024 | I655: 1047 | J655: T52
A656: 630002 | B656: 42100 | E656: 958 | F656: 983 | G656: 1005 | H656: 1027 | I656: 1050 | J656: T52
A657: 630002 | B657: 43806 | E657: 276 | F657: 283 | G657: 289 | H657: 295 | I657: 301 | J657: T52
A658: 630003 | B658: 42100 | E658: 386 | F658: 396 | G658: 405 | H658: 414 | I658: 423 | J658: T52
... A883: 635014 | B883: 47300 | E883: 18017.67 | F883: 15475.35 | G883: 18189.93 | H883: 18189.93 | I883: 18189.93 | J883: T57
A884: 635016 | B884: 43812 | E884: 0 | F884: 337000 | G884: 0 | H884: 0 | I884: 0 | J884: T57
A885: 635901 | B885: 41100 | E885: 678031.1 | F885: 863865.67 | G885: 898221.49 | H885: 934157.68 | I885: 971746.93 | J885: T57
A886: 635901 | B886: 47300 | E886: 80877 | F886: 81590 | G886: 93871 | H886: 93871 | I886: 86789 | J886: T57
A887: 635901 | B887: 41100 | E887: 0 | F887: 0 | G887: 0 | H887: 0 | I887: 0 | J887: T57
A888: 635901 | B888: 47300 | E888: 0 | F888: 0 | G888: 0 | H888: 0 | I888: 0 | J888: T57
A889: 635002 | B889: 83800 | E889: -30030 | F889: -30811 | G889: -31488 | H889: -32182 | I889: -32892 | J889: T57
A890: 635004 | B890: 83600 | E890: -1973 | F890: -2024 | G890: -2069 | H890: -2115 | I890: -2162 | J890: T57
A891: 635004 | B891: 83800 | E891: -3797 | F891: -3896 | G891: -3982 | H891: -4070 | I891: -4160 | J891: T57
A892: 635006 | B892: 83800 | E892: -41703 | F892: -42449 | G892: -43097 | H892: -43759 | I892: -44436 | J892: T57
A893: 635007 | B893: 83300 | E893: -4285 | F893: -1000 | G893: -1022 | H893: -1044 | I893: -1067 | J893: T57
A894: 635008 | B894: 84360 | E894: -5716 | F894: -5715 | G894: -5715 | H894: -5714 | I894: -5714 | J894: T57
A895: 635012 | B895: 83800 | E895: -58908 | F895: -104010 | G895: -135541 | H895: -102383 | I895: -37590 | J895: T57
A896: 636012 | B896: 42100 | E896: 426 | F896: 437 | G896: 447 | H896: 457 | I896: 467 | J896: T61
... A1051: 678011 | B1051: 43812 | E1051: 59200 | F1051: 22780 | G1051: 23280 | H1051: 23800 | I1051: 24320 | J1051: T660
A1052: 678901 | E1052: 0 | F1052: 0 | G1052: 0 | H1052: 0 | I1052: 0 | J1052: T660
A1053: 678004 | B1053: 83800 | E1053: -20530 | F1053: -21060 | G1053: -21520 | H1053: -21990 | I1053: -22470 | J1053: T660
A1054: 679001 | B1054: 43410 | E1054: 2337300 | F1054: 2666800 | G1054: 2789300 | H1054: 2917900 | I1054: 3051900 | J1054: T6711
A1055: 679002 | B1055: 83420 | E1055: -90000 | F1055: -92500 | G1055: -173600 | H1055: -181600 | I1055: -186000 | J1055: T6711
A1056: 680001 | B1056: 43410 | E1056: 2679674 | F1056: 1677574 | G1056: 1878975 | H1056: 2062175 | I1056: 2137375 | J1056: T6712
A1057: 680901 | B1057: 43812 | E1057: 255060 | F1057: 255701 | G1057: 261327 | H1057: 267077 | I1057: 272952 | J1057: T6712
A1058: 680002 | B1058: 83420 | E1058: -60000 | F1058: -61000 | G1058: -125500 | H1058: -131300 | I1058: -137300 | J1058: T6712
A1059: 681001 | B1059: 43410 | E1059: 551800 | F1059: 617200 | G1059: 645800 | H1059: 675600 | I1059: 706700 | J1059: T6713
A1060: 681002 | B1060: 44380 | E1060: 110400 | F1060: 115500 | G1060: 120800 | H1060: 126400 | I1060: 132200 | J1060: T6713
A1061: 682001 | B1061: 43410 | E1061: 60700 | F1061: 63500 | G1061: 66400 | H1061: 69500 | I1061: 72700 | J1061: T6714
A1062: 688001 | B1062: 43410 | E1062: 2616317 | F1062: 3749240 | G1062: 3864690 | H1062: 4008140 | I1062: 4086140 | J1062: T6752
A1063: 688002 | B1063: 43410 | E1063: 1589000 | F1063: 2828000 | G1063: 2958000 | H1063: 3094000 | I1063: 3237000 | J1063: T6752
A1064: 688003 | B1064: 43410 | E1064: 662000 | F1064: 41000 | G1064: 43000 | H1064: 45000 | I1064: 47000 | J1064: T6752
... A1207: 649019 | B1207: 84310 | E1207: -51200 | F1207: -52400 | G1207: -53700 | H1207: 0 | I1207: 0 | J1207: T74
A1208: 649024 | B1208: 83800 | E1208: 0 | F1208: 0 | G1208: -600000 | H1208: -600000 | I1208: -600000 | J1208: T74
A1209: 649024 | B1209: 84310 | E1209: 0 | F1209: 0 | G1209: -400000 | H1209: -400000 | I1209: -400000 | J1209: T74
A1210: 650001 | B1210: 43812 | E1210: 2107 | F1210: 7809 | G1210: 8112 | H1210: 8438 | I1210: 8488 | J1210: T75
A1211: 650901 | B1211: 41100 | E1211: 1555 | F1211: 2943 | G1211: 3078 | H1211: 3220 | I1211: 3368 | J1211: T75
A1212: 650901 | B1212: 47300 | E1212: 2069 | F1212: 2069 | G1212: 2069 | H1212: 2069 | I1212: 2069 | J1212: T75
A1213: 650001 | B1213: 83700 | E1213: -4067 | F1213: -4067 | G1213: -4067 | H1213: -4063 | I1213: -4063 | J1213: T75
A1214: 651001 | B1214: 43804 | E1214: 96872 | F1214: 149391 | G1214: 151578 | H1214: 153813 | I1214: 156097 | J1214: T81
A1215: 651002 | B1215: 43511 | E1215: 57716 | F1215: 58870 | G1215: 61578 | H1215: 64411 | I1215: 67374 | J1215: T81
A1216: 651003 | B1216: 43511 | E1216: 200000 | F1216: 204300 | G1216: 212429 | H1216: 220982 | I1216: 229861 | J1216: T81
A1217: 651004 | B1217: 43812 | E1217: 16853 | F1217: 17291 | G1217: 17671 | H1217: 18060 | I1217: 18457 | J1217: T81
A1218: 651005 | B1218: 44380 | E1218: 31235 | F1218: 31527 | G1218: 31781 | H1218: 27040 | I1218: 27305 | J1218: T81
A1219: 651007 | B1219: 43100 | E1219: 1416143 | F1219: 1416143 | G1219: 0 | H1219: 0 | I1219: 0 | J1219: T81
A1220: 651007 | B1220: 43812 | E1220: 133432 | F1220: 58432 | G1220: 58432 | H1220: 58432 | I1220: 58432 | J1220: T81
A1221: 651008 | B1221: 43511 | E1221: 56447 | F1221: 357576 | G1221: 360224 | H1221: 362994 | I1221: 365892 | J1221: T81
... A1223: 651012 | B1223: 43812 | E1223: 0 | F1223: 100000 | G1223: 100000 | H1223: 100000 | I1223: 0 | J1223: T81
A1224: 651015 | B1224: 43812 | E1224: 0 | F1224: 50000 | G1224: 50000 | H1224: 0 | I1224: 0 | J1224: T81
A1225: 651901 | B1225: 41100 | E1225: 1430328.9 | F1225: 1408186.7 | G1225: 1358707 | H1225: 1604255 | I1225: 1678676 | J1225: T81
A1226: 651901 | B1226: 43812 | E1226: 3034 | F1226: 3100 | G1226: 3140 | H1226: 3262 | I1226: 3282 | J1226: T81
A1227: 651901 | B1227: 47300 | E1227: 0 | F1227: 0 | G1227: 16667 | H1227: 33334 | I1227: 50001 | J1227: T81
A1228: 651902 | B1228: 41100 | E1228: 152151.62 | F1228: 170945.85 | G1228: 178810 | H1228: 187036 | I1228: 195640 | J1228: T81
A1229: 651903 | B1229: 41100 | E1229: 320783 | F1229: 407289.67 | G1229: 426025 | H1229: 445622 | I1229: 466121 | J1229: T81
A1230: 651006 | B1230: 83700 | E1230: -17499 | F1230: -17954 | G1230: -18349 | H1230: -18753 | I1230: -19166 | J1230: T81
A1231: 651007 | B1231: 83100 | E1231: -1416143 | F1231: -1416143 | G1231: 0 | H1231: 0 | I1231: 0 | J1231: T81
A1232: 651007 | B1232: 83800 | E1232: -320783 | F1232: -407289.67 | G1232: -426025 | H1232: -445622 | I1232: -466121 | J1232: T81
A1233: 651007 | B1233: 83800 | E1233: -133432 | F1233: -58432 | G1233: -58432 | H1233: -58432 | I1233: -58432 | J1233: T81
A1234: 651008 | B1234: 83800 | E1234: -28224 | F1234: 0 | G1234: 0 | H1234: 0 | I1234: 0 | J1234: T81
A1235: 652008 | B1235: 43812 | E1235: 236570.76 | F1235: 258764.67 | G1235: 237805.08 | H1235: 148990.77 | I1235: 139392.96 | J1235: T82
A1236: 652008 | B1236: 43812 | E1236: 1570.9557 | F1236: 0 | G1236: 0 | H1236: 0 | I1236: 0 | J1236: T82
... A1321: 653006 | B1321: 83700 | E1321: -11235 | F1321: -11527 | G1321: -11781 | H1321: -12040 | I1321: -12305 | J1321: T83

Sheet draaitabel inlees CODA
A2: Element 3 | B2: (Alle)
A4: Rijlabels | B4: Som van 2026 | C4: Som van 2027 | D4: Som van 2028 | E4: Som van 2029
A5: 601001 | B5: 134315.79 | C5: 126874.96 | D5: 129491.96 | E5: 132164.88
A6: 601002 | B6: 23922 | C6: 24536 | D6: 25164 | E6: 25805
A7: 601003 | B7: 43712 | C7: 45231 | D7: 47118 | E7: 48879.5
A8: 601004 | B8: 70000 | C8: 71540 | D8: 73114 | E8: 74723
A9: 601005 | B9: 1728.6992 | C9: 1766.7306 | D9: 1805.5986 | E9: 1845.3218
A10: 601007 | B10: 0 | C10: 0 | D10: 0 | E10: 0
A11: 601008 | B11: 18740 | C11: 19152 | D11: 19574 | E11: 20003
A12: 601010 | B12: 35717 | C12: 36502 | D12: 37304 | E12: 38124
A13: 601011 | B13: 24153 | C13: 24684 | D13: 25227 | E13: 25782
A14: 601012 | B14: 321495 | C14: 340729 | D14: 357023 | E14: 377551.05
A15: 601013 | B15: 79636 | C15: 84595 | D15: 87532.6 | E15: 93374.148
A16: 601014 | B16: 29867 | C16: 31241 | D16: 32678 | E16: 34181
... A189: 617021 | B189: 72819 | C189: 72819 | D189: 72819 | E189: 259615
A190: 617023 | B190: 500000
A191: 617901 | B191: 1579483.8 | C191: 1866724 | D191: 2186933 | E191: 2508648
A192: 617902 | B192: 0 | C192: 0 | D192: 0 | E192: 0
A193: 617903 | B193: 14736 | C193: 15414 | D193: 16123 | E193: 16865
A194: 618001 | B194: 45653.891 | C194: 46729.393 | D194: 47828.242 | E194: 68955.896
A195: 618901 | B195: 31806 | C195: 31806 | D195: 31806 | E195: 81806
A196: 621001 | B196: 95236.3 | C196: 97339.4 | D196: 99489.48 | E196: 101685.54
A197: 621002 | B197: 1417 | C197: 1445 | D197: 1476 | E197: 1506
A198: 621901 | B198: 7452.51 | C198: 7565 | D198: 7683 | E198: 7806
A199: 622001 | B199: 1469 | C199: 1502 | D199: 1535 | E199: 1569
A200: 622003 | B200: 27830 | C200: 28451 | D200: 29077 | E200: 29707
A201: 622004 | B201: 0 | C201: 0 | D201: 0 | E201: 0.056814965
A202: 622005 | B202: 232833 | C202: 225443 | D202: 230403 | E202: 235472
... A513: 696001 | B513: 85000 | C513: 89000 | D513: 93000 | E513: 97000
A514: 635016 | B514: 337000 | C514: 0 | D514: 0 | E514: 0
A515: 649024 | B515: 0 | C515: -1000000 | D515: -1000000 | E515: -1000000
A516: 651015 | B516: 50000 | C516: 50000 | D516: 0 | E516: 0
A517: Eindtotaal | B517: -1700582.9 | C517: -1455914.4 | D517: 1142980.5 | E517: 887102.62
A520: Eindtotaal draaitabel | B520: -1700582.9 | C520: -1455914.4 | D520: 1142980.5 | E520: 887102.62
B521: -980246.6 | C521: -946399.04 | D521: -3851192.2 | E521: -4003624.4 | F521: t/m 28-8-2025
A523: Verwacht begrotingssaldo - start van de begroting | B523: -1003000 | C523: -873000 | D523: -4317000 | E523: -4931000
A524: Begrotingssaldo 2026-2029 | B524: 364489.35 | C524: 344581.87 | D524: -3873182.7 | E524: -4232187.2
A526: Verschil | B526: =B524-B523 -> 1367489.4 | C526: =C524-C523 -> 1217581.9 | D526: =D524-D523 -> 443817.33 | E526: =E524-E523 -> 698812.78
A527: Correctie reserves | B527: =-B561 -> -1460000 | C527: =-C561 -> -1737500 | D527: =-D561 -> 0 | E527: =-E561 -> 0
A528: Correctie rente | B528: 0 | C528: 300000 | D528: -150000 | E528: 450000
A529: Correctie lonen | B529: -325000 | C529: -325000 | D529: -325000 | E529: -325000
A530: Correctie inflatie | B530: -24489.351 | C530: -171081.87 | D530: 265182.67 | E530: 435187.22
A531: OZB | B531: -288000 | C531: -304000 | D531: -334000 | E531: -1384000 | G531: Afstemmen met Monique | I531: OZB | J531: -150000 | K531: -189000 | L531: -201000 | M531: 804000
A532: Correctie economie besparingsopdracht | B532: 60000 | C532: 60000 | D532: 60000 | E532: 60000
A533: Correctie besparing lokaal arbeidsvoorwaarden | B533: 50000 | C533: 50000 | D533: 50000 | E533: 50000
A534: Correctie WSD | B534: 30000 | C534: 60000 | D534: 80000 | E534: 105000
A535: Correctie inzet CDOKE (duurzaamheid) gelden | B535: 0 | C535: 0 | D535: -170000 | E535: -170000
A536: Correctie BIZOB | B536: 60000 | C536: 60000 | D536: 60000 | E536: 60000 | I536: Ondernemersfonds | J536: 251642 | K536: 283086 | L536: 307010 | M536: 332930
A537: Programma digitaal werken | B537: 500000 | C537: 500000 | D537: 0 | E537: 0 | J537: 186275 | K537: 209746 | L537: 227680 | M537: 247124
A538: Automatisering - indexering | B538: 15000 | C538: 15000 | D538: 15000 | E538: 15000 | J538: =SUM(J536:J537) -> 437917 | K538: =SUM(K536:K537) -> 492832 | L538: =SUM(L536:L537) -> 534690 | M538: =SUM(M536:M537) -> 580054
A539: Bibliotheek - indexering | B539: 20000 | C539: 20000 | D539: 20000 | E539: 20000 | I539: In 2025 meerjarig opgenomen | J539: 370000 | K539: 370000 | L539: 370000 | M539: 370000
A540: Onderhoud Groen - Indexering | B540: 15000 | C540: 15000 | D540: 15000 | E540: 15000 | J540: =+J538-J539 -> 67917 | K540: =+K538-K539 -> 122832 | L540: =+L538-L539 -> 164690 | M540: =+M538-M539 -> 210054
A541: Strategisch adviseur - staffunctie | B541: -120000 | C541: 120000 | D541: 0 | E541: 0
A542: Cultuur | B542: 15000 | C542: 15000 | D542: 15000 | E542: 15000
A543: Veiligheid | B543: 45000 | C543: 0 | D543: 0 | E543: 0
A544: Meubels | B544: 0 | C544: 5000 | D544: 5000 | E544: 5000
A545: Aanpassing bestaand beleid | B545: 40000 | C545: 100000 | D545: -50000 | E545: -50000 | I545: meer opbrengsten | J545: =J531+J538 -> 287917 | K545: =K531+K538 -> 303832 | L545: =L531+L538 -> 333690 | M545: =M531+M538 -> 1384054
B546: =SUM(B526:B545) -> 0 | C546: =SUM(C526:C545) -> 4.6566129e-10 | D546: =SUM(D526:D545) -> 2.3283064e-10 | E546: =SUM(E526:E545) -> -2.3283064e-10
A550: Inzet VAR | B550: 2026 | C550: 2027
A552: Begrotingssaldo 2026 | B552: =B521 -> -980246.6 | C552: =C521 -> -946399.04
A554: Best Oirschot (T01) | B554: ='T01'!K495 -> 210000 | C554: ='T01'!L495 -> 0
A555: Staffunctie Best Oirschot (T01) | B555: ='T01'!K517 -> 120000 | C555: ='T01'!L517 -> 120000
A556: Schaalsprong regionale opgave (T01) | B556: ='T01'!K521 -> 500000 | C556: ='T01'!L521 -> 500000
A557: Schaalsprong mobiliteit (T21) | B557: ='T21'!K651 -> 230000 | C557: ='T21'!L651 -> 655000
A558: Visie Dorpsplein | B558: 100000 | C558: 100000
A559: Actualisatie omgevingsvisie | B559: 50000 | C559: 50000
A560: Schaalsprong woningbouw (T83) | B560: ='T83'!K235 -> 250000 | C560: ='T83'!L235 -> 312500
B561: =SUM(B554:B560) -> 1460000 | C561: =SUM(C554:C560) -> 1737500
A563: Begrotingssaldo na inzet van de VAR | B563: =B552+B561 -> 479753.4 | C563: =C552+C561 -> 791100.96
B564: =B524 -> 364489.35 | C564: =C524 -> 344581.87
B565: =B563-B564 -> 115264.05 | C565: =C563-C564 -> 446519.09
A567: * Formatie mobiliteit schaalsprong en kapitaallasten niet meegenomen in de totalen van de schaalsprong.
A568: Afschrijving scheelt vormen van dekkingsreserve
A569: Formatie is waarschijnlijk structureel van aard in tegenstelling tot staffunctie.

Sheet draaitabel inlees CODA (2)
A2: Element 3 | B2: 41100
A4: Rijlabels | B4: Som van 2026
A5: 601901 | B5: 1503457.5
A6: T01 | B6: 1503457.5
A7: 601902 | B7: 172976.63
A8: T01 | B8: 172976.63
A9: 602901 | B9: 100258.11
A10: T02 | B10: 100258.11
A11: 602902 | B11: 118349.84
A12: T02 | B12: 118349.84
A13: 602903 | B13: 116735.24
A14: T02 | B14: 116735.24
A15: 602904 | B15: 119739.37
A16: T02 | B16: 119739.37
A17: 602905 | B17: 40461.45
A18: T02 | B18: 40461.45
A19: 602906 | B19: 169988.77
A20: T02 | B20: 169988.77
A21: 602907 | B21: 7848
A22: T02 | B22: 7848
A23: 603901 | B23: 158580.05
A24: T03 | B24: 158580.05
A25: 604002 | B25: 300000
A26: T04L | B26: 300000
A27: 604017 | B27: 31600
A28: T04B | B28: 31600
A29: 604901 | B29: 9058262
A30: T04L | B30: 9058262
A31: 605901 | B31: 0
A32: T05 | B32: 0
A33: 606901 | B33: 92269
A34: T061 | B34: 92269
A35: 607901 | B35: 77455
A36: T062 | B36: 77455
A37: 609901 | B37: 65986
A38: T064 | B38: 65986
A39: 611901 | B39: 0
A40: T08 | B40: 0
A41: 615901 | B41: 53449.78
A42: T11 | B42: 53449.78
A43: 616901 | B43: 113909.32
A44: T12 | B44: 113909.32
A45: 616902 | B45: 179523.23
A46: T12 | B46: 179523.23
A47: 616903 | B47: 1137843.8
A48: T12 | B48: 1137843.8
A49: 617901 | B49: 766253.83
A50: T21 | B50: 766253.83
A51: 617902 | B51: 0
A52: T21 | B52: 0
A53: 617903 | B53: 14736
A54: T21 | B54: 14736
A55: 618901 | B55: 0
A56: T22 | B56: 0
A57: 621901 | B57: 2452.51
A58: T25 | B58: 2452.51
A59: 622901 | B59: 196836.7
A60: T31 | B60: 196836.7
A61: 622902 | B61: 114331
A62: T31 | B62: 114331
A63: 624901 | B63: 32097
A64: T33 | B64: 32097
A65: 625901 | B65: 26011.08
A66: T34 | B66: 26011.08
A67: 625902 | B67: 154759
A68: T34 | B68: 154759
A69: 627901 | B69: 58898.64
A70: T42 | B70: 58898.64
A71: 628901 | B71: 303283.23
A72: T43 | B72: 303283.23
A73: 629901 | B73: 140596.75
A74: T51 | B74: 140596.75
A75: 630901 | B75: 683392.85
A76: T52 | B76: 683392.85
A77: 631901 | B77: 197752.58
A78: T53 | B78: 197752.58
A79: 633901 | B79: 62839.12
A80: T55 | B80: 62839.12
A81: 634901 | B81: 0
A82: T56 | B82: 0
A83: 635901 | B83: 863865.67
A84: T57 | B84: 863865.67
A85: 636901 | B85: 807384.23
A86: T61 | B86: 807384.23
A87: 638901 | B87: 1791856.9
A88: T63 | B88: 1791856.9
A89: 640901 | B89: 1242653
A90: T65 | B90: 1242653
A91: 646901 | B91: 37580.25
A92: T71 | B92: 37580.25
A93: 647901 | B93: 467723.04
A94: T72 | B94: 467723.04
A95: 648901 | B95: 239958.64
A96: T73 | B96: 239958.64
A97: 649018 | B97: 371992
A98: T74 | B98: 371992
A99: 649901 | B99: 0
A100: T74 | B100: 0
A101: 649902 | B101: 589800.71
A102: T74 | B102: 589800.71
...

Sheet afschrijvingen
A2: Rijlabels | B2: Som van 2026 | C2: Som van 2027 | D2: Som van 2028 | E2: Som van 2029
A3: 601901 | B3: 5000 | C3: 5000 | D3: 5000 | E3: 5000
A4: 603901 | B4: 39979 | C4: 28411 | D4: 28411 | E4: 28411
A5: 604045 | B5: 31559 | C5: 31559 | D5: 31559 | E5: 31559
A6: 604046 | B6: 0 | C6: 0 | D6: 0 | E6: 0
A7: 604048 | B7: 46895 | C7: 55121 | D7: 55121 | E7: 55121
A8: 604901 | B8: 443300 | C8: 684780 | D8: 657411 | E8: 628224
A9: 604902 | B9: -78454 | C9: -86680 | D9: -86680 | E9: -86680
A10: 605002 | B10: 0 | C10: 0 | D10: 0 | E10: 0
A11: 605901
A12: 615901 | B12: 11467 | C12: 29498 | D12: 29498 | E12: 29498
A13: 616903 | B13: 4519 | C13: 10000 | D13: 10000 | E13: 10000
A14: 617014 | B14: 0 | C14: 0 | D14: 0 | E14: 0
A15: 617016
A16: 617017 | B16: 0 | C16: 0 | D16: 0 | E16: 0
A17: 617018 | B17: 29812.42 | C17: 32938.42 | D17: 32938.42 | E17: 32938.42
A18: 617901 | B18: 813230 | C18: 1073107 | D18: 1364887 | E18: 1657064
A19: 617903 | B19: 0 | C19: 0 | D19: 0 | E19: 0
A20: 618901 | B20: 31806 | C20: 31806 | D20: 31806 | E20: 81806
A21: 621901 | B21: 5000 | C21: 5000 | D21: 5000 | E21: 5000
A22: 622901 | B22: 0 | C22: 0 | D22: 0 | E22: 0
A23: 627901 | B23: 1369938 | C23: 1366235 | D23: 2090360 | E23: 2203027
A24: 630022 | B24: 0 | C24: 0 | D24: 0 | E24: 0
A25: 630023 | B25: 22751.66 | C25: 25137.2 | D25: 25137.2 | E25: 25137.2
A26: 630901 | B26: 777187 | C26: 808687 | D26: 701859 | E26: 773169
A27: 634901 | B27: 98704 | C27: 98704 | D27: 98704 | E27: 98704
... A40: 688901 | B40: 235 | C40: 0 | D40: 0 | E40: 0
A41: Eindtotaal | B41: 4006425.9 | C41: 4936730 | D41: 5898764 | E41: 6428433
A43: Begroting 2025 | B43: 4202810 | C43: 4879877 | D43: 4972334
A45: verschil | B45: =GETPIVOTDATA("Som van 2026",'draaitabel inlees CODA'!$A$4)-B43 -> -5903392.9 | C45: =GETPIVOTDATA("Som van 2026",'draaitabel inlees CODA'!$A$4)-C43 -> -6580459.9 | D45: =GETPIVOTDATA("Som van 2026",'draaitabel inlees CODA'!$A$4)-D43 -> -6672916.9 | E45: =GETPIVOTDATA("Som van 2026",'draaitabel inlees CODA'!$A$4)-E43 -> -1700582.9
A47: nieuw beleid | B47: 0 | C47: =21334+13267+3533+28067+17600+5267+297334+16667+266667 -> 669736 | D47: =25000+21334+562400+13267+3533+5000+28067+17600+5267+297333+16667+16667+266667+83334 -> 1362136
A49: correctie in FF | B49: 235182 | C49: 714924 | D49: 384745
A51: restant | B51: =B43+B47-B41-B49 -> -38797.9 | C51: =C43+C47-C41-C49 -> -102041.02 | D51: =D43+D47-D41-D49 -> 50960.98 | E51: =E43+E47-E41-E49 -> -6428433
B54: =B41-B43 -> -196384.1

Sheet controle
A1: Rijlabels | B1: Som van 2026 | C1: Som van 2027 | D1: Som van 2028 | E1: Som van 2029 | F1: verschil 2028
A2: T01 | B2: 2947171.6 | C2: 2598568.7 | D2: 2709143.2 | E2: 2830665.9 | F2: =controle!D2-controle!C2 -> 110574.47
A3: T010 | B3: -4523443 | C3: -2757998 | D3: -2144788 | E3: -2265651 | F3: =controle!D3-controle!C3 -> 613210
A4: T011 | B4: 0 | C4: 0 | D4: 0 | E4: 0 | F4: =controle!D4-controle!C4 -> 0
A5: T02 | B5: 509576 | C5: 521878.63 | D5: 551790.56 | E5: 583844.87 | F5: =controle!D5-controle!C5 -> 29911.932
A6: T03 | B6: -41339.485 | C6: -50662.047 | D6: -48132.266 | E6: -45405.369 | F6: =controle!D6-controle!C6 -> 2529.7803
A7: T04B | B7: 2813365.7 | C7: 3097094.3 | D7: 3132756.8 | E7: 3169045.7 | F7: =controle!D7-controle!C7 -> 35662.43
A8: T04L | B8: 11319252 | C8: 11985724 | D8: 12471658 | E8: 13096449 | F8: =controle!D8-controle!C8 -> 485934.13
A9: T04W | B9: 2.0008883e-11 | C9: 0 | D9: -5.0931703e-11 | E9: 3.2741809e-11 | F9: =controle!D9-controle!C9 -> -5.0931703e-11
A10: T05 | B10: 81449.853 | C10: 220805.12 | D10: 372027.54 | E10: 367921.87 | F10: =controle!D10-controle!C10 -> 151222.43
A11: T061 | B11: -5487204.5 | C11: -6204408 | D11: -6795381 | E11: -7422117 | F11: =controle!D11-controle!C11 -> -590973
A12: T062 | B12: -3885527 | C12: -4383929 | D12: -4763146 | E12: -5175167 | F12: =controle!D12-controle!C12 -> -379217
A13: T064 | B13: -20300.492 | C13: -20383.379 | D13: -20439.337 | E13: -20340.279 | F13: =controle!D13-controle!C13 -> -55.958273
... A60: T83 | B60: 716424.48 | C60: 730021 | D60: 779681 | E60: 836333 | F60: =controle!D60-controle!C60 -> 49660
A61: Eindtotaal | B61: -1700582.9 | C61: -1455914.4 | D61: 1142980.5 | E61: 887102.62
A70: nieuw | B70: 2813365.7 | C70: 3097094.3 | D70: 3132756.8 | E70: 3169045.7
A71: oud | B71: 2966934 | C71: 2987781 | D71: 3038806
B72: =B70-B71 -> -153568.32 | C72: =C70-C71 -> 109313.34 | D72: =D70-D71 -> 93950.768 | E72: =E70-E71 -> 3169045.7

Sheet Details1
A1: Details voor Som van 2029 - Taakveld: T83
A3: Element 2 | B3: Element 3 | C3: Element 4 | D3: Element 5 | E3: 2025 | F3: 2026 | G3: 2027 | H3: 2028 | I3: 2029 | J3: Taakveld
A4: 653001 | B4: 43812 | E4: 22113 | F4: 22622 | G4: 23211 | H4: 23722 | I4: 24243 | J4: T83 | N4: 2025
A5: 653002 | B5: 43812 | E5: 50733 | F5: 52754 | G5: 53845 | H5: 56176 | I5: 58610 | J5: T83 | N5: =28300000 -> 28300000 | P5: =N5*2.2% -> 622600
A6: 653002 | B6: 43511 | E6: 31633 | F6: 32361 | G6: 33202 | H6: 33932 | I6: 34679 | J6: T83 | L6: 0.042 | M6: 2 | N6: -600000
A7: 653003 | B7: 43511 | E7: 144626 | F7: 147952 | G7: 151799 | H7: 155139 | I7: 158552 | J7: T83 | N7: 700000 | P7: KB 2026
A8: 653004 | B8: 43511 | E8: 39206 | F8: 40108 | G8: 41151 | H8: 42056 | I8: 42981 | J8: T83 | N8: -200000 | P8: Onderuitputting - besparing
A9: 653005 | B9: 83700 | E9: -1140000 | F9: -1140000 | G9: -1140000 | H9: -1140000 | I9: -1140000 | J9: T83 | N9: -100000 | P9: Verrekening opslag
A10: 653006 | B10: 83700 | E10: -11235 | F10: -11493 | G10: -11792 | H10: -12051 | I10: -12316 | J10: T83
A11: 653006 | B11: 43813 | E11: 17762 | F11: 18171 | G11: 18643 | H11: 19053 | I11: 19472 | J11: T83 | N11: -100000 | P11: PG
A12: 653007 | B12: 43812 | E12: 18947 | F12: 19383 | G12: 19887 | H12: 20325 | I12: 20772 | J12: T83 | N12: =SUM(N5:N11) -> 28000000
A13: 653008 | B13: 43812 | E13: 1184 | F13: 1211 | G13: 1242 | H13: 1269 | I13: 1297 | J13: T83
A14: 653009 | B14: 43511 | E14: 185914 | F14: 190190 | G14: 195135 | H14: 199428 | I14: 203815 | J14: T83
A15: 653010 | B15: 43511 | E15: 23683 | F15: 24228 | G15: 24858 | H15: 25405 | I15: 25964 | J15: T83
A16: 653011 | B16: 43511 | E16: 22237 | F16: 22748 | G16: 23339 | H16: 23852 | I16: 24377 | J16: T83
A17: 653012 | B17: 43812 | E17: 16340 | F17: 16716 | G17: 17151 | H17: 17528 | I17: 17914 | J17: T83
A18: 653013 | B18: 43812 | E18: 208023 | F18: 153831 | G18: 117319 | H18: 114899 | I18: 115514 | J18: T83
A19: 653014 | B19: 43511 | E19: 30700 | F19: 31400 | G19: 32200 | H19: 32200 | I19: 32200 | J19: T83
A20: 653901 | B20: 83800 | E20: -39323 | F20: -40227 | G20: -41273 | H20: -42181 | I20: -43109 | J20: T83
A21: 653901 | B21: 41100 | E21: 906685.85 | F21: 640300.9 | G21: 653107 | H21: 683150 | I21: 714575 | J21: T83
A22: 653902 | B22: 43812 | E22: 88426 | F22: 90515 | G22: 92867 | H22: 94887 | I22: 96944 | J22: T83
A23: 653902 | B23: 41100 | E23: 355295.08 | F23: 149055.58 | G23: 152037 | H23: 159031 | I23: 166346 | J23: T83

Sheet Inhoudsopgave 2
A1: Inhoudsopgave | B1: Pagina
A4: T01 bestuur en ondersteuning | B4: 1
A5: T02 burgerzaken | B5: 8
A6: T03 beheer overige gebouwen en gronden | B6: 19
A7: T04 bedrijf | B7: 24
A8: T04 loon | B8: 34
A9: T04 werf | B9: 48
A10: T05 Treasury | B10: 54
A11: T06 1 OZB Woningen | B11: 56
A12: T06 2 OZB Niet-Woningen | B12: 60
A13: T06 4 Belastingen overig | B13: 63
A14: T07 Gemeentefonds en overige rijksuitkeringen | B14: 65
A15: T08 Overige baten en lasten | B15: 68
... A76: T83 wonen en bouwen | B76: 261

Sheet Indexering
D1: 2021 | E1: 2022 | F1: 2023 | G1: 2024 | H1: 2025 | I1: 2026 | J1: 2027 | K1: 2028 | L1: 2029 | M1: 2030
J2: Hoofdjaar | K2: Hoofdjaar +1 | L2: Hoofdjaar +2 | M2: Hoofdjaar +3
B4: Prijsindex | D4: 1.015 | E4: 1.014 | F4: 1.024 | G4: 1.037 | H4: 1.028 | I4: 1.026 | J4: 1.021 | K4: 1.023 | L4: 1.023 | M4: 1.023
B5: Loonindex | D5: 1.031 | E5: 1.015 | F5: 1.046 | G5: 1.052 | H5: 1.049 | I5: 1.02 | J5: 1.042 | K5: 1.037 | L5: 1.037 | M5: 1.037
E6: =+(E4+E5)/2 -> 1.0145 | F6: =+(F4+F5)/2 -> 1.035 | G6: =+(G4+G5)/2 -> 1.0445 | H6: 1.036 | I6: =+I13 -> 1.02282 | J6: =+J13 -> 1.03213 | K6: =+K13 -> 1.03042 | L6: =+L13 -> 1.03042 | M6: =+M13 -> 1.03042
B7: Sociaal domein loonindex | J7: 1.042 | K7: 1.042 | L7: 1.042 | M7: 1.042
I8: =+H6-I6 -> 0.01318
F11: =+H4*0.47 -> 0.48316 | I11: =+I4*0.47 -> 0.48222 | J11: =+J4*0.47 -> 0.47987 | K11: =+K4*0.47 -> 0.48081 | L11: =+L4*0.47 -> 0.48081 | M11: =+M4*0.47 -> 0.48081
F12: =+H5*0.53 -> 0.55597 | I12: =+I5*0.53 -> 0.5406 | J12: =+J5*0.53 -> 0.55226 | K12: =+K5*0.53 -> 0.54961 | L12: =+L5*0.53 -> 0.54961 | M12: =+M5*0.53 -> 0.54961
F13: =+F11+F12 -> 1.03913 | I13: =+I11+I12 -> 1.02282 | J13: =+J11+J12 -> 1.03213 | K13: =+K11+K12 -> 1.03042 | L13: =+L11+L12 -> 1.03042 | M13: =+M11+M12 -> 1.03042
H16: Index conform kaderbrief
H18: 1.028 | I18: 1.023 | J18: 1.023 | K18: 1.023
H19: 1.049 | I19: 1.042 | J19: 1.042 | K19: 1.042
H20: 1.036 | I20: 1.0325 | J20: 1.0325 | K20: 1.0325

Sheet Verwerkingscontrole
F1: Primitieve begroting | L1: Gewijzigde begroting (recap) | P1: Mutaties | U1: Toelichting
A3: Taakveld | C3: Omschrijving | E3: 2025 | F3: 2026 | G3: 2027 | H3: 2028 | K3: 2025 | L3: 2026 | M3: 2027 | N3: 2028 | P3: 2025 | Q3: 2026 | R3: 2027 | S3: 2028 | V3: 2025 | W3: 2026 | X3: 2027 | Y3: 2028
A4: T01 bestuur en ondersteuning.xlsx | B4: T01 | C4: Bestuur | D4: L | E4: 2638500.7 | F4: 2646582.3 | G4: 2757419.5 | H4: 2865885.4 | J4: L | K4: =Recap!#REF! -> #REF! | L4: =Recap!E3 -> 4096256.6 | M4: =Recap!F3 -> 3519006 | N4: =Recap!G3 -> 3429319.8 | P4: =K4-E4 -> #REF! | Q4: =L4-F4 -> 1449674.3 | R4: =M4-G4 -> 761586.56 | S4: =N4-H4 -> 563434.38 | U4: W01-2025 | V4: 100000
U5: W02-2025 | V5: 10000 | W5: 10000 | X5: 10000 | Y5: 10000
U6: W02-2025 | V6: 4000 | W6: 14000 | X6: 4000 | Y6: 4000
A7: T02 burgerzaken.xlsx | B7: T02 | C7: Burgerzaken | D7: L | E7: 1150625.5 | F7: 1229061.5 | G7: 1290202.9 | H7: 1332894.2 | J7: L | K7: =Recap!#REF! -> #REF! | L7: =Recap!E4 -> 1279045.3 | M7: =Recap!F4 -> 1306068.9 | N7: =Recap!G4 -> 1349138.8 | P7: =K7-E7 -> #REF! | Q7: =L7-F7 -> 49983.764 | R7: =M7-G7 -> 15866.046 | S7: =N7-H7 -> 16244.526 | U7: W02-2025 | V7: 10400
A8: T03 beheer overige gebouwen en gronden.xlsx | B8: T03 | C8: Beheer overige gebouwen en gronden | D8: L | E8: 349018 | F8: 307885 | G8: 305512 | H8: 315036 | J8: L | K8: =Recap!#REF! -> #REF! | L8: =Recap!E5 -> 653245.52 | M8: =Recap!F5 -> 339365.95 | N8: =Recap!G5 -> 348755.73 | P8: =K8-E8 -> #REF! | Q8: =L8-F8 -> 345360.52 | R8: =M8-G8 -> 33853.953 | S8: =N8-H8 -> 33719.734
A9: T04 bedrijf.xlsx | B9: T04B | C9: Overhead - 1 bedrijfsvoering | D9: L | E9: 3036473.8 | F9: 2975494.8 | G9: 2996539.2 | H9: 3047765.1 | J9: L | K9: =Recap!#REF! -> #REF! | L9: =Recap!E6 -> 3325272.6 | M9: =Recap!F6 -> 3607658.3 | N9: =Recap!G6 -> 3180175.8 | P9: =K9-E9 -> #REF! | Q9: =L9-F9 -> 349777.72 | R9: =M9-G9 -> 611119.18 | S9: =N9-H9 -> 132410.73
A10: T04 loon.xlsx | B10: T04L | C10: Overhead - 2 loonkosten | D10: L | E10: 11485863 | F10: 11835935 | G10: 12250280 | H10: 12855626 | J10: L | K10: =Recap!#REF! -> #REF! | L10: =Recap!E7 -> 11367751 | M10: =Recap!F7 -> 11709325 | N10: =Recap!G7 -> 12465644 | P10: =K10-E10 -> #REF! | Q10: =L10-F10 -> -468184.28 | R10: =M10-G10 -> -540955.4 | S10: =N10-H10 -> -389981.58
A11: T04 werf.xlsx | B11: T04W | C11: Overhead - 3 werf en vervoermiddelen | D11: L | E11: 0 | F11: 0 | G11: 0 | H11: 0 | J11: L | K11: =Recap!#REF! -> #REF! | L11: =Recap!E8 -> 0 | M11: =Recap!F8 -> 0 | N11: =Recap!G8 -> 0 | P11: =K11-E11 -> #REF! | Q11: =L11-F11 -> 0 | R11: =M11-G11 -> 0 | S11: =N11-H11 -> 0
A12: T05 Treasury.xlsx | B12: T05 | C12: Treasury | D12: L | E12: 61245 | F12: 92483 | G12: 266627 | H12: 439206 | J12: L | K12: =Recap!#REF! -> #REF! | L12: =Recap!E9 -> 204771 | M12: =Recap!F9 -> 629078 | N12: =Recap!G9 -> 1083905 | P12: =K12-E12 -> #REF! | Q12: =L12-F12 -> 112288 | R12: =M12-G12 -> 362451 | S12: =N12-H12 -> 644699
A13: T06 1 OZB Woningen.xlsx | B13: T061 | C13: OZB Woningen | D13: L | E13: 179046 | F13: 185090 | G13: 191357 | H13: 197851 | J13: L | K13: =Recap!#REF! -> #REF! | L13: =Recap!E10 -> 172088 | M13: =Recap!F10 -> 177644 | N13: =Recap!G10 -> 183043 | P13: =K13-E13 -> #REF! | Q13: =L13-F13 -> -13002 | R13: =M13-G13 -> -13713 | S13: =N13-H13 -> -14808
A14: T06 2 OZB Niet-Woningen.xlsx | B14: T062 | C14: OZB Niet woningen | D14: L | E14: 138814 | F14: 143662 | G14: 148690 | H14: 153907 | J14: L | K14: =Recap!#REF! -> #REF! | L14: =Recap!E11 -> 130667 | M14: =Recap!F11 -> 135042 | N14: =Recap!G11 -> 139255 | P14: =K14-E14 -> #REF! | Q14: =L14-F14 -> -12995 | R14: =M14-G14 -> -13648 | S14: =N14-H14 -> -14652
A15: T06 4 Belastingen overig.xlsx | B15: T064 | C15: Belastingen overig | D15: L | E15: 63955 | F15: 66641 | G15: 69440 | H15: 72356 | J15: L | K15: =Recap!#REF! -> #REF! | L15: =Recap!E12 -> 65986 | M15: =Recap!F12 -> 68757 | N15: =Recap!G12 -> 71301 | P15: =K15-E15 -> #REF! | Q15: =L15-F15 -> -655 | R15: =M15-G15 -> -683 | S15: =N15-H15 -> -1055
A16: T07 Gemeentefonds en overige rijksuitkeringen.xlsx | B16: T07 | C16: Alg. uitkeringen en ov uitkeringen gemeentefonds | D16: L | E16: 5645 | F16: 5775 | G16: 5908 | H16: 6044 | J16: L | K16: =Recap!#REF! -> #REF! | L16: =Recap!E13 -> 5780 | M16: =Recap!F13 -> 5901 | N16: =Recap!G13 -> 6037 | P16: =K16-E16 -> #REF! | Q16: =L16-F16 -> 5 | R16: =M16-G16 -> -7 | S16: =N16-H16 -> -7
A17: T08 Overige baten en lasten.xlsx | B17: T08 | C17: Overige baten en lasten | D17: L | E17: 207972 | F17: 230693 | G17: 234994 | H17: 239394 | J17: L | K17: =Recap!#REF! -> #REF! | L17: =Recap!E14 -> 594431.35 | M17: =Recap!F14 -> 233854 | N17: =Recap!G14 -> 238228 | P17: =K17-E17 -> #REF! | Q17: =L17-F17 -> 363738.35 | R17: =M17-G17 -> -1140 | S17: =N17-H17 -> -1166 | U17: W01-2025 | V17: 120000 | W17: 123000 | X17: 127000 | Y17: 130000
A18: T09 Vennootschapsbelasting.xlsx | B18: T09 | C18: Vennootschapsbelasting | D18: L | E18: 0 | F18: 5000 | G18: 5000 | H18: 5000 | J18: L | K18: =Recap!#REF! -> #REF! | L18: =Recap!E15 -> 11400 | M18: =Recap!F15 -> 11400 | N18: =Recap!G15 -> 11400 | P18: =K18-E18 -> #REF! | Q18: =L18-F18 -> 6400 | R18: =M18-G18 -> 6400 | S18: =N18-H18 -> 6400
A19: T010 Mutaties Reserve.xlsx | B19: T010 | C19: Mutaties reserves | D19: L | E19: 423871 | F19: 336578 | G19: 336288 | H19: 335987 | J19: L | K19: =Recap!#REF! -> #REF! | L19: =Recap!E16 -> 905588 | M19: =Recap!F16 -> 471829 | N19: =Recap!G16 -> 438368 | P19: =K19-E19 -> #REF! | Q19: =L19-F19 -> 569010 | R19: =M19-G19 -> 135541 | S19: =N19-H19 -> 102381
A20: T011 Resultaat rekening baten en lasten.xlsx | B20: T011 | C20: Resultaat van de rekening van baten en lasten | D20: L | E20: 0 | F20: 0 | G20: 0 | H20: 2 | J20: L | K20: =Recap!#REF! -> #REF! | L20: =Recap!E17 -> 0 | M20: =Recap!F17 -> 0 | N20: =Recap!G17 -> 0 | P20: =K20-E20 -> #REF! | Q20: =L20-F20 -> 0 | R20: =M20-G20 -> 0 | S20: =N20-H20 -> -2
A21: T11 crisisbeheersing en brandweer.xlsx | B21: T11 | C21: Crisisbeheersing en brandweer | D21: L | E21: 1964601 | F21: 2046117 | G21: 2134352 | H21: 2222835 | J21: L | K21: =Recap!#REF! -> #REF! | L21: =Recap!E18 -> 2088526.5 | M21: =Recap!F18 -> 2264477.9 | N21: =Recap!G18 -> 2326060.9 | P21: =K21-E21 -> #REF! | Q21: =L21-F21 -> 42409.532 | R21: =M21-G21 -> 130125.94 | S21: =N21-H21 -> 103225.85
A22: T12 openbare orde en veiligheid.xlsx | B22: T12 | C22: Openbare orde en veiligheid | D22: L | E22: 1679340.3 | F22: 1746066.9 | G22: 1797877.9 | H22: 1868557.8 | J22: L | K22: =Recap!#REF! -> #REF! | L22: =Recap!E19 -> 2005361.2 | M22: =Recap!F19 -> 1932160.2 | N22: =Recap!G19 -> 1999201.4 | P22: =K22-E22 -> #REF! | Q22: =L22-F22 -> 259294.27 | R22: =M22-G22 -> 134282.37 | S22: =N22-H22 -> 130643.63
A23: T21 Verkeer en vervoer.xlsx | B23: T21 | C23: Verkeer en vervoer | D23: L | E23: 3624954.3 | F23: 3837871.7 | G23: 4166670.5 | H23: 4361801.4 | J23: L | K23: =Recap!#REF! -> #REF! | L23: =Recap!E20 -> 4152536.9 | M23: =Recap!F20 -> 4859110.9 | N23: =Recap!G20 -> 5275649.8 | P23: =K23-E23 -> #REF! | Q23: =L23-F23 -> 314665.18 | R23: =M23-G23 -> 692440.46 | S23: =N23-H23 -> 913848.35
A24: T22 parkeren.xlsx | B24: T22 | C24: Parkeren | D24: L | E24: 88269.931 | F24: 89637.833 | G24: 91040.353 | H24: 92477.233 | J24: L | K24: =Recap!#REF! -> #REF! | L24: =Recap!E21 -> 89294.891 | M24: =Recap!F21 -> 90577.142 | N24: =Recap!G21 -> 91996.267 | P24: =K24-E24 -> #REF! | Q24: =L24-F24 -> -342.94146 | R24: =M24-G24 -> -463.21053 | S24: =N24-H24 -> -480.96587
A25: T25 openbaar vervoer.xlsx | B25: T25 | C25: Openbaar vervoer | D25: L | E25: 78581.49 | F25: 80320 | G25: 82101 | H25: 83927 | J25: L | K25: =Recap!#REF! -> #REF! | L25: =Recap!E22 -> 99454.81 | M25: =Recap!F22 -> 101593.02 | N25: =Recap!G22 -> 103963.27 | P25: =K25-E25 -> #REF! | Q25: =L25-F25 -> 19134.81 | R25: =M25-G25 -> 19492.02 | S25: =N25-H25 -> 20036.27
A26: T31 economische ontwikkeling.xlsx | B26: T31 | C26: Economische ontwikkeling | D26: L | E26: 869239.44 | F26: 895173.69 | G26: 910956.14 | H26: 939885.72 | J26: L | K26: =Recap!#REF! -> #REF! | L26: =Recap!E23 -> 1355577.6 | M26: =Recap!F23 -> 1122696.5 | N26: =Recap!G23 -> 1152490.1 | P26: =K26-E26 -> #REF! | Q26: =L26-F26 -> 460403.87 | R26: =M26-G26 -> 211740.39 | S26: =N26-H26 -> 212604.39
A27: T33 bedrijfsloket en bedrijfsregelingen.xlsx | B27: T33 | C27: Bedrijvenloket en bedrijvenregeling | D27: L | E27: 37083.62 | F27: 38417.024 | G27: 39801.504 | H27: 41241.464 | J27: L | K27: =Recap!#REF! -> #REF! | L27: =Recap!E24 -> 41976.024 | M27: =Recap!F24 -> 43502.504 | N27: =Recap!G24 -> 44931.464 | P27: =K27-E27 -> #REF! | Q27: =L27-F27 -> 3559 | R27: =M27-G27 -> 3701 | S27: =N27-H27 -> 3690
A28: T34 economische promotie.xlsx | B28: T34 | C28: Economische promotie | D28: L | E28: 476690.77 | F28: 484795.75 | G28: 493218.76 | H28: 502008.59 | J28: L | K28: =Recap!#REF! -> #REF! | L28: =Recap!E25 -> 517402.83 | M28: =Recap!F25 -> 526952.76 | N28: =Recap!G25 -> 536047.59 | P28: =K28-E28 -> #REF! | Q28: =L28-F28 -> 32607.08 | R28: =M28-G28 -> 33734 | S28: =N28-H28 -> 34039
A29: T42 onderwijshuisvesting.xlsx | B29: T42 | C29: Onderwijshuisvesting | D29: L | E29: 958258.62 | F29: 1742768.6 | G29: 2235701.1 | H29: 2360346.3 | J29: L | K29: =Recap!#REF! -> #REF! | L29: =Recap!E26 -> 1735325.4 | M29: =Recap!F26 -> 1740867.3 | N29: =Recap!G26 -> 3159300.5 | P29: =K29-E29 -> #REF! | Q29: =L29-F29 -> -7443.1948 | R29: =M29-G29 -> -494833.83 | S29: =N29-H29 -> 798954.18
A30: T43 onderwijsbeleid en leerlingenzaken.xlsx | B30: T43 | C30: Onderwijsbeleid en leerlingenzaken | D30: L | E30: 1779281.4 | F30: 1823915 | G30: 1870313 | H30: 1919495 | J30: L | K30: =Recap!#REF! -> #REF! | L30: =Recap!E27 -> 1829738.2 | M30: =Recap!F27 -> 1882242 | N30: =Recap!G27 -> 1908620 | P30: =K30-E30 -> #REF! | Q30: =L30-F30 -> 5823.23 | R30: =M30-G30 -> 11929 | S30: =N30-H30 -> -10875 | U30: W01-2025 | V30: 8160 | W30: 8261 | X30: 8629 | Y30: 9021
A31: T51 Sportbeleid en activering.xlsx | B31: T51 | C31: Sportbeleid en activering | D31: L | E31: 548740.44 | F31: 549642 | G31: 559951 | H31: 570664 | J31: L | K31: =Recap!#REF! -> #REF! | L31: =Recap!E28 -> 689486.75 | M31: =Recap!F28 -> 684695 | N31: =Recap!G28 -> 695336 | P31: =K31-E31 -> #REF! | Q31: =L31-F31 -> 139844.75 | R31: =M31-G31 -> 124744 | S31: =N31-H31 -> 124672
A32: T52 Sportaccommodaties.xlsx | B32: T52 | C32: Sportaccommodaties | D32: L | E32: 2458176.2 | F32: 2507208.6 | G32: 2525720.8 | H32: 2479547.6 | J32: L | K32: =Recap!#REF! -> #REF! | L32: =Recap!E29 -> 2533362.2 | M32: =Recap!F29 -> 2615409 | N32: =Recap!G29 -> 2576630 | P32: =K32-E32 -> #REF! | Q32: =L32-F32 -> 26153.567 | R32: =M32-G32 -> 89688.198 | S32: =N32-H32 -> 97082.449
A33: T53 cultuurpresentatie,product,particip.xlsx | B33: T53 | C33: Cultuurproductie, presentatie en participatie | D33: L | E33: 899113.44 | F33: 932400.57 | G33: 950482.02 | H33: 985712.81 | J33: L | K33: =Recap!#REF! -> #REF! | L33: =Recap!E30 -> 886151.49 | M33: =Recap!F30 -> 840851.77 | N33: =Recap!G30 -> 871065.5 | P33: =K33-E33 -> #REF! | Q33: =L33-F33 -> -46249.078 | R33: =M33-G33 -> -109630.26 | S33: =N33-H33 -> -114647.31
A34: T54 Musea.xlsx | B34: T54 | C34: Musea | D34: L | E34: 129097 | F34: 134519 | G34: 140169 | H34: 146056 | J34: L | K34: =Recap!#REF! -> #REF! | L34: =Recap!E31 -> 134868 | M34: =Recap!F31 -> 140533 | N34: =Recap!G31 -> 145733 | P34: =K34-E34 -> #REF! | Q34: =L34-F34 -> 349 | R34: =M34-G34 -> 364 | S34: =N34-H34 -> -323
A35: T55 Cultureel erfgoed.xlsx | B35: T55 | C35: Cultureel erfgoed | D35: L | E35: 164125 | F35: 168781 | G35: 173579 | H35: 178525 | J35: L | K35: =Recap!#REF! -> #REF! | L35: =Recap!E32 -> 183726.12 | M35: =Recap!F32 -> 188904 | N35: =Recap!G32 -> 194166 | P35: =K35-E35 -> #REF! | Q35: =L35-F35 -> 14945.12 | R35: =M35-G35 -> 15325 | S35: =N35-H35 -> 15641
A36: T56 Media.xlsx | B36: T56 | C36: Media | D36: L | E36: 864942.48 | F36: 895029.96 | G36: 926371.59 | H36: 959024.14 | J36: L | K36: =Recap!#REF! -> #REF! | L36: =Recap!E33 -> 1007683.7 | M36: =Recap!F33 -> 949093.35 | N36: =Recap!G33 -> 964852.89 | P36: =K36-E36 -> #REF! | Q36: =L36-F36 -> 112653.77 | R36: =M36-G36 -> 22721.761 | S36: =N36-H36 -> 5828.7521 | U36: W01-2025 | V36: 100000 | W36: 100000
A37: T57 openbaar groen,(openlucht) recreatie.xlsx | B37: T57 | C37: Openbaar groen en (openlucht) recreatie | D37: L | E37: 3025219.6 | F37: 3198338.7 | G37: 3351719.5 | H37: 3393401 | J37: L | K37: =Recap!#REF! -> #REF! | L37: =Recap!E34 -> 3759810.8 | M37: =Recap!F34 -> 3514527.3 | N37: =Recap!G34 -> 3617129.2 | P37: =K37-E37 -> #REF! | Q37: =L37-F37 -> 561472.16 | R37: =M37-G37 -> 162807.78 | S37: =N37-H37 -> 223728.23
A38: T61 samenkracht en burgerparticipatie.xlsx | B38: T61 | C38: Samenkracht en burgerparticipatie | D38: L | E38: 3173329 | F38: 3238292 | G38: 3354555 | H38: 3475577 | J38: L | K38: =Recap!#REF! -> #REF! | L38: =Recap!E35 -> 4909998.1 | M38: =Recap!F35 -> 3579688.2 | N38: =Recap!G35 -> 3705656.9 | P38: =K38-E38 -> #REF! | Q38: =L38-F38 -> 1671706.1 | R38: =M38-G38 -> 225133.25 | S38: =N38-H38 -> 230079.92
A39: T62 2 toegang en eerstelijnsvoorzieningen Jeugd.xlsx | B39: T622 | C39: Toegang en eerstelijnsvoorzieningen jeugd | D39: L | E39: 1379590 | F39: 1435560 | G39: 1493810 | H39: 1554470 | J39: L | K39: =Recap!#REF! -> #REF! | L39: =Recap!E36 -> #REF! | M39: =Recap!F36 -> #REF! | N39: =Recap!G36 -> #REF! | P39: =K39-E39 -> #REF! | Q39: =L39-F39 -> #REF! | R39: =M39-G39 -> #REF! | S39: =N39-H39 -> #REF!
A40: T62 3 toegang en eerstelijnsvoorzieningen Integraal.xlsx | B40: T623 | C40: Toegang en eerstelijnsvoorzieningen integraal | D40: L | E40: 1992298 | F40: 2072186 | G40: 2155292 | H40: 2216718 | J40: L | K40: =Recap!#REF! -> #REF! | L40: =Recap!E37 -> #REF! | M40: =Recap!F37 -> #REF! | N40: =Recap!G37 -> #REF! | P40: =K40-E40 -> #REF! | Q40: =L40-F40 -> #REF! | R40: =M40-G40 -> #REF! | S40: =N40-H40 -> #REF!
A41: T63 inkomensregelingen.xlsx | B41: T63 | C41: Inkomensregelingen | D41: L | E41: 9531583.8 | F41: 9605131 | G41: 9595897 | H41: 9674473 | J41: L | K41: =Recap!#REF! -> #REF! | L41: =Recap!E38 -> 11332734 | M41: =Recap!F38 -> 10727447 | N41: =Recap!G38 -> 10709251 | P41: =K41-E41 -> #REF! | Q41: =L41-F41 -> 1727602.9 | R41: =M41-G41 -> 1131550 | S41: =N41-H41 -> 1034778
A42: T64 begeleide participatie.xlsx | B42: T64 | C42: WSW en beschut werk | D42: L | E42: 3335675 | F42: 3251506 | G42: 3095304 | H42: 2951231 | J42: L | K42: =Recap!#REF! -> #REF! | L42: =Recap!E39 -> #REF! | M42: =Recap!F39 -> #REF! | N42: =Recap!G39 -> #REF! | P42: =K42-E42 -> #REF! | Q42: =L42-F42 -> #REF! | R42: =M42-G42 -> #REF! | S42: =N42-H42 -> #REF! | U42: W01-2025 | V42: 24560 | W42: 23902 | X42: 22705 | Y42: 21593
A43: T65 arbeidsparticipatie.xlsx | B43: T65 | C43: Arbeidsparticipatie | D43: L | E43: 1887054 | F43: 1956621 | G43: 2019999 | H43: 2088504 | J43: L | K43: =Recap!#REF! -> #REF! | L43: =Recap!E40 -> 2733683 | M43: =Recap!F40 -> 2265920 | N43: =Recap!G40 -> 2295116 | P43: =K43-E43 -> #REF! | Q43: =L43-F43 -> 777061.98 | R43: =M43-G43 -> 245921 | S43: =N43-H43 -> 206612 | U43: W01-2025 | V43: 9769 | W43: 10467 | X43: 11163 | Y43: 11859
A44: T66 0 hulpmiddelen en diensten (Wmo).xlsx | B44: T660 | C44: Hulpmiddelen en diensten (WMO) | D44: L | E44: 1471559 | F44: 1505612 | G44: 1428082 | H44: 1468890 | J44: L | K44: =Recap!#REF! -> #REF! | L44: =Recap!E41 -> #REF! | M44: =Recap!F41 -> #REF! | N44: =Recap!G41 -> #REF! | P44: =K44-E44 -> #REF! | Q44: =L44-F44 -> #REF! | R44: =M44-G44 -> #REF! | S44: =N44-H44 -> #REF!
A45: T67 11 Huishoudelijke hulp (Wmo).xlsx | B45: T6711 | C45: Huishoudelijke hulp (WMO) | D45: L | E45: 2337300 | F45: 2435500 | G45: 2537800 | H45: 2644400 | J45: L | K45: =Recap!#REF! -> #REF! | L45: =Recap!E42 -> #REF! | M45: =Recap!F42 -> #REF! | N45: =Recap!G42 -> #REF! | P45: =K45-E45 -> #REF! | Q45: =L45-F45 -> #REF! | R45: =M45-G45 -> #REF! | S45: =N45-H45 -> #REF!
A46: T67 12 Begeleiding (Wmo).xlsx | B46: T6712 | C46: Begeleiding (WMO) | D46: L | E46: 2899734 | F46: 3009527 | G46: 3127109 | H46: 3248708 | J46: L | K46: =Recap!#REF! -> #REF! | L46: =Recap!E43 -> #REF! | M46: =Recap!F43 -> #REF! | N46: =Recap!G43 -> #REF! | P46: =K46-E46 -> #REF! | Q46: =L46-F46 -> #REF! | R46: =M46-G46 -> #REF! | S46: =N46-H46 -> #REF! | U46: W01-2025 | W46: 100000 | X46: 205000 | Y46: 313000
A47: T67 13 dagbesteding (Wmo).xlsx | B47: T6713 | C47: Dagbesteding (WMO) | D47: L | E47: 662200 | F47: 690000 | G47: 719000 | H47: 749200 | J47: L | K47: =Recap!#REF! -> #REF! | L47: =Recap!E44 -> #REF! | M47: =Recap!F44 -> #REF! | N47: =Recap!G44 -> #REF! | P47: =K47-E47 -> #REF! | Q47: =L47-F47 -> #REF! | R47: =M47-G47 -> #REF! | S47: =N47-H47 -> #REF!
A48: T67 14 overige maatwerkarrangementen (Wmo).xlsx | B48: T6714 | C48: Overige maatwerkarrangementen (WMO) | D48: L | E48: 60700 | F48: 63200 | G48: 65900 | H48: 68700 | J48: L | K48: =Recap!#REF! -> #REF! | L48: =Recap!E45 -> #REF! | M48: =Recap!F45 -> #REF! | N48: =Recap!G45 -> #REF! | P48: =K48-E48 -> #REF! | Q48: =L48-F48 -> #REF! | R48: =M48-G48 -> #REF! | S48: =N48-H48 -> #REF!
A49: T67 52 jeugdhulp ambulant regionaal.xlsx | B49: T6752 | C49: Jeugdhulp ambulant regionaal | D49: L | E49: 5723634 | F49: 4492903 | G49: 4618779 | H49: 4671205 | J49: L | K49: =Recap!#REF! -> #REF! | L49: =Recap!E46 -> #REF! | M49: =Recap!F46 -> #REF! | N49: =Recap!G46 -> #REF! | P49: =K49-E49 -> #REF! | Q49: =L49-F49 -> #REF! | R49: =M49-G49 -> #REF! | S49: =N49-H49 -> #REF! | U49: W01-2025 | W49: 694000 | X49: 721000 | Y49: 785000
A50: T67 62 jeugdhulp met verblijf regionaal.xlsx | B50: T6762 | C50: Jeugdhulp met verblijf regionaal | D50: L | E50: 1937000 | F50: 2019000 | G50: 2103000 | H50: 2191000 | J50: L | K50: =Recap!#REF! -> #REF! | L50: =Recap!E47 -> #REF! | M50: =Recap!F47 -> #REF! | N50: =Recap!G47 -> #REF! | P50: =K50-E50 -> #REF! | Q50: =L50-F50 -> #REF! | R50: =M50-G50 -> #REF! | S50: =N50-H50 -> #REF!
A51: T68 21 jeugdbescherming.xlsx | B51: T6821 | C51: Jeugdbescherming | D51: L | E51: 596000 | F51: 621000 | G51: 647000 | H51: 674000 | J51: L | K51: =Recap!#REF! -> #REF! | L51: =Recap!E50 -> #REF! | M51: =Recap!F50 -> #REF! | N51: =Recap!G50 -> #REF! | P51: =K51-E51 -> #REF! | Q51: =L51-F51 -> #REF! | R51: =M51-G51 -> #REF! | S51: =N51-H51 -> #REF!
A52: T68 22 jeugdreclassering.xlsx | B52: T6822 | C52: Jeugdreclassering | D52: L | E52: 56000 | F52: 58000 | G52: 60000 | H52: 63000 | J52: L | K52: =Recap!#REF! -> #REF! | L52: =Recap!E51 -> #REF! | M52: =Recap!F51 -> #REF! | N52: =Recap!G51 -> #REF! | P52: =K52-E52 -> #REF! | Q52: =L52-F52 -> #REF! | R52: =M52-G52 -> #REF! | S52: =N52-H52 -> #REF!
A53: T69 1 Coördinatie en beleid Wmo.xlsx | B53: T691 | C53: Coordinatie en beleid WMO | D53: L | E53: 718676.59 | F53: 748861.01 | G53: 780313.17 | H53: 813086.32 | J53: L | K53: =Recap!#REF! -> #REF! | L53: =Recap!E52 -> 1051284.9 | M53: =Recap!F52 -> 976024.9 | N53: =Recap!G52 -> 1012137.4 | P53: =K53-E53 -> #REF! | Q53: =L53-F53 -> 302423.86 | R53: =M53-G53 -> 195711.73 | S53: =N53-H53 -> 199051.12
A54: T69 2 Coördinatie en beleid Jeugd.xlsx | B54: T692 | C54: Coordinatie en beleid jeugd | D54: L | E54: 543758.83 | F54: 566596 | G54: 590393 | H54: 615189 | J54: L | K54: =Recap!#REF! -> #REF! | L54: =Recap!E53 -> 1851945.8 | M54: =Recap!F53 -> 1929728 | N54: =Recap!G53 -> 2001127 | P54: =K54-E54 -> #REF! | Q54: =L54-F54 -> 1285349.8 | R54: =M54-G54 -> 1339335 | S54: =N54-H54 -> 1385938
A55: T71 volksgezondheid.xlsx | B55: T71 | C55: Volksgezondheid | D55: L | E55: 1612047.9 | F55: 1612587 | G55: 1676626 | H55: 1743327 | J55: L | K55: =Recap!#REF! -> #REF! | L55: =Recap!E54 -> 1602422.2 | M55: =Recap!F54 -> 1665901 | N55: =Recap!G54 -> 1725279 | P55: =K55-E55 -> #REF! | Q55: =L55-F55 -> -10164.75 | R55: =M55-G55 -> -10725 | S55: =N55-H55 -> -18048
A56: T72 riolering met toevoeging toerekening belastingen.xlsx | B56: T72 | C56: Riolering | D56: L | E56: 2148357 | F56: 2253022.8 | G56: 2357514.3 | H56: 2651875.5 | J56: L | K56: =Recap!#REF! -> #REF! | L56: =Recap!E55 -> 2273231.2 | M56: =Recap!F55 -> 2352929.4 | N56: =Recap!G55 -> 2641245.2 | P56: =K56-E56 -> #REF! | Q56: =L56-F56 -> 20208.39 | R56: =M56-G56 -> -4584.9531 | S56: =N56-H56 -> -10630.34
A57: T73 afvalinzameling.xlsx | B57: T73 | C57: Afval | D57: L | E57: 4764881.5 | F57: 4929504.9 | G57: 5100042.7 | H57: 5276760.1 | J57: L | K57: =Recap!#REF! -> #REF! | L57: =Recap!E56 -> 5037977.7 | M57: =Recap!F56 -> 5146129.7 | N57: =Recap!G56 -> 5277551.1 | P57: =K57-E57 -> #REF! | Q57: =L57-F57 -> 108472.88 | R57: =M57-G57 -> 46087 | S57: =N57-H57 -> 791
A58: T74 milieubeheer.xlsx | B58: T74 | C58: Milieubeheer | D58: L | E58: 2155758.9 | F58: 2297096 | G58: 1846752 | H58: 1807785 | J58: L | K58: =Recap!#REF! -> #REF! | L58: =Recap!E57 -> 3775750.7 | M58: =Recap!F57 -> 2544143 | N58: =Recap!G57 -> 2568597 | P58: =K58-E58 -> #REF! | Q58: =L58-F58 -> 1478654.7 | R58: =M58-G58 -> 697391 | S58: =N58-H58 -> 760812 | U58: W01-2025 | V58: 150000 | W58: -150000
A59: T75 begraafplaatsen en crematoria.xlsx | B59: T75 | C59: Begraafplaatsen en crematoria | D59: L | E59: 5731 | F59: 5845 | G59: 5962 | H59: 6083 | J59: L | K59: =Recap!#REF! -> #REF! | L59: =Recap!E58 -> 12821 | M59: =Recap!F58 -> 13247 | N59: =Recap!G58 -> 13687 | P59: =K59-E59 -> #REF! | Q59: =L59-F59 -> 6976 | R59: =M59-G59 -> 7285 | S59: =N59-H59 -> 7604 | U59: W01-2025 | W59: 5647 | X59: 5903 | Y59: 6180
A60: T81 ruimtelijke ordening.xlsx | B60: T81 | C60: Ruimtelijke ordening | D60: L | E60: 2396420.6 | F60: 2378798 | G60: 2360118 | H60: 2454701 | J60: L | K60: =Recap!#REF! -> #REF! | L60: =Recap!E59 -> 7112395.2 | M60: =Recap!F59 -> 3187867 | N60: =Recap!G59 -> 3247665 | P60: =K60-E60 -> #REF! | Q60: =L60-F60 -> 4733597.2 | R60: =M60-G60 -> 827749 | S60: =N60-H60 -> 792964 | U60: W14-2024 | V60: 1549575 | W60: 1474575 | X60: 58432 | Y60: 58432
U61: W01-2025 | V61: 129000 | W61: 92700 | X61: 96600 | Y61: 100700
A62: T82 grondexploitaties 2025 aangepast MPG.xlsx | B62: T82 | C62: Grondexploitatie | D62: L | E62: 14181291 | F62: 11973003 | G62: 12195422 | H62: 3107876 | J62: L | K62: =Recap!#REF! -> #REF! | L62: =Recap!E60 -> 13358021 | M62: =Recap!F60 -> 14982625 | N62: =Recap!G60 -> 9626857 | P62: =K62-E62 -> #REF! | Q62: =L62-F62 -> 1385018 | R62: =M62-G62 -> 2787203 | S62: =N62-H62 -> 6518981
A63: T83 wonen en bouwen.xlsx | B63: T83 | C63: Wonen en bouwen | D63: L | E63: 2131573.9 | F63: 2048093 | G63: 2092199 | H63: 2160583 | J63: L | K63: =Recap!#REF! -> #REF! | L63: =Recap!E61 -> 2177296.5 | M63: =Recap!F61 -> 1946685 | N63: =Recap!G61 -> 1990661 | P63: =K63-E63 -> #REF! | Q63: =L63-F63 -> 129203.48 | R63: =M63-G63 -> -145514 | S63: =N63-H63 -> -169922 | U63: W01-2025 | V63: 31934 | W63: 27142 | X63: 14937 | Y63: 11914
B65: Saldo lasten | D65: L | E65: 1.070889e+08 | F65: 1.0649933e+08 | G65: 1.0933515e+08 | H65: 1.033498e+08 | J65: L | K65: =SUM(K4:K64) -> #REF! | L65: =SUM(L4:L64) -> #REF! | M65: =SUM(M4:M64) -> #REF! | N65: =SUM(N4:N64) -> #REF! | P65: =SUM(P4:P64) -> #REF! | Q65: =SUM(Q4:Q64) -> #REF! | R65: =SUM(R4:R64) -> #REF! | S65: =SUM(S4:S64) -> #REF! | V65: =SUM(V4:V64) -> 2247398 | W65: =SUM(W4:W64) -> 2533694 | X65: =SUM(X4:X64) -> 1285369 | Y65: =SUM(Y4:Y64) -> 1461699
A67: Taakveld | B67: Taakveld | C67: Omschrijving
A68: T01 bestuur en ondersteuning.xlsx | B68: T01 | C68: Bestuur | D68: B | E68: -259919 | F68: -178052 | G68: -188494 | H68: -194995 | J68: B | K68: =Recap!#REF! -> #REF! | L68: =Recap!E68 -> -296085 | M68: =Recap!F68 -> -309181 | N68: =Recap!G68 -> -246510 | P68: =K68-E68 -> #REF! | Q68: =L68-F68 -> -118033 | R68: =M68-G68 -> -120687 | S68: =N68-H68 -> -51515
A69: T02 burgerzaken.xlsx | B69: T02 | C69: Burgerzaken | D69: B | E69: -615573.2 | F69: -725381.6 | G69: -773732.9 | H69: -792081.6 | J69: B | K69: =Recap!#REF! -> #REF! | L69: =Recap!E69 -> -769469.28 | M69: =Recap!F69 -> -787704.9 | N69: =Recap!G69 -> -806996.9 | P69: =K69-E69 -> #REF! | Q69: =L69-F69 -> -44087.68 | R69: =M69-G69 -> -13972 | S69: =N69-H69 -> -14915.3
A70: T03 beheer overige gebouwen en gronden.xlsx | B70: T03 | C70: Beheer overige gebouwen en gronden | D70: B | E70: -356566.45 | F70: -364692 | G70: -373056 | H70: -381558 | J70: B | K70: =Recap!#REF! -> #REF! | L70: =Recap!E70 -> -466575 | M70: =Recap!F70 -> -374703.47 | N70: =Recap!G70 -> -383222.98 | P70: =K70-E70 -> #REF! | Q70: =L70-F70 -> -101883 | R70: =M70-G70 -> -1647.47 | S70: =N70-H70 -> -1664.98
A71: T04 bedrijf.xlsx | B71: T04B | C71: Overhead - 1 bedrijfsvoering | D71: B | E71: -8369 | F71: -8561 | G71: -8758 | H71: -8959 | J71: B | K71: =Recap!#REF! -> #REF! | L71: =Recap!E71 -> -8586 | M71: =Recap!F71 -> -8766 | N71: =Recap!G71 -> -8968 | P71: =K71-E71 -> #REF! | Q71: =L71-F71 -> -25 | R71: =M71-G71 -> -8 | S71: =N71-H71 -> -9
A72: T04 loon.xlsx | B72: T04L | C72: Overhead - 2 loonkosten | D72: B | E72: -11404 | F72: -11666 | G72: -11934 | H72: -12208 | J72: B | K72: =Recap!#REF! -> #REF! | L72: =Recap!E72 -> -11701 | M72: =Recap!F72 -> -11947 | N72: =Recap!G72 -> -12222 | P72: =K72-E72 -> #REF! | Q72: =L72-F72 -> -35 | R72: =M72-G72 -> -13 | S72: =N72-H72 -> -14
A73: T04 werf.xlsx | B73: T04W | C73: Overhead - 3 werf en vervoermiddelen | D73: B | E73: 0 | F73: 0 | G73: 0 | H73: 0 | J73: B | K73: =Recap!#REF! -> #REF! | L73: =Recap!E73 -> 0 | M73: =Recap!F73 -> 0 | N73: =Recap!G73 -> 0 | P73: =K73-E73 -> #REF! | Q73: =L73-F73 -> 0 | R73: =M73-G73 -> 0 | S73: =N73-H73 -> 0
A74: T05 Treasury.xlsx | B74: T05 | C74: Treasury | D74: B | E74: -385203.74 | F74: -146221.15 | G74: -132674.88 | H74: -131059.46 | J74: B | K74: =Recap!#REF! -> #REF! | L74: =Recap!E74 -> -187991.15 | M74: =Recap!F74 -> -107046.88 | N74: =Recap!G74 -> -106285.46 | P74: =K74-E74 -> #REF! | Q74: =L74-F74 -> -41770 | R74: =M74-G74 -> 25628 | S74: =N74-H74 -> 24774
A75: T06 1 OZB Woningen.xlsx | B75: T061 | C75: OZB Woningen | D75: B | E75: -5070056 | F75: -5714264 | G75: -6456477 | H75: -7048696 | J75: B | K75: =Recap!#REF! -> #REF! | L75: =Recap!E75 -> -5659292.5 | M75: =Recap!F75 -> -6382487 | N75: =Recap!G75 -> -6979704 | P75: =K75-E75 -> #REF! | Q75: =L75-F75 -> 54971.516 | R75: =M75-G75 -> 73990 | S75: =N75-H75 -> 68992
A76: T06 2 OZB Niet-Woningen.xlsx | B76: T062 | C76: OZB Niet woningen | D76: B | E76: -3258037 | F76: -3674176 | G76: -4142318 | H76: -4501463 | J76: B | K76: =Recap!#REF! -> #REF! | L76: =Recap!E76 -> -4016194 | M76: =Recap!F76 -> -4519324 | N76: =Recap!G76 -> -4903470 | P76: =K76-E76 -> #REF! | Q76: =L76-F76 -> -342018 | R76: =M76-G76 -> -377006 | S76: =N76-H76 -> -402007
A77: T06 4 Belastingen overig.xlsx | B77: T064 | C77: Belastingen overig | D77: B | E77: -146351 | F77: -150824 | G77: -155436 | H77: -160189 | J77: B | K77: =Recap!#REF! -> #REF! | L77: =Recap!E77 -> -86286.492 | M77: =Recap!F77 -> -89404.379 | N77: =Recap!G77 -> -92635.337 | P77: =K77-E77 -> #REF! | Q77: =L77-F77 -> 64537.508 | R77: =M77-G77 -> 66031.621 | S77: =N77-H77 -> 67553.663
A78: T07 Gemeentefonds en overige rijksuitkeringen.xlsx | B78: T07 | C78: Alg. uitkeringen en ov uitkeringen gemeentefonds | D78: B | E78: -58780570 | F78: -57219692 | G78: -59297784 | H78: -61427518 | J78: B | K78: =Recap!#REF! -> #REF! | L78: =Recap!E78 -> -63264435 | M78: =Recap!F78 -> -65532292 | N78: =Recap!G78 -> -66117057 | P78: =K78-E78 -> #REF! | Q78: =L78-F78 -> -6044743 | R78: =M78-G78 -> -6234508 | S78: =N78-H78 -> -4689539 | U78: W01-2024 | V78: -487042 | W78: -1346258 | X78: -1396447 | Y78: -1519329
A79: T08 Overige baten en lasten.xlsx | B79: T08 | C79: Overige baten en lasten | D79: B | E79: -47274 | F79: -48346 | G79: -49442 | H79: -50563 | J79: B | K79: =Recap!#REF! -> #REF! | L79: =Recap!E79 -> -48485 | M79: =Recap!F79 -> -49489 | N79: =Recap!G79 -> -50611 | P79: =K79-E79 -> #REF! | Q79: =L79-F79 -> -139 | R79: =M79-G79 -> -47 | S79: =N79-H79 -> -48
A80: T09 Vennootschapsbelasting.xlsx | B80: T09 | C80: Vennootschapsbelasting | D80: B | E80: 0 | F80: 0 | G80: 0 | H80: 0 | J80: B | K80: =Recap!#REF! -> #REF! | L80: =Recap!E80 -> 0 | M80: =Recap!F80 -> 0 | N80: =Recap!G80 -> 0 | P80: =K80-E80 -> #REF! | Q80: =L80-F80 -> 0 | R80: =M80-G80 -> 0 | S80: =N80-H80 -> 0
A81: T010 Mutaties Reserve.xlsx | B81: T010 | C81: Mutaties reserves | D81: B | E81: -3235448 | F81: -3409332 | G81: -2632923 | H81: -2128204 | J81: B | K81: =Recap!#REF! -> #REF! | L81: =Recap!E81 -> -9500031 | M81: =Recap!F81 -> -4464327 | N81: =Recap!G81 -> -2208156 | P81: =K81-E81 -> #REF! | Q81: =L81-F81 -> -6090699 | R81: =M81-G81 -> -1831404 | S81: =N81-H81 -> -79952 | U81: W01-2024 | V81: 217400 | W81: 150000
A82: T011 Resultaat rekening baten en lasten.xlsx | B82: T011 | C82: Resultaat van de rekening van baten en lasten | D82: B | E82: 0 | F82: 0 | G82: 0 | H82: 0 | J82: B | K82: =Recap!#REF! -> #REF! | L82: =Recap!E82 -> 0 | M82: =Recap!F82 -> 0 | N82: =Recap!G82 -> 0 | P82: =K82-E82 -> #REF! | Q82: =L82-F82 -> 0 | R82: =M82-G82 -> 0 | S82: =N82-H82 -> 0
A83: T11 crisisbeheersing en brandweer.xlsx | B83: T11 | C83: Crisisbeheersing en brandweer | D83: B | E83: -106263 | F83: -108707 | G83: -111207 | H83: -113765 | J83: B | K83: =Recap!#REF! -> #REF! | L83: =Recap!E83 -> -109768 | M83: =Recap!F83 -> -112837.49 | N83: =Recap!G83 -> -115433 | P83: =K83-E83 -> #REF! | Q83: =L83-F83 -> -1061 | R83: =M83-G83 -> -1630.49 | S83: =N83-H83 -> -1668
A84: T12 openbare orde en veiligheid.xlsx | B84: T12 | C84: Openbare orde en veiligheid | D84: B | E84: -190082 | F84: -196217 | G84: -202567 | H84: -209140 | J84: B | K84: =Recap!#REF! -> #REF! | L84: =Recap!E84 -> -177559 | M84: =Recap!F84 -> -183276 | N84: =Recap!G84 -> -188872 | P84: =K84-E84 -> #REF! | Q84: =L84-F84 -> 18658 | R84: =M84-G84 -> 19291 | S84: =N84-H84 -> 20268
A85: T21 Verkeer en vervoer.xlsx | B85: T21 | C85: Verkeer en vervoer | D85: B | E85: -488543 | F85: -500903 | G85: -467760 | H85: -527191 | J85: B | K85: =Recap!#REF! -> #REF! | L85: =Recap!E85 -> -544578 | M85: =Recap!F85 -> -527968 | N85: =Recap!G85 -> -556996 | P85: =K85-E85 -> #REF! | Q85: =L85-F85 -> -43675 | R85: =M85-G85 -> -60208 | S85: =N85-H85 -> -29805
A86: T22 parkeren.xlsx | B86: T22 | C86: Parkeren | D86: B | E86: -11507 | F86: -12017 | G86: -12293 | H86: -12576 | J86: B | K86: =Recap!#REF! -> #REF! | L86: =Recap!E86 -> -11835 | M86: =Recap!F86 -> -9779.79 | N86: =Recap!G86 -> -10005 | P86: =K86-E86 -> #REF! | Q86: =L86-F86 -> 182 | R86: =M86-G86 -> 2513.21 | S86: =N86-H86 -> 2571
A87: T25 openbaar vervoer.xlsx | B87: T25 | C87: Openbaar vervoer | D87: B | E87: -350 | F87: -349 | G87: -349 | H87: -348 | J87: B | K87: =Recap!#REF! -> #REF! | L87: =Recap!E87 -> -349 | M87: =Recap!F87 -> -349 | N87: =Recap!G87 -> -348 | P87: =K87-E87 -> #REF! | Q87: =L87-F87 -> 0 | R87: =M87-G87 -> 0 | S87: =N87-H87 -> 0
A88: T31 economische ontwikkeling.xlsx | B88: T31 | C88: Economische ontwikkeling | D88: B | E88: -140092 | F88: -143314 | G88: -146610 | H88: -149982 | J88: B | K88: =Recap!#REF! -> #REF! | L88: =Recap!E88 -> -143733 | M88: =Recap!F88 -> -146751 | N88: =Recap!G88 -> -150126 | P88: =K88-E88 -> #REF! | Q88: =L88-F88 -> -419 | R88: =M88-G88 -> -141 | S88: =N88-H88 -> -144
A89: T33 bedrijfsloket en bedrijfsregelingen.xlsx | B89: T33 | C89: Bedrijvenloket en bedrijvenregeling | D89: B | E89: -28133 | F89: -28655 | G89: -28698 | H89: -29702 | J89: B | K89: =Recap!#REF! -> #REF! | L89: =Recap!E89 -> -28660 | M89: =Recap!F89 -> -28708 | N89: =Recap!G89 -> -29718 | P89: =K89-E89 -> #REF! | Q89: =L89-F89 -> -5 | R89: =M89-G89 -> -10 | S89: =N89-H89 -> -16
A90: T34 economische promotie.xlsx | B90: T34 | C90: Economische promotie | D90: B | E90: -661699 | F90: -674930 | G90: -688501 | H90: -702422 | J90: B | K90: =Recap!#REF! -> #REF! | L90: =Recap!E90 -> -875019 | M90: =Recap!F90 -> -887697 | N90: =Recap!G90 -> -901330 | P90: =K90-E90 -> #REF! | Q90: =L90-F90 -> -200089 | R90: =M90-G90 -> -199196 | S90: =N90-H90 -> -198908
A91: T42 onderwijshuisvesting.xlsx | B91: T42 | C91: Onderwijshuisvesting | D91: B | E91: -50113 | F91: -51270 | G91: -52450 | H91: -53660 | J91: B | K91: =Recap!#REF! -> #REF! | L91: =Recap!E91 -> #REF! | M91: =Recap!F91 -> #REF! | N91: =Recap!G91 -> #REF! | P91: =K91-E91 -> #REF! | Q91: =L91-F91 -> #REF! | R91: =M91-G91 -> #REF! | S91: =N91-H91 -> #REF!
A92: T43 onderwijsbeleid en leerlingenzaken.xlsx | B92: T43 | C92: Onderwijsbeleid en leerlingenzaken | D92: B | E92: -419180 | F92: -419450 | G92: -419720 | H92: -419999 | J92: B | K92: =Recap!#REF! -> #REF! | L92: =Recap!E92 -> -444540 | M92: =Recap!F92 -> -419730 | N92: =Recap!G92 -> -420010 | P92: =K92-E92 -> #REF! | Q92: =L92-F92 -> -25090 | R92: =M92-G92 -> -10 | S92: =N92-H92 -> -11
A93: T51 Sportbeleid en activering.xlsx | B93: T51 | C93: Sportbeleid en activering | D93: B | E93: -153025 | F93: -144004 | G93: -144004 | H93: -144004 | J93: B | K93: =Recap!#REF! -> #REF! | L93: =Recap!E93 -> -144004 | M93: =Recap!F93 -> -144004 | N93: =Recap!G93 -> -144004 | P93: =K93-E93 -> #REF! | Q93: =L93-F93 -> 0 | R93: =M93-G93 -> 0 | S93: =N93-H93 -> 0
... A112: T67 62 jeugdhulp met verblijf regionaal.xlsx | B112: T6762 | C112: Jeugdhulp met verblijf regionaal | D112: B | E112: 0 | F112: 0 | G112: 0 | H112: 0 | J112: B | K112: =Recap!#REF! -> #REF! | L112: =Recap!E112 -> #REF! | M112: =Recap!F112 -> #REF! | N112: =Recap!G112 -> #REF! | P112: =K112-E112 -> #REF! | Q112: =L112-F112 -> #REF! | R112: =M112-G112 -> #REF! | S112: =N112-H112 -> #REF!
A113: T68 21 jeugdbescherming.xlsx | B113: T6821 | C113: Jeugdbescherming | D113: B | E113: 0 | F113: 0 | G113: 0 | H113: 0 | J113: B | K113: =Recap!#REF! -> #REF! | L113: =Recap!E115 -> #REF! | M113: =Recap!F115 -> #REF! | N113: =Recap!G115 -> #REF! | P113: =K113-E113 -> #REF! | Q113: =L113-F113 -> #REF! | R113: =M113-G113 -> #REF! | S113: =N113-H113 -> #REF!
A114: T68 22 jeugdreclassering.xlsx | B114: T6822 | C114: Jeugdreclassering | D114: B | E114: 0 | F114: 0 | G114: 0 | H114: 0 | J114: B | K114: =Recap!#REF! -> #REF! | L114: =Recap!E116 -> #REF! | M114: =Recap!F116 -> #REF! | N114: =Recap!G116 -> #REF! | P114: =K114-E114 -> #REF! | Q114: =L114-F114 -> #REF! | R114: =M114-G114 -> #REF! | S114: =N114-H114 -> #REF!
A115: T69 1 Coördinatie en beleid Wmo.xlsx | B115: T691 | C115: Coordinatie en beleid WMO | D115: B | E115: 0 | F115: 0 | G115: 0 | H115: 0 | J115: B | K115: =Recap!#REF! -> #REF! | L115: =Recap!E117 -> 0 | M115: =Recap!F117 -> 0 | N115: =Recap!G117 -> 0 | P115: =K115-E115 -> #REF! | Q115: =L115-F115 -> 0 | R115: =M115-G115 -> 0 | S115: =N115-H115 -> 0
A116: T69 2 Coördinatie en beleid Jeugd.xlsx | B116: T692 | C116: Coordinatie en beleid jeugd | D116: B | E116: 0 | F116: 0 | G116: 0 | H116: 0 | J116: B | K116: =Recap!#REF! -> #REF! | L116: =Recap!E118 -> 0 | M116: =Recap!F118 -> 0 | N116: =Recap!G118 -> 0 | P116: =K116-E116 -> #REF! | Q116: =L116-F116 -> 0 | R116: =M116-G116 -> 0 | S116: =N116-H116 -> 0
A117: T71 volksgezondheid.xlsx | B117: T71 | C117: Volksgezondheid | D117: B | E117: -120627 | F117: -59690 | G117: -59690 | H117: -59690 | J117: B | K117: =Recap!#REF! -> #REF! | L117: =Recap!E119 -> -62180 | M117: =Recap!F119 -> -62180 | N117: =Recap!G119 -> -62180 | P117: =K117-E117 -> #REF! | Q117: =L117-F117 -> -2490 | R117: =M117-G117 -> -2490 | S117: =N117-H117 -> -2490
A118: T72 riolering met toevoeging toerekening belastingen.xlsx | B118: T72 | C118: Riolering | D118: B | E118: -2951320.5 | F118: -3048592.6 | G118: -3149075.5 | H118: -3252874.6 | J118: B | K118: =Recap!#REF! -> #REF! | L118: =Recap!E120 -> -3063140.3 | M118: =Recap!F120 -> -3161192.2 | N118: =Recap!G120 -> -3262400.2 | P118: =K118-E118 -> #REF! | Q118: =L118-F118 -> -14547.648 | R118: =M118-G118 -> -12116.664 | S118: =N118-H118 -> -9525.582
A119: T73 afvalinzameling.xlsx | B119: T73 | C119: Afval | D119: B | E119: -5909281 | F119: -6101480.2 | G119: -6301386.2 | H119: -6510521.8 | J119: B | K119: =Recap!#REF! -> #REF! | L119: =Recap!E121 -> -6279202.8 | M119: =Recap!F121 -> -6412730.4 | N119: =Recap!G121 -> -6567935.4 | P119: =K119-E119 -> #REF! | Q119: =L119-F119 -> -177722.55 | R119: =M119-G119 -> -111344.2 | S119: =N119-H119 -> -57413.6
A120: T74 milieubeheer.xlsx | B120: T74 | C120: Milieubeheer | D120: B | E120: -415205 | F120: -416730 | G120: -418362 | H120: -365001 | J120: B | K120: =Recap!#REF! -> #REF! | L120: =Recap!E122 -> -689772 | M120: =Recap!F122 -> -1418376 | N120: =Recap!G122 -> -1365016 | P120: =K120-E120 -> #REF! | Q120: =L120-F120 -> -273042 | R120: =M120-G120 -> -1000014 | S120: =N120-H120 -> -1000015
A121: T75 begraafplaatsen en crematoria.xlsx | B121: T75 | C121: Begraafplaatsen en crematoria | D121: B | E121: -4067 | F121: -4067 | G121: -4067 | H121: -4063 | J121: B | K121: =Recap!#REF! -> #REF! | L121: =Recap!E123 -> -4067 | M121: =Recap!F123 -> -4067 | N121: =Recap!G123 -> -4063 | P121: =K121-E121 -> #REF! | Q121: =L121-F121 -> 0 | R121: =M121-G121 -> 0 | S121: =N121-H121 -> 0
...

Sheet Recap
A1: TAAKVELDENRAMING 2027 (NIEUW) | J1: TAAKVELDENRAMING 2026 (OUD) | R1: CODA | X1: VERSCHIL
A2: Taakveld | C2: Omschrijving | E2: 2026 | F2: 2027 | G2: 2028 | H2: 2029 | I2: 2030 | J2: 2026 | K2: verschil 2026 | L2: 2027 | M2: verschil 2027 | N2: 2028 | O2: verschil 2028 | P2: 2029 | Q2: verschil 2029 | R2: Taakveld | S2: Begroot 2026 | T2: Begroot 2027 | U2: Begroot 2028 | V2: Begroot 2029 | X2: Begroot 2026 | Y2: Begroot 2027 | Z2: Begroot 2028 | AA2: Begroot 2029
A3: T01 bestuur en ondersteuning.xlsx | B3: T01 | C3: Bestuur | D3: L | E3: ='T01'!K59 -> 4096256.6 | F3: ='T01'!L59 -> 3519006 | G3: ='T01'!M59 -> 3429319.8 | H3: ='T01'!N59 -> 3483441.6 | I3: ='T01'!O59 -> 3375675.2 | J3: 3623256.6 | K3: =J3-E3 -> -473000 | L3: 3527749.7 | M3: =L3-F3 -> 8743.6455 | N3: 3455653.2 | O3: =N3-G3 -> 26333.33 | P3: 3530153.9 | Q3: =P3-H3 -> 46712.333 | R3: 01 - Bestuur | S3: 3773257 | T3: 3527750 | U3: 3455654 | V3: 3530154 | X3: =S3-E3 -> -322999.6 | Y3: =T3-F3 -> 8743.9572 | Z3: =U3-G3 -> 26334.172 | AA3: =V3-H3 -> 46712.44
A4: T02 burgerzaken.xlsx | B4: T02 | C4: Burgerzaken | D4: L | E4: ='T02'!K41 -> 1279045.3 | F4: ='T02'!L41 -> 1306068.9 | G4: ='T02'!M41 -> 1349138.8 | H4: ='T02'!N41 -> 1393851.2 | I4: ='T02'!O41 -> 1439152.7 | J4: 1279045.3 | K4: =J4-E4 -> 0 | L4: 1310633.5 | M4: =L4-F4 -> 4564.615 | N4: 1360649.3 | O4: =N4-G4 -> 11510.507 | P4: 1413091.3 | Q4: =P4-H4 -> 19240.098 | R4: 02 - Burgerzaken | S4: 1279045 | T4: 1310634 | U4: 1360649 | V4: 1413091 | X4: =S4-E4 -> -0.28 | Y4: =T4-F4 -> 4565.085 | Z4: =U4-G4 -> 11510.245 | AA4: =V4-H4 -> 19239.832
A5: T03 beheer overige gebouwen en gronden.xlsx | B5: T03 | C5: Beheer overige gebouwen en gronden | D5: L | E5: ='T03'!K47 -> 653245.52 | F5: ='T03'!L47 -> 339365.95 | G5: ='T03'!M47 -> 348755.73 | H5: ='T03'!N47 -> 358458.63 | I5: ='T03'!O47 -> 349646 | J5: 341264.52 | K5: =J5-E5 -> -311981 | L5: 340102.95 | M5: =L5-F5 -> 737 | N5: 350926.73 | O5: =N5-G5 -> 2171 | P5: 362180.63 | Q5: =P5-H5 -> 3722 | R5: 03 - Beheer overige gebouwen en gronden | S5: 516264 | T5: 340103 | U5: 350927 | V5: 362181 | X5: =S5-E5 -> -136981.52 | Y5: =T5-F5 -> 737.04656 | Z5: =U5-G5 -> 2171.2663 | AA5: =V5-H5 -> 3722.3691
A6: T04 bedrijf.xlsx | B6: T04B | C6: Overhead - 1 bedrijfsvoering | D6: L | E6: =T04B!K53 -> 3325272.6 | F6: =T04B!L53 -> 3607658.3 | G6: =T04B!M53 -> 3180175.8 | H6: =T04B!N53 -> 3219679.8 | I6: =T04B!O53 -> 2851594.3 | J6: 3325272.6 | K6: =J6-E6 -> 0 | L6: 3610113.2 | M6: =L6-F6 -> 2454.8389 | N6: 3180589.5 | O6: =N6-G6 -> 413.74496 | P6: 3217938.9 | Q6: =P6-H6 -> -1740.916 | X6: =S6-E6 -> -3325272.6 | Y6: =T6-F6 -> -3607658.3 | Z6: =U6-G6 -> -3180175.8 | AA6: =V6-H6 -> -3219679.8
A7: T04 loon.xlsx | B7: T04L | C7: Overhead - 2 loonkosten | D7: L | E7: =T04L!K52 -> 11367751 | F7: =T04L!L52 -> 11709325 | G7: =T04L!M52 -> 12465644 | H7: =T04L!N52 -> 12994586 | I7: =T04L!O52 -> 13679959 | J7: 11509751 | K7: =J7-E7 -> 142000 | L7: 12108487 | M7: =L7-F7 -> 399162.46 | N7: 12596822 | O7: =N7-G7 -> 131178.14 | P7: 13225641 | Q7: =P7-H7 -> 231055.77 | R7: 04 - Overhead | S7: 14936461 | T7: 15479335 | U7: 15612493 | V7: 16278708 | X7: =S7-E7 -> 3568710.4 | Y7: =T7-F7 -> 3770010.4 | Z7: =U7-G7 -> 3146849 | AA7: =V7-H7 -> 3284122.4
A8: T04 werf.xlsx | B8: T04W | C8: Overhead - 3 werf en vervoermiddelen | D8: L | E8: =T04W!K41 -> 0 | F8: =T04W!L41 -> 0 | G8: =T04W!M41 -> 0 | H8: =T04W!N41 -> 0 | I8: =T04W!O41 -> 0 | J8: 0 | K8: =J8-E8 -> 0 | L8: 0 | M8: =L8-F8 -> 0 | N8: 0 | O8: =N8-G8 -> 0 | P8: 0 | Q8: =P8-H8 -> 0 | X8: =S8-E8 -> 0 | Y8: =T8-F8 -> 0 | Z8: =U8-G8 -> 0 | AA8: =V8-H8 -> 0
A9: T05 Treasury.xlsx | B9: T05 | C9: Treasury | D9: L | E9: ='T05'!K29 -> 204771 | F9: ='T05'!L29 -> 629078 | G9: ='T05'!M29 -> 1083905 | H9: ='T05'!N29 -> 1780521.3 | I9: ='T05'!O29 -> 18000 | J9: 204771 | K9: =J9-E9 -> 0 | L9: 629078 | M9: =L9-F9 -> 0 | N9: 1083905 | O9: =N9-G9 -> 0 | P9: 1780521.3 | Q9: =P9-H9 -> 0 | R9: 05 - Treasury | S9: 204771 | T9: 629078 | U9: 733905 | V9: 1430521 | X9: =S9-E9 -> 0 | Y9: =T9-F9 -> 0 | Z9: =U9-G9 -> -350000 | AA9: =V9-H9 -> -350000.33
A10: T06 1 OZB Woningen.xlsx | B10: T061 | C10: OZB Woningen | D10: L | E10: ='T061'!K27 -> 172088 | F10: ='T061'!L27 -> 177644 | G10: ='T061'!M27 -> 183043 | H10: ='T061'!N27 -> 188616 | I10: ='T061'!O27 -> 188017 | J10: 172088 | K10: =J10-E10 -> 0 | L10: 178088 | M10: =L10-F10 -> 444 | N10: 184323 | O10: =N10-G10 -> 1280 | P10: 190801 | Q10: =P10-H10 -> 2185 | R10: 061 - OZB woningen | S10: 172088 | T10: 178088 | U10: 184323 | V10: 190801 | X10: =S10-E10 -> 0 | Y10: =T10-F10 -> 444 | Z10: =U10-G10 -> 1280 | AA10: =V10-H10 -> 2185
A11: T06 2 OZB Niet-Woningen.xlsx | B11: T062 | C11: OZB Niet woningen | D11: L | E11: ='T062'!K29 -> 130667 | F11: ='T062'!L29 -> 135042 | G11: ='T062'!M29 -> 139255 | H11: ='T062'!N29 -> 143607 | I11: ='T062'!O29 -> 143871 | J11: 130667 | K11: =J11-E11 -> 0 | L11: 135401 | M11: =L11-F11 -> 359 | N11: 140324 | O11: =N11-G11 -> 1069 | P11: 145445 | Q11: =P11-H11 -> 1838 | R11: 062 - OZB niet-woningen | S11: 130667 | T11: 135401 | U11: 140324 | V11: 145445 | X11: =S11-E11 -> 0 | Y11: =T11-F11 -> 359 | Z11: =U11-G11 -> 1069 | AA11: =V11-H11 -> 1838
A12: T06 4 Belastingen overig.xlsx | B12: T064 | C12: Belastingen overig | D12: L | E12: ='T064'!K29 -> 65986 | F12: ='T064'!L29 -> 68757 | G12: ='T064'!M29 -> 71301 | H12: ='T064'!N29 -> 73939 | I12: ='T064'!O29 -> 76675 | J12: 65986 | K12: =J12-E12 -> 0 | L12: 69021 | M12: =L12-F12 -> 264 | N12: 72196 | O12: =N12-G12 -> 895 | P12: 75517 | Q12: =P12-H12 -> 1578 | R12: 064 - Belastingen overig | S12: 65986 | T12: 69021 | U12: 72196 | V12: 75517 | X12: =S12-E12 -> 0 | Y12: =T12-F12 -> 264 | Z12: =U12-G12 -> 895 | AA12: =V12-H12 -> 1578
A13: T07 Gemeentefonds en overige rijksuitkeringen.xlsx | B13: T07 | C13: Alg. uitkeringen en ov uitkeringen gemeentefonds | D13: L | E13: ='T07'!K34 -> 5780 | F13: ='T07'!L34 -> 5901 | G13: ='T07'!M34 -> 6037 | H13: ='T07'!N34 -> 6176 | I13: ='T07'!O34 -> 6318 | J13: 5780 | K13: =J13-E13 -> 0 | L13: 5907 | M13: =L13-F13 -> 6 | N13: 6037 | O13: =N13-G13 -> 0 | P13: 6170 | Q13: =P13-H13 -> -6 | R13: 07 - Alg.uitkering en ov.uitk.Gemeentefonds | S13: 5780 | T13: 5907 | U13: 6037 | V13: 6170 | X13: =S13-E13 -> 0 | Y13: =T13-F13 -> 6 | Z13: =U13-G13 -> 0 | AA13: =V13-H13 -> -6
A14: T08 Overige baten en lasten.xlsx | B14: T08 | C14: Overige baten en lasten | D14: L | E14: ='T08'!K40 -> 594431.35 | F14: ='T08'!L40 -> 233854 | G14: ='T08'!M40 -> 238228 | H14: ='T08'!N40 -> 242703 | I14: ='T08'!O40 -> 247281 | J14: 594431.35 | K14: =J14-E14 -> 0 | L14: 578621.87 | M14: =L14-F14 -> 344767.87 | N14: -3634954.7 | O14: =N14-G14 -> -3873182.7 | P14: -3989678.2 | Q14: =P14-H14 -> -4232381.2 | R14: 08 - Overige baten en lasten | S14: 703750 | T14: 740749 | U14: 1699388 | V14: 1776715 | X14: =S14-E14 -> 109318.65 | Y14: =T14-F14 -> 506895 | Z14: =U14-G14 -> 1461160 | AA14: =V14-H14 -> 1534012
A15: T09 Vennootschapsbelasting.xlsx | B15: T09 | C15: Vennootschapsbelasting | D15: L | E15: ='T09'!K40 -> 11400 | F15: ='T09'!L40 -> 11400 | G15: ='T09'!M40 -> 11400 | H15: ='T09'!N40 -> 11400 | I15: ='T09'!O40 -> 11400 | J15: 11400 | K15: =J15-E15 -> 0 | L15: 11400 | M15: =L15-F15 -> 0 | N15: 11400 | O15: =N15-G15 -> 0 | P15: 11400 | Q15: =P15-H15 -> 0 | R15: 09 - Vennootschapsbelasting (VPB) | S15: 11400 | T15: 11400 | U15: 11400 | V15: 11400 | X15: =S15-E15 -> 0 | Y15: =T15-F15 -> 0 | Z15: =U15-G15 -> 0 | AA15: =V15-H15 -> 0
A16: T010 Mutaties Reserve.xlsx | B16: T010 | C16: Mutaties reserves | D16: L | E16: ='T010'!K22 -> 905588 | F16: ='T010'!L22 -> 471829 | G16: ='T010'!M22 -> 438368 | H16: ='T010'!N22 -> 373260 | I16: ='T010'!O22 -> 0 | J16: 590588 | K16: =J16-E16 -> -315000 | L16: 471829 | M16: =L16-F16 -> 0 | N16: 438368 | O16: =N16-G16 -> 0 | P16: 373260 | Q16: =P16-H16 -> 0 | R16: 010 - Mutaties reserves | S16: 590588 | T16: 471829 | U16: 438368 | V16: 373260 | X16: =S16-E16 -> -315000 | Y16: =T16-F16 -> 0 | Z16: =U16-G16 -> 0 | AA16: =V16-H16 -> 0
A17: T011 Resultaat rekening baten en lasten.xlsx | B17: T011 | C17: Resultaat van de rekening van baten en lasten | D17: L | E17: ='T011'!K37 -> 0 | F17: ='T011'!L37 -> 0 | G17: ='T011'!M37 -> 0 | H17: ='T011'!N37 -> 0 | I17: ='T011'!O37 -> 0 | J17: 0 | K17: =J17-E17 -> 0 | L17: 0 | M17: =L17-F17 -> 0 | N17: 0 | O17: =N17-G17 -> 0 | P17: 0 | Q17: =P17-H17 -> 0 | S17: 0 | T17: 0 | U17: 0 | V17: 0 | X17: =S17-E17 -> 0 | Y17: =T17-F17 -> 0 | Z17: =U17-G17 -> 0 | AA17: =V17-H17 -> 0
A18: T11 crisisbeheersing en brandweer.xlsx | B18: T11 | C18: Crisisbeheersing en brandweer | D18: L | E18: ='T11'!K46 -> 2088526.5 | F18: ='T11'!L46 -> 2264477.9 | G18: ='T11'!M46 -> 2326060.9 | H18: ='T11'!N46 -> 2396344 | I18: ='T11'!O46 -> 2406801.2 | J18: 2088526.5 | K18: =J18-E18 -> 0 | L18: 2270039.7 | M18: =L18-F18 -> 5561.7831 | N18: 2341425.4 | O18: =N18-G18 -> 15364.571 | P18: 2422153.4 | Q18: =P18-H18 -> 25809.367 | R18: 11 - Crisisbeheersing en brandweer | S18: 2088527 | T18: 2270040 | U18: 2341426 | V18: 2422153 | X18: =S18-E18 -> 0.46765 | Y18: =T18-F18 -> 5562.0603 | Z18: =U18-G18 -> 15365.149 | AA18: =V18-H18 -> 25809.016
A19: T12 openbare orde en veiligheid.xlsx | B19: T12 | C19: Openbare orde en veiligheid | D19: L | E19: ='T12'!K55 -> 2005361.2 | F19: ='T12'!L55 -> 1932160.2 | G19: ='T12'!M55 -> 1999201.4 | H19: ='T12'!N55 -> 2061561.9 | I19: ='T12'!O55 -> 2134460.1 | J19: 1893861.2 | K19: =J19-E19 -> -111500 | L19: 1924507.1 | M19: =L19-F19 -> -7653.1138 | N19: 2008492.2 | O19: =N19-G19 -> 9290.8087 | P19: 2095062 | Q19: =P19-H19 -> 33500.116 | R19: 12 - Openbare orde en veiligheid | S19: 1903861 | T19: 1934507 | U19: 2016493 | V19: 2095063 | X19: =S19-E19 -> -101500.18 | Y19: =T19-F19 -> 2346.7628 | Z19: =U19-G19 -> 17291.617 | AA19: =V19-H19 -> 33501.089
A20: T21 Verkeer en vervoer.xlsx | B20: T21 | C20: Verkeer en vervoer | D20: L | E20: ='T21'!K67 -> 4152536.9 | F20: ='T21'!L67 -> 4859110.9 | G20: ='T21'!M67 -> 5275649.8 | H20: ='T21'!N67 -> 5910454 | I20: ='T21'!O67 -> 4063920.3 | J20: 4112749.9 | K20: =J20-E20 -> -39787 | L20: 4863397.2 | M20: =L20-F20 -> 4286.3 | N20: 5284607.8 | O20: =N20-G20 -> 8958 | P20: 5924632.9 | Q20: =P20-H20 -> 14178.92 | R20: 21 - Verkeer en vervoer | S20: 4112752 | T20: 4863396 | U20: 5259611 | V20: 5714629 | X20: =S20-E20 -> -39784.884 | Y20: =T20-F20 -> 4285.081 | Z20: =U20-G20 -> -16038.753 | AA20: =V20-H20 -> -195825.01
A21: T22 parkeren.xlsx | B21: T22 | C21: Parkeren | D21: L | E21: ='T22'!K32 -> 89294.891 | F21: ='T22'!L32 -> 90577.142 | G21: ='T22'!M32 -> 91996.267 | H21: ='T22'!N32 -> 163450.07 | I21: ='T22'!O32 -> 89595.837 | J21: 89294.891 | K21: =J21-E21 -> 0 | L21: 90630.393 | M21: =L21-F21 -> 53.250559 | N21: 91995.242 | O21: =N21-G21 -> -1.0247494 | P21: 163394.9 | Q21: =P21-H21 -> -55.174923 | R21: 22 - Parkeren | S21: 89295 | T21: 90631 | U21: 91995 | V21: 163395 | X21: =S21-E21 -> 0.10892786 | Y21: =T21-F21 -> 53.857895 | Z21: =U21-G21 -> -1.2668785 | AA21: =V21-H21 -> -55.070632
A22: T25 openbaar vervoer.xlsx | B22: T25 | C22: Openbaar vervoer | D22: L | E22: ='T25'!K34 -> 99454.81 | F22: ='T25'!L34 -> 101593.02 | G22: ='T25'!M34 -> 103963.27 | H22: ='T25'!N34 -> 106389.34 | I22: ='T25'!O34 -> 108873.65 | J22: 99454.81 | K22: =J22-E22 -> 0 | L22: 101698.4 | M22: =L22-F22 -> 105.38 | N22: 103996.48 | O22: =N22-G22 -> 33.21 | P22: 106345.54 | Q22: =P22-H22 -> -43.8 | R22: 25 - Openbaar vervoer | S22: 99455 | T22: 101698 | U22: 103996 | V22: 106346 | X22: =S22-E22 -> 0.19 | Y22: =T22-F22 -> 104.98 | Z22: =U22-G22 -> 32.73 | AA22: =V22-H22 -> -43.34
A23: T31 economische ontwikkeling.xlsx | B23: T31 | C23: Economische ontwikkeling | D23: L | E23: ='T31'!K43 -> 1355577.6 | F23: ='T31'!L43 -> 1122696.5 | G23: ='T31'!M43 -> 1152490.1 | H23: ='T31'!N43 -> 1182934.2 | I23: ='T31'!O43 -> 1216184.8 | J23: 1105577.6 | K23: =J23-E23 -> -250000 | L23: 1124466.9 | M23: =L23-F23 -> 1770.39 | N23: 1157510.1 | O23: =N23-G23 -> 5020 | P23: 1191437.7 | Q23: =P23-H23 -> 8503.58 | R23: 31 - Economische ontwikkeling | S23: 1355578 | T23: 1124467 | U23: 1157510 | V23: 1191438 | X23: =S23-E23 -> 0.44 | Y23: =T23-F23 -> 1770.47 | Z23: =U23-G23 -> 5019.89 | AA23: =V23-H23 -> 8503.8432
A24: T33 bedrijfsloket en bedrijfsregelingen.xlsx | B24: T33 | C24: Bedrijvenloket en bedrijvenregeling | D24: L | E24: ='T33'!K39 -> 41976.024 | F24: ='T33'!L39 -> 43502.504 | G24: ='T33'!M39 -> 44931.464 | H24: ='T33'!N39 -> 46407.928 | I24: ='T33'!O39 -> 47935.919 | J24: 41976.024 | K24: =J24-E24 -> 0 | L24: 43634.504 | M24: =L24-F24 -> 132 | N24: 45364.464 | O24: =N24-G24 -> 433 | P24: 47167.928 | Q24: =P24-H24 -> 760 | R24: 33 - Bedrijvenloket en bedrijfsregelingen | S24: 41976 | T24: 43635 | U24: 45364 | V24: 47168 | X24: =S24-E24 -> -0.024 | Y24: =T24-F24 -> 132.49562 | Z24: =U24-G24 -> 432.53555 | AA24: =V24-H24 -> 760.07211
A25: T34 economische promotie.xlsx | B25: T34 | C25: Economische promotie | D25: L | E25: ='T34'!K55 -> 517402.83 | F25: ='T34'!L55 -> 526952.76 | G25: ='T34'!M55 -> 536047.59 | H25: ='T34'!N55 -> 545414.76 | I25: ='T34'!O55 -> 554987.85 | J25: 517402.83 | K25: =J25-E25 -> 0 | L25: 527714.76 | M25: =L25-F25 -> 762 | N25: 538500.59 | O25: =N25-G25 -> 2453 | P25: 549700.76 | Q25: =P25-H25 -> 4286 | R25: 34 - Economische promotie | S25: 517403 | T25: 527715 | U25: 538501 | V25: 549701 | X25: =S25-E25 -> 0.173 | Y25: =T25-F25 -> 762.23582 | Z25: =U25-G25 -> 2453.4132 | AA25: =V25-H25 -> 4286.2377
A26: T42 onderwijshuisvesting.xlsx | B26: T42 | C26: Onderwijshuisvesting | D26: L | E26: ='T42'!K53 -> 1735325.4 | F26: ='T42'!L53 -> 1740867.3 | G26: ='T42'!M53 -> 3159300.5 | H26: ='T42'!N53 -> 3420717.7 | I26: ='T42'!O53 -> 403035 | J26: 1735325.4 | K26: =J26-E26 -> 0 | L26: 1741492.3 | M26: =L26-F26 -> 625 | N26: 2475764.5 | O26: =N26-G26 -> -683536 | P26: 2598887.7 | Q26: =P26-H26 -> -821830 | R26: 42 - Onderwijshuisvesting | S26: 1735326 | T26: 1741492 | U26: 3154117 | V26: 2977241 | X26: =S26-E26 -> 0.64467532 | Y26: =T26-F26 -> 624.68921 | Z26: =U26-G26 -> -5183.4693 | AA26: =V26-H26 -> -443476.73
A27: T43 onderwijsbeleid en leerlingenzaken.xlsx | B27: T43 | C27: Onderwijsbeleid en leerlingenzaken | D27: L | E27: ='T43'!K43 -> 1829738.2 | F27: ='T43'!L43 -> 1882242 | G27: ='T43'!M43 -> 1908620 | H27: ='T43'!N43 -> 1931690 | I27: ='T43'!O43 -> 2008399 | J27: 1829738.2 | K27: =J27-E27 -> 0 | L27: 1886486 | M27: =L27-F27 -> 4244 | N27: 1923432 | O27: =N27-G27 -> 14812 | P27: 1984502 | Q27: =P27-H27 -> 52812 | R27: 43 - Onderwijsbeleid en leerlingzaken | S27: 1829738 | T27: 1886486 | U27: 1923432 | V27: 1984502 | X27: =S27-E27 -> -0.23 | Y27: =T27-F27 -> 4244 | Z27: =U27-G27 -> 14812 | AA27: =V27-H27 -> 52812
A28: T51 Sportbeleid en activering.xlsx | B28: T51 | C28: Sportbeleid en activering | D28: L | E28: ='T51'!K39 -> 689486.75 | F28: ='T51'!L39 -> 684695 | G28: ='T51'!M39 -> 695336 | H28: ='T51'!N39 -> 706331 | I28: ='T51'!O39 -> 712997 | J28: 673486.75 | K28: =J28-E28 -> -16000 | L28: 685654 | M28: =L28-F28 -> 959 | N28: 698347 | O28: =N28-G28 -> 3011 | P28: 711564 | Q28: =P28-H28 -> 5233 | R28: 51 - Sportbeleid en activering | S28: 689487 | T28: 685654 | U28: 698347 | V28: 711564 | X28: =S28-E28 -> 0.25 | Y28: =T28-F28 -> 959 | Z28: =U28-G28 -> 3011 | AA28: =V28-H28 -> 5233
A29: T52 Sportaccommodaties.xlsx | B29: T52 | C29: Sportaccommodaties | D29: L | E29: ='T52'!K64 -> 2533362.2 | F29: ='T52'!L64 -> 2615409 | G29: ='T52'!M64 -> 2576630 | H29: ='T52'!N64 -> 2851315.7 | I29: ='T52'!O64 -> 1652621.5 | J29: 2521625.2 | K29: =J29-E29 -> -11737 | L29: 2616704.4 | M29: =L29-F29 -> 1295.3534 | N29: 2587140 | O29: =N29-G29 -> 10510.026 | P29: 2737816 | Q29: =P29-H29 -> -113499.7 | R29: 52 - Sportaccommodaties | S29: 2521626 | T29: 2616705 | U29: 2587138 | V29: 2636159 | X29: =S29-E29 -> -11736.195 | Y29: =T29-F29 -> 1295.9799 | Z29: =U29-G29 -> 10507.979 | AA29: =V29-H29 -> -215156.73
A30: T53 cultuurpresentatie,product,particip.xlsx | B30: T53 | C30: Cultuurproductie, presentatie en participatie | D30: L | E30: ='T53'!K50 -> 886151.49 | F30: ='T53'!L50 -> 840851.77 | G30: ='T53'!M50 -> 871065.5 | H30: ='T53'!N50 -> 902317.91 | I30: ='T53'!O50 -> 934626.78 | J30: 809151.49 | K30: =J30-E30 -> -77000 | L30: 843632.05 | M30: =L30-F30 -> 2780.2789 | N30: 879563.4 | O30: =N30-G30 -> 8497.9013 | P30: 917008.93 | Q30: =P30-H30 -> 14691.012 | R30: 53 - Cultuurpresentatie,-productie,-participatie | S30: 809152 | T30: 843632 | U30: 879563 | V30: 917009 | X30: =S30-E30 -> -76999.492 | Y30: =T30-F30 -> 2780.2305 | Z30: =U30-G30 -> 8497.4978 | AA30: =V30-H30 -> 14691.085
A31: T54 Musea.xlsx | B31: T54 | C31: Musea | D31: L | E31: ='T54'!K34 -> 134868 | F31: ='T54'!L34 -> 140533 | G31: ='T54'!M34 -> 145733 | H31: ='T54'!N34 -> 151125 | I31: ='T54'!O34 -> 156717 | J31: 134868 | K31: =J31-E31 -> 0 | L31: 141072 | M31: =L31-F31 -> 539 | N31: 147562 | O31: =N31-G31 -> 1829 | P31: 154350 | Q31: =P31-H31 -> 3225 | R31: 54 - Musea | S31: 134868 | T31: 141072 | U31: 147562 | V31: 154350 | X31: =S31-E31 -> 0 | Y31: =T31-F31 -> 539 | Z31: =U31-G31 -> 1829 | AA31: =V31-H31 -> 3225
A32: T55 Cultureel erfgoed.xlsx | B32: T55 | C32: Cultureel erfgoed | D32: L | E32: ='T55'!K33 -> 183726.12 | F32: ='T55'!L33 -> 188904 | G32: ='T55'!M33 -> 194166 | H32: ='T55'!N33 -> 199583 | I32: ='T55'!O33 -> 205158 | J32: 183726.12 | K32: =J32-E32 -> 0 | L32: 189277 | M32: =L32-F32 -> 373 | N32: 195020 | O32: =N32-G32 -> 854 | P32: 200962 | Q32: =P32-H32 -> 1379 | R32: 55 - Cultureel erfgoed | S32: 183726 | T32: 189277 | U32: 195020 | V32: 200962 | X32: =S32-E32 -> -0.12 | Y32: =T32-F32 -> 373 | Z32: =U32-G32 -> 854 | AA32: =V32-H32 -> 1379
A33: T56 Media.xlsx | B33: T56 | C33: Media | D33: L | E33: ='T56'!K33 -> 1007683.7 | F33: ='T56'!L33 -> 949093.35 | G33: ='T56'!M33 -> 964852.89 | H33: ='T56'!N33 -> 980936.18 | I33: ='T56'!O33 -> 996641.18 | J33: 1007683.7 | K33: =J33-E33 -> 0 | L33: 923106.35 | M33: =L33-F33 -> -25987 | N33: 938853.89 | O33: =N33-G33 -> -25999 | P33: 954925.18 | Q33: =P33-H33 -> -26011 | R33: 56 - Media | S33: 1033684 | T33: 949106 | U33: 964854 | V33: 980925 | X33: =S33-E33 -> 26000.271 | Y33: =T33-F33 -> 12.651615 | Z33: =U33-G33 -> 1.1057248 | AA33: =V33-H33 -> -11.178363
A34: T57 openbaar groen,(openlucht) recreatie.xlsx | B34: T57 | C34: Openbaar groen en (openlucht) recreatie | D34: L | E34: ='T57'!K46 -> 3759810.8 | F34: ='T57'!L46 -> 3514527.3 | G34: ='T57'!M46 -> 3617129.2 | H34: ='T57'!N46 -> 3718653.6 | I34: ='T57'!O46 -> 3829327.5 | J34: 3691899.8 | K34: =J34-E34 -> -67911 | L34: 3522446.8 | M34: =L34-F34 -> 7919.4627 | N34: 3650337.2 | O34: =N34-G34 -> 33207.992 | P34: 3776788.8 | Q34: =P34-H34 -> 58135.184 | R34: 57 - Openbaar groen en recreatie | S34: 3691898 | T34: 3522446 | U34: 3645338 | V34: 3766788 | X34: =S34-E34 -> -67912.817 | Y34: =T34-F34 -> 7918.6754 | Z34: =U34-G34 -> 28208.78 | AA34: =V34-H34 -> 48134.412
A35: T61 samenkracht en burgerparticipatie.xlsx | B35: T61 | C35: Samenkracht en burgerparticipatie | D35: L | E35: ='T61'!K61 -> 4909998.1 | F35: ='T61'!L61 -> 3579688.2 | G35: ='T61'!M61 -> 3705656.9 | H35: ='T61'!N61 -> 3824034.5 | I35: ='T61'!O61 -> 3868944.1 | J35: 3409998.1 | K35: =J35-E35 -> -1500000 | L35: 3590552.2 | M35: =L35-F35 -> 10864 | N35: 3731387.9 | O35: =N35-G35 -> 25731 | P35: 3865906.5 | Q35: =P35-H35 -> 41872 | R35: 61 - Samenkracht en burgerparticipatie | S35: 4909998 | T35: 3590551 | U35: 3731387 | V35: 3865906 | X35: =S35-E35 -> -0.057929775 | Y35: =T35-F35 -> 10862.751 | Z35: =U35-G35 -> 25730.083 | AA35: =V35-H35 -> 41871.52
A36: T62 2 toegang en eerstelijnsvoorzieningen Jeugd.xlsx | B36: T622 | C36: Toegang en eerstelijnsvoorzieningen jeugd | D36: L | E36: =#REF! -> #REF! | F36: =#REF! -> #REF! | G36: =#REF! -> #REF! | H36: =#REF! -> #REF! | I36: =#REF! -> #REF! | J36: 2205080 | K36: =J36-E36 -> #REF! | L36: 2399654 | M36: =L36-F36 -> #REF! | N36: 2316517 | O36: =N36-G36 -> #REF! | P36: 2413629 | Q36: =P36-H36 -> #REF! | R36: 622 - Toegang en eerstelijnsvoorzieningen Jeugd | S36: 2205080 | T36: 2399654 | U36: 2316517 | V36: 2413629 | X36: =S36-E36 -> #REF! | Y36: =T36-F36 -> #REF! | Z36: =U36-G36 -> #REF! | AA36: =V36-H36 -> #REF!
A37: T62 3 toegang en eerstelijnsvoorzieningen Integraal.xlsx | B37: T623 | C37: Toegang en eerstelijnsvoorzieningen integraal | D37: L | E37: =#REF! -> #REF! | F37: =#REF! -> #REF! | G37: =#REF! -> #REF! | H37: =#REF! -> #REF! | I37: =#REF! -> #REF! | J37: 667719.3 | K37: =J37-E37 -> #REF! | L37: 707207.52 | M37: =L37-F37 -> #REF! | N37: 709141.94 | O37: =N37-G37 -> #REF! | P37: 734203.34 | Q37: =P37-H37 -> #REF! | R37: 623 - Toegang en eerstelijnsvoorzieningen Integraal | S37: 667719 | T37: 707208 | U37: 709142 | V37: 734203 | X37: =S37-E37 -> #REF! | Y37: =T37-F37 -> #REF! | Z37: =U37-G37 -> #REF! | AA37: =V37-H37 -> #REF!
A38: T63 inkomensregelingen.xlsx | B38: T63 | C38: Inkomensregelingen | D38: L | E38: ='T63'!K58 -> 11332734 | F38: ='T63'!L58 -> 10727447 | G38: ='T63'!M58 -> 10709251 | H38: ='T63'!N58 -> 10814879 | I38: ='T63'!O58 -> 10798998 | J38: 10616557 | K38: =J38-E38 -> -716177 | L38: 10621796 | M38: =L38-F38 -> -105651 | N38: 10732811 | O38: =N38-G38 -> 23560 | P38: 10855355 | Q38: =P38-H38 -> 40476 | R38: 63 - Inkomensregelingen | S38: 10616557 | T38: 10621796 | U38: 10732811 | V38: 10855355 | X38: =S38-E38 -> -716176.93 | Y38: =T38-F38 -> -105651 | Z38: =U38-G38 -> 23560 | AA38: =V38-H38 -> 40476
A39: T64 begeleide participatie.xlsx | B39: T64 | C39: WSW en beschut werk | D39: L | E39: =#REF! -> #REF! | F39: =#REF! -> #REF! | G39: =#REF! -> #REF! | H39: =#REF! -> #REF! | I39: =#REF! -> #REF! | J39: 3559883 | K39: =J39-E39 -> #REF! | L39: 3395552 | M39: =L39-F39 -> #REF! | N39: 3240412 | O39: =N39-G39 -> #REF! | P39: 3240609 | Q39: =P39-H39 -> #REF! | R39: 64 - Begeleide participatie | S39: 3560789 | T39: 3396527 | U39: 3241456 | V39: 3241723 | X39: =S39-E39 -> #REF! | Y39: =T39-F39 -> #REF! | Z39: =U39-G39 -> #REF! | AA39: =V39-H39 -> #REF!
A40: T65 arbeidsparticipatie.xlsx | B40: T65 | C40: Arbeidsparticipatie | D40: L | E40: ='T65'!K45 -> 2733683 | F40: ='T65'!L45 -> 2265920 | G40: ='T65'!M45 -> 2295116 | H40: ='T65'!N45 -> 2392153 | I40: ='T65'!O45 -> 2449043 | J40: 2103368 | K40: =J40-E40 -> -630315 | L40: 2210941 | M40: =L40-F40 -> -54979 | N40: 2310500 | O40: =N40-G40 -> 15384 | P40: 2418846 | Q40: =P40-H40 -> 26693 | R40: 65 - Arbeidsparticipatie | S40: 2176536 | T40: 2270851 | U40: 2310500 | V40: 2418846 | X40: =S40-E40 -> -557146.98 | Y40: =T40-F40 -> 4931 | Z40: =U40-G40 -> 15384 | AA40: =V40-H40 -> 26693
A41: T66 0 hulpmiddelen en diensten (Wmo).xlsx | B41: T660 | C41: Hulpmiddelen en diensten (WMO) | D41: L | E41: =#REF! -> #REF! | F41: =#REF! -> #REF! | G41: =#REF! -> #REF! | H41: =#REF! -> #REF! | I41: =#REF! -> #REF! | J41: 976550 | K41: =J41-E41 -> #REF! | L41: 984930 | M41: =L41-F41 -> #REF! | N41: 1006830 | O41: =N41-G41 -> #REF! | P41: 1029220 | Q41: =P41-H41 -> #REF! | R41: 660 - Hulpmiddelen en diensten (Wmo) | S41: 976550 | T41: 984930 | U41: 1006830 | V41: 1029220 | X41: =S41-E41 -> #REF! | Y41: =T41-F41 -> #REF! | Z41: =U41-G41 -> #REF! | AA41: =V41-H41 -> #REF!
A42: T67 11 Huishoudelijke hulp (Wmo).xlsx | B42: T6711 | C42: Huishoudelijke hulp (WMO) | D42: L | E42: =#REF! -> #REF! | F42: =#REF! -> #REF! | G42: =#REF! -> #REF! | H42: =#REF! -> #REF! | I42: =#REF! -> #REF! | J42: 2666800 | K42: =J42-E42 -> #REF! | L42: 2789300 | M42: =L42-F42 -> #REF! | N42: 2917900 | O42: =N42-G42 -> #REF! | P42: 3051900 | Q42: =P42-H42 -> #REF! | R42: 6711 - Huishoudelijke hulp (Wmo) | S42: 2666800 | T42: 2789300 | U42: 2917900 | V42: 3051900 | X42: =S42-E42 -> #REF! | Y42: =T42-F42 -> #REF! | Z42: =U42-G42 -> #REF! | AA42: =V42-H42 -> #REF!
A43: T67 12 Begeleiding (Wmo).xlsx | B43: T6712 | C43: Begeleiding (WMO) | D43: L | E43: =#REF! -> #REF! | F43: =#REF! -> #REF! | G43: =#REF! -> #REF! | H43: =#REF! -> #REF! | I43: =#REF! -> #REF! | J43: 1933275 | K43: =J43-E43 -> #REF! | L43: 2140302 | M43: =L43-F43 -> #REF! | N43: 2329252 | O43: =N43-G43 -> #REF! | P43: 2410327 | Q43: =P43-H43 -> #REF! | R43: 6712 - Begeleiding (Wmo) | S43: 1933275 | T43: 2140302 | U43: 2329252 | V43: 2410327 | X43: =S43-E43 -> #REF! | Y43: =T43-F43 -> #REF! | Z43: =U43-G43 -> #REF! | AA43: =V43-H43 -> #REF!
A44: T67 13 dagbesteding (Wmo).xlsx | B44: T6713 | C44: Dagbesteding (WMO) | D44: L | E44: =#REF! -> #REF! | F44: =#REF! -> #REF! | G44: =#REF! -> #REF! | H44: =#REF! -> #REF! | I44: =#REF! -> #REF! | J44: 732700 | K44: =J44-E44 -> #REF! | L44: 766600 | M44: =L44-F44 -> #REF! | N44: 802000 | O44: =N44-G44 -> #REF! | P44: 838900 | Q44: =P44-H44 -> #REF! | R44: 6713 - Dagbesteding (Wmo) | S44: 732700 | T44: 766600 | U44: 802000 | V44: 838900 | X44: =S44-E44 -> #REF! | Y44: =T44-F44 -> #REF! | Z44: =U44-G44 -> #REF! | AA44: =V44-H44 -> #REF!
A45: T67 14 overige maatwerkarrangementen (Wmo).xlsx | B45: T6714 | C45: Overige maatwerkarrangementen (WMO) | D45: L | E45: =#REF! -> #REF! | F45: =#REF! -> #REF! | G45: =#REF! -> #REF! | H45: =#REF! -> #REF! | I45: =#REF! -> #REF! | J45: 63500 | K45: =J45-E45 -> #REF! | L45: 66400 | M45: =L45-F45 -> #REF! | N45: 69500 | O45: =N45-G45 -> #REF! | P45: 72700 | Q45: =P45-H45 -> #REF! | R45: 6714 - Overige maatwerkarrangement (Wmo) | S45: 63500 | T45: 66400 | U45: 69500 | V45: 72700 | X45: =S45-E45 -> #REF! | Y45: =T45-F45 -> #REF! | Z45: =U45-G45 -> #REF! | AA45: =V45-H45 -> #REF!
A46: T67 52 jeugdhulp ambulant regionaal.xlsx | B46: T6752 | C46: Jeugdhulp ambulant regionaal | D46: L | E46: =#REF! -> #REF! | F46: =#REF! -> #REF! | G46: =#REF! -> #REF! | H46: =#REF! -> #REF! | I46: =#REF! -> #REF! | J46: 7706287 | K46: =J46-E46 -> #REF! | L46: 8002136 | M46: =L46-F46 -> #REF! | N46: 8334234 | O46: =N46-G46 -> #REF! | P46: 8610896 | Q46: =P46-H46 -> #REF! | R46: 6752 - Jeugdhulp ambulant regionaal | S46: 7706287 | T46: 8002136 | U46: 6834234 | V46: 7110896 | X46: =S46-E46 -> #REF! | Y46: =T46-F46 -> #REF! | Z46: =U46-G46 -> #REF! | AA46: =V46-H46 -> #REF!
A47: T67 62 jeugdhulp met verblijf regionaal.xlsx | B47: T6762 | C47: Jeugdhulp met verblijf regionaal | D47: L | E47: =#REF! -> #REF! | F47: =#REF! -> #REF! | G47: =#REF! -> #REF! | H47: =#REF! -> #REF! | I47: =#REF! -> #REF! | J47: 1885000 | K47: =J47-E47 -> #REF! | L47: 1971000 | M47: =L47-F47 -> #REF! | N47: 2062000 | O47: =N47-G47 -> #REF! | P47: 2155000 | Q47: =P47-H47 -> #REF! | R47: 6762 - Jeugdhulp met verblijf regionaal | S47: 1885000 | T47: 1971000 | U47: 2062000 | V47: 2155000 | X47: =S47-E47 -> #REF! | Y47: =T47-F47 -> #REF! | Z47: =U47-G47 -> #REF! | AA47: =V47-H47 -> #REF!
A48: T6791 PGB Wmo | E48: =#REF! -> #REF! | F48: =#REF! -> #REF! | G48: =#REF! -> #REF! | H48: =#REF! -> #REF! | I48: =#REF! -> #REF! | J48: 382000 | K48: =J48-E48 -> #REF! | L48: 400000 | M48: =L48-F48 -> #REF! | N48: 418000 | O48: =N48-G48 -> #REF! | P48: 437000 | Q48: =P48-H48 -> #REF! | R48: 6791 - PGB Wmo | S48: 382000 | T48: 400000 | U48: 418000 | V48: 437000 | X48: =S48-E48 -> #REF! | Y48: =T48-F48 -> #REF! | Z48: =U48-G48 -> #REF! | AA48: =V48-H48 -> #REF!
A49: T6792 PGB Jeugd | E49: =#REF! -> #REF! | F49: =#REF! -> #REF! | G49: =#REF! -> #REF! | H49: =#REF! -> #REF! | I49: =#REF! -> #REF! | J49: 554000 | K49: =J49-E49 -> #REF! | L49: 579000 | M49: =L49-F49 -> #REF! | N49: 606000 | O49: =N49-G49 -> #REF! | P49: 634000 | Q49: =P49-H49 -> #REF! | R49: 6792 - PGB Jeugd | S49: 554000 | T49: 579000 | U49: 606000 | V49: 634000 | X49: =S49-E49 -> #REF! | Y49: =T49-F49 -> #REF! | Z49: =U49-G49 -> #REF! | AA49: =V49-H49 -> #REF!
A50: T68 21 jeugdbescherming.xlsx | B50: T6821 | C50: Jeugdbescherming | D50: L | E50: =#REF! -> #REF! | F50: =#REF! -> #REF! | G50: =#REF! -> #REF! | H50: =#REF! -> #REF! | I50: =#REF! -> #REF! | J50: 429000 | K50: =J50-E50 -> #REF! | L50: 449000 | M50: =L50-F50 -> #REF! | N50: 470000 | O50: =N50-G50 -> #REF! | P50: 491000 | Q50: =P50-H50 -> #REF! | R50: 6821 - Jeugdbescherming | S50: 429000 | T50: 449000 | U50: 470000 | V50: 491000 | X50: =S50-E50 -> #REF! | Y50: =T50-F50 -> #REF! | Z50: =U50-G50 -> #REF! | AA50: =V50-H50 -> #REF!
A51: T68 22 jeugdreclassering.xlsx | B51: T6822 | C51: Jeugdreclassering | D51: L | E51: =#REF! -> #REF! | F51: =#REF! -> #REF! | G51: =#REF! -> #REF! | H51: =#REF! -> #REF! | I51: =#REF! -> #REF! | J51: 85000 | K51: =J51-E51 -> #REF! | L51: 89000 | M51: =L51-F51 -> #REF! | N51: 93000 | O51: =N51-G51 -> #REF! | P51: 97000 | Q51: =P51-H51 -> #REF! | R51: 6822 - Jeugdreclassering | S51: 85000 | T51: 89000 | U51: 93000 | V51: 97000 | X51: =S51-E51 -> #REF! | Y51: =T51-F51 -> #REF! | Z51: =U51-G51 -> #REF! | AA51: =V51-H51 -> #REF!
A52: T69 1 Coördinatie en beleid Wmo.xlsx | B52: T691 | C52: Coordinatie en beleid WMO | D52: L | E52: ='T691'!K33 -> 1051284.9 | F52: ='T691'!L33 -> 976024.9 | G52: ='T691'!M33 -> 1012137.4 | H52: ='T691'!N33 -> 1049587.1 | I52: ='T691'!O33 -> 1088422.2 | J52: 1051284.9 | K52: =J52-E52 -> 0 | L52: 979772.62 | M52: =L52-F52 -> 3747.7175 | N52: 1024841.4 | O52: =N52-G52 -> 12703.999 | P52: 1071984.2 | Q52: =P52-H52 -> 22397.042 | R52: 691 - Coordinatie en beleid Wmo | S52: 1051285 | T52: 979773 | U52: 1024841 | V52: 1071984 | X52: =S52-E52 -> 0.13 | Y52: =T52-F52 -> 3748.0965 | Z52: =U52-G52 -> 12703.559 | AA52: =V52-H52 -> 22396.878
A53: T69 2 Coördinatie en beleid Jeugd.xlsx | B53: T692 | C53: Coordinatie en beleid jeugd | D53: L | E53: ='T692'!K40 -> 1851945.8 | F53: ='T692'!L40 -> 1929728 | G53: ='T692'!M40 -> 2001127 | H53: ='T692'!N40 -> 2075169 | I53: ='T692'!O40 -> 2151951 | J53: 1851945.8 | K53: =J53-E53 -> 0 | L53: 1937135 | M53: =L53-F53 -> 7407 | N53: 2026244 | O53: =N53-G53 -> 25117 | P53: 2119451 | Q53: =P53-H53 -> 44282 | R53: 692 - Coordinatie en beleid Jeugd | S53: 1851946 | T53: 1937135 | U53: 2026244 | V53: 2119451 | X53: =S53-E53 -> 0.19 | Y53: =T53-F53 -> 7407 | Z53: =U53-G53 -> 25117 | AA53: =V53-H53 -> 44282
A54: T71 volksgezondheid.xlsx | B54: T71 | C54: Volksgezondheid | D54: L | E54: ='T71'!K56 -> 1602422.2 | F54: ='T71'!L56 -> 1665901 | G54: ='T71'!M56 -> 1725279 | H54: ='T71'!N56 -> 1786802 | I54: ='T71'!O56 -> 1849566 | J54: 1586422.2 | K54: =J54-E54 -> -16000 | L54: 1655916 | M54: =L54-F54 -> -9985 | N54: 1728603 | O54: =N54-G54 -> 3324 | P54: 1804614 | Q54: =P54-H54 -> 17812 | R54: 71 - Volksgezondheid | S54: 1602422 | T54: 1671916 | U54: 1745603 | V54: 1822614 | X54: =S54-E54 -> -0.25 | Y54: =T54-F54 -> 6015 | Z54: =U54-G54 -> 20324 | AA54: =V54-H54 -> 35812
A55: T72 riolering met toevoeging toerekening belastingen.xlsx | B55: T72 | C55: Riolering | D55: L | E55: ='T72'!K53 -> 2273231.2 | F55: ='T72'!L53 -> 2352929.4 | G55: ='T72'!M53 -> 2641245.2 | H55: ='T72'!N53 -> 2726931.1 | I55: ='T72'!O53 -> 2813636.1 | J55: 2280810.7 | K55: =J55-E55 -> 7579.5016 | L55: 2366874 | M55: =L55-F55 -> 13944.63 | N55: 2660138.8 | O55: =N55-G55 -> 18893.647 | P55: 2751005.4 | Q55: =P55-H55 -> 24074.331 | R55: 72 - Riolering | S55: 2280811 | T55: 2366874 | U55: 2660139 | V55: 2751005 | X55: =S55-E55 -> 7579.8251 | Y55: =T55-F55 -> 13944.604 | Z55: =U55-G55 -> 18893.823 | AA55: =V55-H55 -> 24073.922
A56: T73 afvalinzameling.xlsx | B56: T73 | C56: Afval | D56: L | E56: ='T73'!K51 -> 5037977.7 | F56: ='T73'!L51 -> 5146129.7 | G56: ='T73'!M51 -> 5277551.1 | H56: ='T73'!N51 -> 5412461.1 | I56: ='T73'!O51 -> 5590413.3 | J56: 5017976.7 | K56: =J56-E56 -> -20001 | L56: 5150760.7 | M56: =L56-F56 -> 4631 | N56: 5286616.1 | O56: =N56-G56 -> 9065 | P56: 5426397.1 | Q56: =P56-H56 -> 13936 | R56: 73 - Afval | S56: 5017977 | T56: 5150761 | U56: 5286616 | V56: 5426397 | X56: =S56-E56 -> -20000.729 | Y56: =T56-F56 -> 4631.3162 | Z56: =U56-G56 -> 9064.9066 | AA56: =V56-H56 -> 13935.923
A57: T74 milieubeheer.xlsx | B57: T74 | C57: Milieubeheer | D57: L | E57: ='T74'!K66 -> 3775750.7 | F57: ='T74'!L66 -> 2544143 | G57: ='T74'!M66 -> 2568597 | H57: ='T74'!N66 -> 2634849 | I57: ='T74'!O66 -> 2203787 | J57: 1861750.7 | K57: =J57-E57 -> -1914000 | L57: 2546751 | M57: =L57-F57 -> 2608 | N57: 2575216 | O57: =N57-G57 -> 6619 | P57: 2645932 | Q57: =P57-H57 -> 11083 | R57: 74 - Milieubeheer | S57: 3791751 | T57: 2546751 | U57: 2491882 | V57: 2515931 | X57: =S57-E57 -> 16000.29 | Y57: =T57-F57 -> 2608 | Z57: =U57-G57 -> -76715 | AA57: =V57-H57 -> -118918
A58: T75 begraafplaatsen en crematoria.xlsx | B58: T75 | C58: Begraafplaatsen en crematoria | D58: L | E58: ='T75'!K32 -> 12821 | F58: ='T75'!L32 -> 13247 | G58: ='T75'!M32 -> 13687 | H58: ='T75'!N32 -> 13856 | I58: ='T75'!O32 -> 14032 | J58: 12821 | K58: =J58-E58 -> 0 | L58: 13259 | M58: =L58-F58 -> 12 | N58: 13727 | O58: =N58-G58 -> 40 | P58: 13925 | Q58: =P58-H58 -> 69 | R58: 75 - Begraafplaatsen en crematoria | S58: 12821 | T58: 13259 | U58: 13727 | V58: 13925 | X58: =S58-E58 -> 0 | Y58: =T58-F58 -> 12 | Z58: =U58-G58 -> 40 | AA58: =V58-H58 -> 69
A59: T81 ruimtelijke ordening.xlsx | B59: T81 | C59: Ruimtelijke ordening | D59: L | E59: ='T81'!K65 -> 7112395.2 | F59: ='T81'!L65 -> 3187867 | G59: ='T81'!M65 -> 3247665 | H59: ='T81'!N65 -> 3261658 | I59: ='T81'!O65 -> 3375861 | J59: 4596252.2 | K59: =J59-E59 -> -2516143 | L59: 3197742 | M59: =L59-F59 -> 9875 | N59: 3279241 | O59: =N59-G59 -> 31576 | P59: 3317138 | Q59: =P59-H59 -> 55480 | R59: 81 - Ruimtelijke ordening | S59: 6892396 | T59: 3181075 | U59: 3245907 | V59: 3267137 | X59: =S59-E59 -> -219999.23 | Y59: =T59-F59 -> -6792 | Z59: =U59-G59 -> -1758 | AA59: =V59-H59 -> 5479
A60: T82 grondexploitaties 2025 aangepast MPG.xlsx | B60: T82 | C60: Grondexploitatie | D60: L | E60: ='T82'!K44 -> 13358021 | F60: ='T82'!L44 -> 14982625 | G60: ='T82'!M44 -> 9626857 | H60: ='T82'!N44 -> 3633979 | I60: ='T82'!O44 -> 3633979 | J60: 13258021 | K60: =J60-E60 -> -100000 | L60: 14982625 | M60: =L60-F60 -> 0 | N60: 9626857 | O60: =N60-G60 -> 0 | P60: 3633979 | Q60: =P60-H60 -> 0 | R60: 82 - Grondexploitatie (niet-bedrijventerreinen) | S60: 13258020 | T60: 14982625 | U60: 9626858 | V60: 3633981 | X60: =S60-E60 -> -100001 | Y60: =T60-F60 -> 0 | Z60: =U60-G60 -> 1 | AA60: =V60-H60 -> 2
A61: T83 wonen en bouwen.xlsx | B61: T83 | C61: Wonen en bouwen | D61: L | E61: ='T83'!K56 -> 2177296.5 | F61: ='T83'!L56 -> 1946685 | G61: ='T83'!M56 -> 1990661 | H61: ='T83'!N56 -> 2041148 | I61: ='T83'!O56 -> 2092790 | J61: 1873296.5 | K61: =J61-E61 -> -304000 | L61: 1950535 | M61: =L61-F61 -> 3850 | N61: 2001361 | O61: =N61-G61 -> 10700 | P61: 2059205 | Q61: =P61-H61 -> 18057 | R61: 83 - Wonen en bouwen | S61: 2207297 | T61: 1950535 | U61: 2001361 | V61: 2059205 | X61: =S61-E61 -> 30000.52 | Y61: =T61-F61 -> 3850 | Z61: =U61-G61 -> 10700 | AA61: =V61-H61 -> 18057
B63: Saldo lasten | D63: L | E63: =SUM(E3:E61) -> #REF! | F63: =SUM(F3:F61) -> #REF! | G63: =SUM(G3:G61) -> #REF! | H63: =SUM(H3:H61) -> #REF! | I63: =SUM(I3:I61) -> #REF! | J63: =SUM(J3:J61) -> 1.1775795e+08 | L63: =SUM(L3:L61) -> 1.2241713e+08 | M63: =SUM(M3:M61) -> #REF! | N63: =SUM(N3:N61) -> 1.1668648e+08 | O63: =SUM(O3:O61) -> #REF! | P63: =SUM(P3:P61) -> 1.1507926e+08 | Q63: =SUM(Q3:Q61) -> #REF! | S63: =SUM(S3:S61) -> 124745926 | T63: =SUM(T3:T61) -> 122436213 | U63: =SUM(U3:U61) -> 120589638 | V63: =SUM(V3:V61) -> 118752591 | X63: =SUM(X3:X61) -> #REF! | Y63: =SUM(Y3:Y61) -> #REF! | Z63: =SUM(Z3:Z61) -> #REF! | AA63: =SUM(AA3:AA61) -> #REF!
A64: Was voor index en kolom 2024 verwijderen
J65: =+J63-J60 -> 1.0449993e+08 | K65: =+K63-K60 -> 100000 | L65: =+L63-L60 -> 1.0743451e+08 | M65: =+M63-M60 -> #REF! | N65: =+N63-N60 -> 1.0705963e+08 | O65: =+O63-O60 -> #REF! | P65: =+P63-P60 -> 1.1144529e+08 | Q65: =+Q63-Q60 -> #REF!
A67: Taakveld | B67: Taakveld | C67: Omschrijving
A68: T01 bestuur en ondersteuning.xlsx | B68: T01 | C68: Bestuur | D68: B | E68: ='T01'!K68 -> -296085 | F68: ='T01'!L68 -> -309181 | G68: ='T01'!M68 -> -246510 | H68: ='T01'!N68 -> -199488 | I68: ='T01'!O68 -> 0 | J68: -296085 | K68: =J68-E68 -> 0 | L68: -309181 | M68: =L68-F68 -> 0 | N68: -246510 | O68: =N68-G68 -> 0 | P68: -199488 | Q68: =P68-H68 -> 0 | R68: 01 - Bestuur | S68: -296085 | T68: -309181 | U68: -246510 | V68: -199488 | X68: =S68-E68 -> 0 | Y68: =T68-F68 -> 0 | Z68: =U68-G68 -> 0 | AA68: =V68-H68 -> 0
A69: T02 burgerzaken.xlsx | B69: T02 | C69: Burgerzaken | D69: B | E69: ='T02'!K50 -> -769469.28 | F69: ='T02'!L50 -> -787704.9 | G69: ='T02'!M50 -> -806996.9 | H69: ='T02'!N50 -> -827205.4 | I69: ='T02'!O50 -> -846821.8 | J69: -769469.28 | K69: =J69-E69 -> 0 | L69: -788754.9 | M69: =L69-F69 -> -1050 | N69: -808858.7 | O69: =N69-G69 -> -1861.8 | P69: -829246.4 | Q69: =P69-H69 -> -2041 | R69: 02 - Burgerzaken | S69: -769471 | T69: -788756 | U69: -808859 | V69: -829247 | X69: =S69-E69 -> -1.72 | Y69: =T69-F69 -> -1051.1 | Z69: =U69-G69 -> -1862.1 | AA69: =V69-H69 -> -2041.6
A70: T03 beheer overige gebouwen en gronden.xlsx | B70: T03 | C70: Beheer overige gebouwen en gronden | D70: B | E70: ='T03'!K62 -> -466575 | F70: ='T03'!L62 -> -374703.47 | G70: ='T03'!M62 -> -383222.98 | H70: ='T03'!N62 -> -391983.98 | I70: ='T03'!O62 -> -400888.98 | J70: -372411 | K70: =J70-E70 -> 94164 | L70: -380572 | M70: =L70-F70 -> -5868.53 | N70: -388866 | O70: =N70-G70 -> -5643.02 | P70: -397393 | Q70: =P70-H70 -> -5409.02 | R70: 03 - Beheer overige gebouwen en gronden | S70: -372411 | T70: -380572 | U70: -388866 | V70: -397393 | X70: =S70-E70 -> 94164 | Y70: =T70-F70 -> -5868.53 | Z70: =U70-G70 -> -5643.02 | AA70: =V70-H70 -> -5409.02
A71: T04 bedrijf.xlsx | B71: T04B | C71: Overhead - 1 bedrijfsvoering | D71: B | E71: =T04B!K69 -> -8586 | F71: =T04B!L69 -> -8766 | G71: =T04B!M69 -> -8968 | H71: =T04B!N69 -> -9174 | I71: =T04B!O69 -> -9385 | J71: -8586 | K71: =J71-E71 -> 0 | L71: -8774 | M71: =L71-F71 -> -8 | N71: -8967 | O71: =N71-G71 -> 1 | P71: -9164 | Q71: =P71-H71 -> 10 | X71: =S71-E71 -> 8586 | Y71: =T71-F71 -> 8766 | Z71: =U71-G71 -> 8968 | AA71: =V71-H71 -> 9174
A72: T04 loon.xlsx | B72: T04L | C72: Overhead - 2 loonkosten | D72: B | E72: =T04L!K67 -> -11701 | F72: =T04L!L67 -> -11947 | G72: =T04L!M67 -> -12222 | H72: =T04L!N67 -> -12503 | I72: =T04L!O67 -> -12791 | J72: -11701 | K72: =J72-E72 -> 0 | L72: -11958 | M72: =L72-F72 -> -11 | N72: -12221 | O72: =N72-G72 -> 1 | P72: -12490 | Q72: =P72-H72 -> 13 | R72: 04 - Overhead | S72: -20287 | T72: -20732 | U72: -21188 | V72: -21654 | X72: =S72-E72 -> -8586 | Y72: =T72-F72 -> -8785 | Z72: =U72-G72 -> -8966 | AA72: =V72-H72 -> -9151
A73: T04 werf.xlsx | B73: T04W | C73: Overhead - 3 werf en vervoermiddelen | D73: B | E73: =T04W!K54 -> 0 | F73: =T04W!L54 -> 0 | G73: =T04W!M54 -> 0 | H73: =T04W!N54 -> 0 | I73: =T04W!O54 -> 0 | J73: 0 | K73: =J73-E73 -> 0 | L73: 0 | M73: =L73-F73 -> 0 | N73: 0 | O73: =N73-G73 -> 0 | P73: 0 | Q73: =P73-H73 -> 0 | X73: =S73-E73 -> 0 | Y73: =T73-F73 -> 0 | Z73: =U73-G73 -> 0 | AA73: =V73-H73 -> 0
A74: T05 Treasury.xlsx | B74: T05 | C74: Treasury | D74: B | E74: ='T05'!K36 -> -187991.15 | F74: ='T05'!L36 -> -107046.88 | G74: ='T05'!M36 -> -106285.46 | H74: ='T05'!N36 -> -105508.46 | I74: ='T05'!O36 -> -102171 | J74: -191520.15 | K74: =J74-E74 -> -3529 | L74: -109774.88 | M74: =L74-F74 -> -2728 | N74: -108160.46 | O74: =N74-G74 -> -1875 | P74: -106474.46 | Q74: =P74-H74 -> -966 | R74: 05 - Treasury | S74: -191520 | T74: -109775 | U74: -108160 | V74: -106474 | X74: =S74-E74 -> -3528.8534 | Y74: =T74-F74 -> -2728.1179 | Z74: =U74-G74 -> -1874.5444 | AA74: =V74-H74 -> -965.54
A75: T06 1 OZB Woningen.xlsx | B75: T061 | C75: OZB Woningen | D75: B | E75: ='T061'!K33 -> -5659292.5 | F75: ='T061'!L33 -> -6382487 | G75: ='T061'!M33 -> -6979704 | H75: ='T061'!N33 -> -7612928 | I75: ='T061'!O33 -> -10155 | J75: -5659292.5 | K75: =J75-E75 -> 0 | L75: -6382496 | M75: =L75-F75 -> -9 | N75: -6979704 | O75: =N75-G75 -> 0 | P75: -7612918 | Q75: =P75-H75 -> 10 | R75: 061 - OZB woningen | S75: -5659292 | T75: -6382496 | U75: -6979704 | V75: -7612918 | X75: =S75-E75 -> 0.4836 | Y75: =T75-F75 -> -9 | Z75: =U75-G75 -> 0 | AA75: =V75-H75 -> 10
A76: T06 2 OZB Niet-Woningen.xlsx | B76: T062 | C76: OZB Niet woningen | D76: B | E76: ='T062'!K42 -> -4016194 | F76: ='T062'!L42 -> -4519324 | G76: ='T062'!M42 -> -4903470 | H76: ='T062'!N42 -> -5320618 | I76: ='T062'!O42 -> -6771 | J76: -4016194 | K76: =J76-E76 -> 0 | L76: -4519330 | M76: =L76-F76 -> -6 | N76: -4903470 | O76: =N76-G76 -> 0 | P76: -5320612 | Q76: =P76-H76 -> 6 | R76: 062 - OZB niet-woningen | S76: -4016194 | T76: -4519330 | U76: -4903470 | V76: -5320612 | X76: =S76-E76 -> 0 | Y76: =T76-F76 -> -6 | Z76: =U76-G76 -> 0 | AA76: =V76-H76 -> 6
A77: T06 4 Belastingen overig.xlsx | B77: T064 | C77: Belastingen overig | D77: B | E77: ='T064'!K40 -> -86286.492 | F77: ='T064'!L40 -> -89404.379 | G77: ='T064'!M40 -> -92635.337 | H77: ='T064'!N40 -> -95557.279 | I77: ='T064'!O40 -> -98572.149 | J77: -86286.492 | K77: =J77-E77 -> 0 | L77: -89404.379 | M77: =L77-F77 -> 0 | N77: -92635.337 | O77: =N77-G77 -> 0 | P77: -95857.279 | Q77: =P77-H77 -> -300 | R77: 064 - Belastingen overig | S77: -86286 | T77: -89404 | U77: -92635 | V77: -95857 | X77: =S77-E77 -> 0.492 | Y77: =T77-F77 -> 0.37922 | Z77: =U77-G77 -> 0.3374927 | AA77: =V77-H77 -> -299.7207
A78: T07 Gemeentefonds en overige rijksuitkeringen.xlsx | B78: T07 | C78: Alg. uitkeringen en ov uitkeringen gemeentefonds | D78: B | E78: ='T07'!K54 -> -63264435 | F78: ='T07'!L54 -> -65532292 | G78: ='T07'!M54 -> -66117057 | H78: ='T07'!N54 -> -68912251 | I78: ='T07'!O54 -> 0 | J78: -63264435 | K78: =J78-E78 -> 0 | L78: -65440609 | M78: =L78-F78 -> 91683 | N78: -66133443 | O78: =N78-G78 -> -16386 | P78: -68978504 | Q78: =P78-H78 -> -66253 | R78: 07 - Alg.uitkering en ov.uitk.Gemeentefonds | S78: -64474830 | T78: -65532292 | U78: -66117057 | V78: -68912250 | X78: =S78-E78 -> -1210395 | Y78: =T78-F78 -> 0 | Z78: =U78-G78 -> 0 | AA78: =V78-H78 -> 1
A79: T08 Overige baten en lasten.xlsx | B79: T08 | C79: Overige baten en lasten | D79: B | E79: ='T08'!K61 -> -48485 | F79: ='T08'!L61 -> -49489 | G79: ='T08'!M61 -> -50611 | H79: ='T08'!N61 -> -51760 | I79: ='T08'!O61 -> -52935 | J79: -48485 | K79: =J79-E79 -> 0 | L79: -49536 | M79: =L79-F79 -> -47 | N79: -50611 | O79: =N79-G79 -> 0 | P79: -51709 | Q79: =P79-H79 -> 51 | R79: 08 - Overige baten en lasten | S79: -48485 | T79: -49536 | U79: -50611 | V79: -51709 | X79: =S79-E79 -> 0 | Y79: =T79-F79 -> -47 | Z79: =U79-G79 -> 0 | AA79: =V79-H79 -> 51
A80: T09 Vennootschapsbelasting.xlsx | B80: T09 | C80: Vennootschapsbelasting | D80: B | E80: ='T09'!K52 -> 0 | F80: ='T09'!L52 -> 0 | G80: ='T09'!M52 -> 0 | H80: ='T09'!N52 -> 0 | I80: ='T09'!O52 -> 0 | J80: 0 | K80: =J80-E80 -> 0 | L80: 0 | M80: =L80-F80 -> 0 | N80: 0 | O80: =N80-G80 -> 0 | P80: 0 | Q80: =P80-H80 -> 0 | X80: =S80-E80 -> 0 | Y80: =T80-F80 -> 0 | Z80: =U80-G80 -> 0 | AA80: =V80-H80 -> 0
A81: T010 Mutaties Reserve.xlsx | B81: T010 | C81: Mutaties reserves | D81: B | E81: ='T010'!K27 -> -9500031 | F81: ='T010'!L27 -> -4464327 | G81: ='T010'!M27 -> -2208156 | H81: ='T010'!N27 -> -2363911 | I81: ='T010'!O27 -> 0 | J81: -5174031 | K81: =J81-E81 -> 4326000 | L81: -4439327 | M81: =L81-F81 -> 25000 | N81: -2183156 | O81: =N81-G81 -> 25000 | P81: -2338911 | Q81: =P81-H81 -> 25000 | R81: 010 - Mutaties reserves | S81: -9325031 | T81: -4439327 | U81: -5550656 | V81: -5631411 | X81: =S81-E81 -> 175000 | Y81: =T81-F81 -> 25000 | Z81: =U81-G81 -> -3342500 | AA81: =V81-H81 -> -3267500
A82: T011 Resultaat rekening baten en lasten.xlsx | B82: T011 | C82: Resultaat van de rekening van baten en lasten | D82: B | E82: ='T011'!K49 -> 0 | F82: ='T011'!L49 -> 0 | G82: ='T011'!M49 -> 0 | H82: ='T011'!N49 -> 0 | I82: ='T011'!O49 -> 0 | J82: 0 | K82: =J82-E82 -> 0 | L82: 0 | M82: =L82-F82 -> 0 | N82: 0 | O82: =N82-G82 -> 0 | P82: 0 | Q82: =P82-H82 -> 0 | X82: =S82-E82 -> 0 | Y82: =T82-F82 -> 0 | Z82: =U82-G82 -> 0 | AA82: =V82-H82 -> 0
A83: T11 crisisbeheersing en brandweer.xlsx | B83: T11 | C83: Crisisbeheersing en brandweer | D83: B | E83: ='T11'!K57 -> -109768 | F83: ='T11'!L57 -> -112837.49 | G83: ='T11'!M57 -> -115433 | H83: ='T11'!N57 -> -118088 | I83: ='T11'!O57 -> -120804 | J83: -109768 | K83: =J83-E83 -> 0 | L83: -112183 | M83: =L83-F83 -> 654.49 | N83: -114651 | O83: =N83-G83 -> 782 | P83: -117173 | Q83: =P83-H83 -> 915 | R83: 11 - Crisisbeheersing en brandweer | S83: -109768 | T83: -112183 | U83: -114651 | V83: -117173 | X83: =S83-E83 -> 0 | Y83: =T83-F83 -> 654.49 | Z83: =U83-G83 -> 782 | AA83: =V83-H83 -> 915
A84: T12 openbare orde en veiligheid.xlsx | B84: T12 | C84: Openbare orde en veiligheid | D84: B | E84: ='T12'!K72 -> -177559 | F84: ='T12'!L72 -> -183276 | G84: ='T12'!M72 -> -188872 | H84: ='T12'!N72 -> -194649 | I84: ='T12'!O72 -> -200611 | J84: -177559 | K84: =J84-E84 -> 0 | L84: -183738 | M84: =L84-F84 -> -462 | N84: -190157 | O84: =N84-G84 -> -1285 | P84: -196826 | Q84: =P84-H84 -> -2177 | R84: 12 - Openbare orde en veiligheid | S84: -177559 | T84: -183738 | U84: -190157 | V84: -196826 | X84: =S84-E84 -> 0 | Y84: =T84-F84 -> -462 | Z84: =U84-G84 -> -1285 | AA84: =V84-H84 -> -2177
A85: T21 Verkeer en vervoer.xlsx | B85: T21 | C85: Verkeer en vervoer | D85: B | E85: ='T21'!K79 -> -544578 | F85: ='T21'!L79 -> -527968 | G85: ='T21'!M79 -> -556996 | H85: ='T21'!N79 -> -586680 | I85: ='T21'!O79 -> -616801 | J85: -544578 | K85: =J85-E85 -> 0 | L85: -528920 | M85: =L85-F85 -> -952 | N85: -559360 | O85: =N85-G85 -> -2364 | P85: -590583 | Q85: =P85-H85 -> -3903 | R85: 21 - Verkeer en vervoer | S85: -544578 | T85: -528920 | U85: -559360 | V85: -590583 | X85: =S85-E85 -> 0 | Y85: =T85-F85 -> -952 | Z85: =U85-G85 -> -2364 | AA85: =V85-H85 -> -3903
A86: T22 parkeren.xlsx | B86: T22 | C86: Parkeren | D86: B | E86: ='T22'!K39 -> -11835 | F86: ='T22'!L39 -> -9779.79 | G86: ='T22'!M39 -> -10005 | H86: ='T22'!N39 -> -10235 | I86: ='T22'!O39 -> -10470 | J86: -11835 | K86: =J86-E86 -> 0 | L86: -12095 | M86: =L86-F86 -> -2315.21 | N86: -12361 | O86: =N86-G86 -> -2356 | P86: -12633 | Q86: =P86-H86 -> -2398 | R86: 22 - Parkeren | S86: -11835 | T86: -12095 | U86: -12361 | V86: -12633 | X86: =S86-E86 -> 0 | Y86: =T86-F86 -> -2315.21 | Z86: =U86-G86 -> -2356 | AA86: =V86-H86 -> -2398
A87: T25 openbaar vervoer.xlsx | B87: T25 | C87: Openbaar vervoer | D87: B | E87: ='T25'!K40 -> -349 | F87: ='T25'!L40 -> -349 | G87: ='T25'!M40 -> -348 | H87: ='T25'!N40 -> -348 | I87: ='T25'!O40 -> -348 | J87: -349 | K87: =J87-E87 -> 0 | L87: -349 | M87: =L87-F87 -> 0 | N87: -348 | O87: =N87-G87 -> 0 | P87: -348 | Q87: =P87-H87 -> 0 | R87: 25 - Openbaar vervoer | S87: -349 | T87: -349 | U87: -348 | V87: -348 | X87: =S87-E87 -> 0 | Y87: =T87-F87 -> 0 | Z87: =U87-G87 -> 0 | AA87: =V87-H87 -> 0
A88: T31 economische ontwikkeling.xlsx | B88: T31 | C88: Economische ontwikkeling | D88: B | E88: ='T31'!K51 -> -143733 | F88: ='T31'!L51 -> -146751 | G88: ='T31'!M51 -> -150126 | H88: ='T31'!N51 -> -153578 | I88: ='T31'!O51 -> -157110 | J88: -143733 | K88: =J88-E88 -> 0 | L88: -146895 | M88: =L88-F88 -> -144 | N88: -150126 | O88: =N88-G88 -> 0 | P88: -153428 | Q88: =P88-H88 -> 150 | R88: 31 - Economische ontwikkeling | S88: -143733 | T88: -146895 | U88: -150126 | V88: -153428 | X88: =S88-E88 -> 0 | Y88: =T88-F88 -> -144 | Z88: =U88-G88 -> 0 | AA88: =V88-H88 -> 150
A89: T33 bedrijfsloket en bedrijfsregelingen.xlsx | B89: T33 | C89: Bedrijvenloket en bedrijvenregeling | D89: B | E89: ='T33'!K46 -> -28660 | F89: ='T33'!L46 -> -28708 | G89: ='T33'!M46 -> -29718 | H89: ='T33'!N46 -> -29769 | I89: ='T33'!O46 -> -29821 | J89: -28660 | K89: =J89-E89 -> 0 | L89: -28708 | M89: =L89-F89 -> 0 | N89: -29718 | O89: =N89-G89 -> 0 | P89: -29769 | Q89: =P89-H89 -> 0 | R89: 33 - Bedrijvenloket en bedrijfsregelingen | S89: -28660 | T89: -28708 | U89: -29718 | V89: -29769 | X89: =S89-E89 -> 0 | Y89: =T89-F89 -> 0 | Z89: =U89-G89 -> 0 | AA89: =V89-H89 -> 0
A90: T34 economische promotie.xlsx | B90: T34 | C90: Economische promotie | D90: B | E90: ='T34'!K73 -> -875019 | F90: ='T34'!L73 -> -887697 | G90: ='T34'!M73 -> -901330 | H90: ='T34'!N73 -> -915304 | I90: ='T34'!O73 -> -929628 | J90: -875019 | K90: =J90-E90 -> 0 | L90: -888427 | M90: =L90-F90 -> -730 | N90: -902184 | O90: =N90-G90 -> -854 | P90: -916298 | Q90: =P90-H90 -> -994 | R90: 34 - Economische promotie | S90: -875019 | T90: -888427 | U90: -902184 | V90: -916298 | X90: =S90-E90 -> 0 | Y90: =T90-F90 -> -730 | Z90: =U90-G90 -> -854 | AA90: =V90-H90 -> -994
A91: T42 onderwijshuisvesting.xlsx | B91: T42 | C91: Onderwijshuisvesting | D91: B | E91: ='T42'!K62 -> #REF! | F91: ='T42'!L62 -> #REF! | G91: ='T42'!M62 -> #REF! | H91: ='T42'!N62 -> #REF! | I91: ='T42'!O62 -> #REF! | J91: -80323 | K91: =J91-E91 -> #REF! | L91: -82085 | M91: =L91-F91 -> #REF! | N91: -83887 | O91: =N91-G91 -> #REF! | P91: -85733 | Q91: =P91-H91 -> #REF! | R91: 42 - Onderwijshuisvesting | S91: -80323 | T91: -82085 | U91: -634177 | V91: -636023 | X91: =S91-E91 -> #REF! | Y91: =T91-F91 -> #REF! | Z91: =U91-G91 -> #REF! | AA91: =V91-H91 -> #REF!
A92: T43 onderwijsbeleid en leerlingenzaken.xlsx | B92: T43 | C92: Onderwijsbeleid en leerlingenzaken | D92: B | E92: ='T43'!K50 -> -444540 | F92: ='T43'!L50 -> -419730 | G92: ='T43'!M50 -> -420010 | H92: ='T43'!N50 -> -420300 | I92: ='T43'!O50 -> -420590 | J92: -419480 | K92: =J92-E92 -> 25060 | L92: -419740 | M92: =L92-F92 -> -10 | N92: -420009 | O92: =N92-G92 -> 1 | P92: -420289 | Q92: =P92-H92 -> 11 | R92: 43 - Onderwijsbeleid en leerlingzaken | S92: -419480 | T92: -419740 | U92: -420009 | V92: -420289 | X92: =S92-E92 -> 25060 | Y92: =T92-F92 -> -10 | Z92: =U92-G92 -> 1 | AA92: =V92-H92 -> 11
A93: T51 Sportbeleid en activering.xlsx | B93: T51 | C93: Sportbeleid en activering | D93: B | E93: ='T51'!K59 -> -144004 | F93: ='T51'!L59 -> -144004 | G93: ='T51'!M59 -> -144004 | H93: ='T51'!N59 -> -144004 | I93: ='T51'!O59 -> -144004 | J93: -144004 | K93: =J93-E93 -> 0 | L93: -144004 | M93: =L93-F93 -> 0 | N93: -144004 | O93: =N93-G93 -> 0 | P93: -144004 | Q93: =P93-H93 -> 0 | R93: 51 - Sportbeleid en activering | S93: -144004 | T93: -144004 | U93: -144004 | V93: -144004 | X93: =S93-E93 -> 0 | Y93: =T93-F93 -> 0 | Z93: =U93-G93 -> 0 | AA93: =V93-H93 -> 0
A94: T52 Sportaccommodaties.xlsx | B94: T52 | C94: Sportaccommodaties | D94: B | E94: ='T52'!K99 -> -878101.62 | F94: ='T52'!L99 -> -862779.89 | G94: ='T52'!M99 -> -871864.49 | H94: ='T52'!N99 -> -880875.43 | I94: ='T52'!O99 -> -893583.99 | J94: -878101.62 | K94: =J94-E94 -> 0 | L94: -843594.43 | M94: =L94-F94 -> 19185.464 | N94: -853009.99 | O94: =N94-G94 -> 18854.493 | P94: -862665.59 | Q94: =P94-H94 -> 18209.844 | R94: 52 - Sportaccommodaties | S94: -878103 | T94: -843594 | U94: -853011 | V94: -862666 | X94: =S94-E94 -> -1.3812866 | Y94: =T94-F94 -> 19185.892 | Z94: =U94-G94 -> 18853.485 | AA94: =V94-H94 -> 18209.43
A95: T53 cultuurpresentatie,product,particip.xlsx | B95: T53 | C95: Cultuurproductie, presentatie en participatie | D95: B | E95: ='T53'!K57 -> -531 | F95: ='T53'!L57 -> -16701.01 | G95: ='T53'!M57 -> -17310.8 | H95: ='T53'!N57 -> -17943.8 | I95: ='T53'!O57 -> -18599.6 | J95: -531 | K95: =J95-E95 -> 0 | L95: -16760.2 | M95: =L95-F95 -> -59.19 | N95: -17518.2 | O95: =N95-G95 -> -207.4 | P95: -18310.6 | Q95: =P95-H95 -> -366.8 | R95: 53 - Cultuurpresentatie,-productie,-participatie | S95: -531 | T95: -16760 | U95: -17518 | V95: -18311 | X95: =S95-E95 -> 0 | Y95: =T95-F95 -> -58.99 | Z95: =U95-G95 -> -207.2 | AA95: =V95-H95 -> -367.2
A96: T54 Musea.xlsx | B96: T54 | C96: Musea | D96: B | E96: ='T54'!K40 -> 0 | F96: ='T54'!L40 -> 0 | G96: ='T54'!M40 -> 0 | H96: ='T54'!N40 -> 0 | I96: ='T54'!O40 -> 0 | J96: 0 | K96: =J96-E96 -> 0 | L96: 0 | M96: =L96-F96 -> 0 | N96: 0 | O96: =N96-G96 -> 0 | P96: 0 | Q96: =P96-H96 -> 0 | S96: 0 | T96: 0 | U96: 0 | V96: 0 | X96: =S96-E96 -> 0 | Y96: =T96-F96 -> 0 | Z96: =U96-G96 -> 0 | AA96: =V96-H96 -> 0
A97: T55 Cultureel erfgoed.xlsx | B97: T55 | C97: Cultureel erfgoed | D97: B | E97: ='T55'!K43 -> 0 | F97: ='T55'!L43 -> 0 | G97: ='T55'!M43 -> 0 | H97: ='T55'!N43 -> 0 | I97: ='T55'!O43 -> 0 | J97: 0 | K97: =J97-E97 -> 0 | L97: 0 | M97: =L97-F97 -> 0 | N97: 0 | O97: =N97-G97 -> 0 | P97: 0 | Q97: =P97-H97 -> 0 | X97: =S97-E97 -> 0 | Y97: =T97-F97 -> 0 | Z97: =U97-G97 -> 0 | AA97: =V97-H97 -> 0
A98: T56 Media.xlsx | B98: T56 | C98: Media | D98: B | E98: ='T56'!K43 -> -199108 | F98: ='T56'!L43 -> -205871.36 | G98: ='T56'!M43 -> -211833 | H98: ='T56'!N43 -> -217966 | I98: ='T56'!O43 -> -219127 | J98: -199108 | K98: =J98-E98 -> 0 | L98: -204683 | M98: =L98-F98 -> 1188.36 | N98: -210414 | O98: =N98-G98 -> 1419 | P98: -216306 | Q98: =P98-H98 -> 1660 | R98: 56 - Media | S98: -199108 | T98: -204683 | U98: -210414 | V98: -216306 | X98: =S98-E98 -> 0 | Y98: =T98-F98 -> 1188.36 | Z98: =U98-G98 -> 1419 | AA98: =V98-H98 -> 1660
A99: T57 openbaar groen,(openlucht) recreatie.xlsx | B99: T57 | C99: Openbaar groen en (openlucht) recreatie | D99: B | E99: ='T57'!K66 -> -189905 | F99: ='T57'!L66 -> -221828 | G99: ='T57'!M66 -> -190223 | H99: ='T57'!N66 -> -127019 | I99: ='T57'!O66 -> -128647 | J99: -189905 | K99: =J99-E99 -> 0 | L99: -222914 | M99: =L99-F99 -> -1086 | N99: -191267 | O99: =N99-G99 -> -1044 | P99: -128021 | Q99: =P99-H99 -> -1002 | R99: 57 - Openbaar groen en recreatie | S99: -189905 | T99: -222914 | U99: -191267 | V99: -128021 | X99: =S99-E99 -> 0 | Y99: =T99-F99 -> -1086 | Z99: =U99-G99 -> -1044 | AA99: =V99-H99 -> -1002
A100: T61 samenkracht en burgerparticipatie.xlsx | B100: T61 | C100: Samenkracht en burgerparticipatie | D100: B | E100: ='T61'!K85 -> -887609.1 | F100: ='T61'!L85 -> -909554.77 | G100: ='T61'!M85 -> -926963 | H100: ='T61'!N85 -> -944757 | I100: ='T61'!O85 -> -962953 | J100: -887609.1 | K100: =J100-E100 -> 0 | L100: -903763 | M100: =L100-F100 -> 5791.77 | N100: -920269 | O100: =N100-G100 -> 6694 | P100: -937138 | Q100: =P100-H100 -> 7619 | R100: 61 - Samenkracht en burgerparticipatie | S100: -887608 | T100: -903763 | U100: -920269 | V100: -937138 | X100: =S100-E100 -> 1.102 | Y100: =T100-F100 -> 5791.77 | Z100: =U100-G100 -> 6694 | AA100: =V100-H100 -> 7619
A101: T62 2 toegang en eerstelijnsvoorzieningen Jeugd.xlsx | B101: T622 | C101: Toegang en eerstelijnsvoorzieningen jeugd | D101: B | E101: =#REF! -> #REF! | F101: =#REF! -> #REF! | G101: =#REF! -> #REF! | H101: =#REF! -> #REF! | I101: =#REF! -> #REF! | J101: 0 | K101: =J101-E101 -> #REF! | L101: 0 | M101: =L101-F101 -> #REF! | N101: 0 | O101: =N101-G101 -> #REF! | P101: 0 | Q101: =P101-H101 -> #REF! | R101: 66 - Maatwerkvoorzieningen (WMO) | X101: =S101-E101 -> #REF! | Y101: =T101-F101 -> #REF! | Z101: =U101-G101 -> #REF! | AA101: =V101-H101 -> #REF!
A102: T62 3 toegang en eerstelijnsvoorzieningen Integraal.xlsx | B102: T623 | C102: Toegang en eerstelijnsvoorzieningen integraal | D102: B | E102: =#REF! -> #REF! | F102: =#REF! -> #REF! | G102: =#REF! -> #REF! | H102: =#REF! -> #REF! | I102: =#REF! -> #REF! | J102: -117736 | K102: =J102-E102 -> #REF! | L102: -120326 | M102: =L102-F102 -> #REF! | N102: -122973 | O102: =N102-G102 -> #REF! | P102: -125679 | Q102: =P102-H102 -> #REF! | R102: 623 - Toegang en eerstelijnsvoorzieningen Integraal | S102: -117736 | T102: -120326 | U102: -122973 | V102: -125679 | X102: =S102-E102 -> #REF! | Y102: =T102-F102 -> #REF! | Z102: =U102-G102 -> #REF! | AA102: =V102-H102 -> #REF!
...

Sheet T01
A1: Inhoudsopgave | Q1: 2024 | R1: 2025 | S1: 2026 | T1: 2027 | U1: 2028 | V1: 2029 | W1: 2030
D2: Programma | H2: 01. Algemeen bestuur | Q2: =+Indexering!G4 -> 1.037 | R2: =+Indexering!H4 -> 1.028 | S2: =+Indexering!I4 -> 1.026 | T2: =+Indexering!J4 -> 1.021 | U2: =+Indexering!K4 -> 1.023 | V2: =+Indexering!L4 -> 1.023 | W2: =+Indexering!M4 -> 1.023
Q3: =+Indexering!G5 -> 1.052 | R3: =+Indexering!H5 -> 1.049 | S3: =+Indexering!I5 -> 1.02 | T3: =+Indexering!J5 -> 1.042 | U3: =+Indexering!K5 -> 1.037 | V3: =+Indexering!L5 -> 1.037 | W3: =+Indexering!M5 -> 1.037
S4: =+Indexering!I6 -> 1.02282 | T4: =+Indexering!J6 -> 1.03213 | U4: =+Indexering!K6 -> 1.03042 | V4: =+Indexering!L6 -> 1.03042 | W4: =+Indexering!M6 -> 1.03042
D6: Taakveld | H6: T01 Bestuur en ondersteuning
D30: In te zetten middelen
D32: Lasten in € (+) | J32: 2025 | K32: 2026 | L32: 2027 | M32: 2028 | N32: 2029 | O32: 2030
D33: Raad en raadscommissies | J33: 97488 | K33: =K82 -> 104686 | L33: =L82 -> 96506 | M33: =M82 -> 98542 | N33: =N82 -> 100624 | O33: =O82 -> 102754
D34: Raadsfracties | J34: 7716.168 | K34: =K87 -> 7916.7884 | L34: =L87 -> 8083.0409 | M34: =M87 -> 8268.9509 | N34: =N87 -> 8459.1367 | O34: =O87 -> 8653.6969
D35: Reis- en verblijfkosten raad | J35: 17077 | K35: =K92 -> 17522 | L35: =L92 -> 17890 | M35: =M92 -> 18301 | N35: =N92 -> 18721 | O35: =O92 -> 19152
D36: =G94 -> Communicatieplan gemeenteraad | J36: 4085 | K36: =K97 -> 4191 | L36: =L97 -> 4279 | M36: =M97 -> 4377 | N36: =N97 -> 4478 | O36: =O97 -> 4581
D37: Werkbudget griffie | J37: 22939 | K37: =K103 -> 23922 | L37: =L103 -> 24508 | M37: =M103 -> 25164 | N37: =N103 -> 25835 | O37: =O103 -> 26521
D38: =G105 -> Rekenkamerfunctie | J38: 41778 | K38: =K108 -> 43712 | L38: =L108 -> 45231 | M38: =M108 -> 47118 | N38: =N108 -> 48879.5 | O38: =O108 -> 49890.8
D39: Gemeentefinanciën | J39: 69833 | K39: =K113 -> 70000 | L39: =L113 -> 71470 | M39: =M113 -> 73114 | N39: =N113 -> 74796 | O39: =O113 -> 76516
D40: =G120 -> Directe toerekening raad | J40: 0 | K40: =K123 -> 0 | L40: =L123 -> 0 | M40: =M123 -> 0 | N40: =N123 -> 0 | O40: =O123 -> 0
D41: Jeugdraad | J41: 1684.892 | K41: =+K118 -> 1728.6992 | L41: =+L118 -> 1765.0019 | M41: =+M118 -> 1805.5969 | N41: =+N118 -> 1847.1256 | O41: =+O118 -> 1889.6095
D42: =G125 -> Gewezen burgemeester | J42: 88189 | K42: =K128 -> 117492 | L42: =L128 -> 119842 | M42: =M128 -> 50933 | N42: =N128 -> 0 | O42: =O128 -> 0
D43: =G130 -> Gewezen college | J43: 171730 | K43: =K133 -> 178593 | L43: =L133 -> 189339 | M43: =M133 -> 195577 | N43: =N133 -> 199488 | O43: =O133 -> 0
D44: =G135 -> College van B&W | J44: 48471 | K44: =K141 -> 18740 | L44: =L141 -> 19134 | M44: =M141 -> 19573 | N44: =N141 -> 20023 | O44: =O141 -> 20485
D45: =G148 -> Directe toerekening college | J45: 0 | K45: =K151 -> 0 | L45: =L151 -> 0 | M45: =M151 -> 0 | N45: =N151 -> 0 | O45: =O151 -> 0
D46: broodjes, bloemen ed | J46: 23541 | K46: =+K146 -> 24153 | L46: =+L146 -> 24660 | M46: =+M146 -> 25227 | N46: =+N146 -> 25807 | O46: =+O146 -> 26401
D47: =G153 -> Representatie | J47: 34813 | K47: =K157 -> 35717 | L47: =L157 -> 36468 | M47: =M157 -> 37307 | N47: =N157 -> 38166 | O47: =O157 -> 39046
D48: Metropoolregio Eindhoven | J48: 306624 | K48: =K172 -> 321495 | L48: =L172 -> 339457 | M48: =M172 -> 354094 | N48: =N172 -> 372394.66 | O48: =O172 -> 385904.18
D49: Actieplan Regio Eindhoven | J49: 78557 | K49: =K177 -> 79636 | L49: =L177 -> 84274 | M49: =M177 -> 87272.28 | N49: =N177 -> 92279.142 | O49: =O177 -> 95696.888
D50: Regionale projecten | J50: 29281 | K50: =K182 -> 29867 | L50: =L182 -> 31121 | M50: =M182 -> 32272 | N50: =N182 -> 33466 | O50: =O182 -> 34704
D51: Convenant SGE | J51: 26628 | K51: =K188 -> 27321 | L51: =L188 -> 27895 | M51: =M188 -> 28537 | N51: =N188 -> 29193 | O51: =O188 -> 29864
D52: Project voorzieningen SGE | J52: 0 | K52: =K193 -> 0 | L52: =L193 -> 0 | M52: =M193 -> 0 | N52: =N193 -> 0 | O52: =O193 -> 0
D53: Challenge ontsluiting | J53: 0 | K53: =K198 -> 0 | L53: =L198 -> 0 | M53: =M198 -> 0 | N53: =N198 -> 0 | O53: =O198 -> 0
D54: Samenwerking Best-Oirschot | J54: 305000 | K54: =+K203 -> 688130 | L54: =+L203 -> 5238 | M54: =+M203 -> 5358 | N54: =+N203 -> 5481 | O54: =+O203 -> 5607
D55: Directe toerekening bestuur | J55: 1433816 | K55: =K209 -> 1508457.5 | L55: =L209 -> 1571604 | M55: =M209 -> 1629568 | N55: =N209 -> 1689677 | O55: =O209 -> 1747010
D56: Directe toerekening regionale samenwerking | J56: 165249.64 | K56: =K215 -> 792976.63 | L56: =L215 -> 800242 | M56: =M215 -> 686911 | N56: =N215 -> 693827 | O56: =O215 -> 700999
D59: Totaal lasten | J59: 2974500.7 | K59: =SUM(K33:K58) -> 4096256.6 | L59: =SUM(L33:L58) -> 3519006 | M59: =SUM(M33:M58) -> 3429319.8 | N59: =SUM(N33:N58) -> 3483441.6 | O59: =SUM(O33:O58) -> 3375675.2
D62: Baten in € (-) | J62: 2025 | K62: 2026 | L62: =+L32 -> 2027 | M62: =+M32 -> 2028 | N62: =+N32 -> 2029 | O62: =+O32 -> 2030
D64: =G159 -> Gewezen bestuurders | J64: -88189 | K64: =K162 -> -117492 | L64: =L162 -> -119842 | M64: =M162 -> -50933 | N64: =N162 -> 0 | O64: =O162 -> 0
D65: =G164 -> Gewezen bestuurders | J65: -171730 | K65: =K167 -> -178593 | L65: =L167 -> -189339 | M65: =M167 -> -195577 | N65: =N167 -> -199488 | O65: =O167 -> 0
D68: Totaal baten | J68: -259919 | K68: =SUM(K64:K67) -> -296085 | L68: =SUM(L64:L67) -> -309181 | M68: =SUM(M64:M67) -> -246510 | N68: =SUM(N64:N67) -> -199488 | O68: =SUM(O64:O67) -> 0
D70: Saldo voor bijdragen en stortingen in reserves (+ = nadeel) | J70: 2714581.7 | K70: =K59+K68 -> 3800171.6 | L70: =L59+L68 -> 3209825 | M70: =M59+M68 -> 3182809.8 | N70: =N59+N68 -> 3283953.6 | O70: =O59+O68 -> 3375675.2
D74: Financiële toelichting
D76: Grootb/cat t/m 2019 | E76: Bbv Taakv/ | F76: Grootb/cat nummer | G76: Omschrijving
E77: Bbv cat | J77: 2025 | K77: 2026 | L77: =+L32 -> 2027 | M77: =+M32 -> 2028 | N77: =+N32 -> 2029 | O77: =+O32 -> 2030
D78: 601001 | G78: Raad en raadscommissies
G79: Lasten
A80: =+D78 -> 601001 | B80: =+G78 -> Raad en raadscommissies | D80: 43819 | G80: Studie en opleiding | J80: 9573 | K80: 9822 | L80: =+L225 -> 10028 | M80: =+M225 -> 10259 | N80: =+N225 -> 10495 | O80: =+O225 -> 10736
A81: =+D78 -> 601001 | B81: =G78 -> Raad en raadscommissies | D81: 43812 | G81: Overige goederen en diensten | J81: 87915 | K81: 94864 | L81: =L242 -> 86478 | M81: =M242 -> 88283 | N81: =N242 -> 90129 | O81: =O242 -> 92018
G82: Totaal | J82: 97488 | K82: 104686 | L82: =SUM(L80:L81) -> 96506 | M82: =SUM(M80:M81) -> 98542 | N82: =SUM(N80:N81) -> 100624 | O82: =SUM(O80:O81) -> 102754
D84: 601001 | G84: Raadsfracties
G85: Lasten
A86: =+D84 -> 601001 | B86: =+G84 -> Raadsfracties | D86: 43812 | G86: Overige goederen en diensten | J86: 7716.168 | K86: 7916.7884 | L86: =+L255 -> 8083.0409 | M86: =+M255 -> 8268.9509 | N86: =+N255 -> 8459.1367 | O86: =+O255 -> 8653.6969
G87: Totaal | J87: 7716.168 | K87: 7916.7884 | L87: =SUM(L85:L86) -> 8083.0409 | M87: =SUM(M85:M86) -> 8268.9509 | N87: =SUM(N85:N86) -> 8459.1367 | O87: =SUM(O85:O86) -> 8653.6969
D89: 601001 | G89: Reis- en verblijfskosten raad
G90: Lasten
A91: =+D89 -> 601001 | B91: =+G89 -> Reis- en verblijfskosten raad | D91: 43812 | G91: Overige goederen en diensten | J91: 17077 | K91: 17522 | L91: =+L277 -> 17890 | M91: =+M277 -> 18301 | N91: =+N277 -> 18721 | O91: =+O277 -> 19152
G92: Totaal | J92: 17077 | K92: 17522 | L92: =SUM(L90:L91) -> 17890 | M92: =SUM(M90:M91) -> 18301 | N92: =SUM(N90:N91) -> 18721 | O92: =SUM(O90:O91) -> 19152
D94: 601001 | G94: Communicatieplan gemeenteraad
G95: Lasten
A96: =+D94 -> 601001 | B96: =+G94 -> Communicatieplan gemeenteraad | D96: 43812 | G96: Overige goederen en diensten | J96: 4085 | K96: 4191 | L96: =+L280 -> 4279 | M96: =+M280 -> 4377 | N96: =+N280 -> 4478 | O96: =+O280 -> 4581
G97: Totaal | J97: 4085 | K97: 4191 | L97: =SUM(L95:L96) -> 4279 | M97: =SUM(M95:M96) -> 4377 | N97: =SUM(N95:N96) -> 4478 | O97: =SUM(O95:O96) -> 4581
D99: 601002 | G99: Werkbudget griffie
G100: Lasten
A101: =+D99 -> 601002 | B101: =G99 -> Werkbudget griffie | D101: 43819 | G101: Studie en opleiding | J101: 11538 | K101: 12121 | L101: =+L287 -> 12375 | M101: =+M287 -> 12660 | N101: =+N287 -> 12951 | O101: =+O287 -> 13249
A102: =+D99 -> 601002 | B102: =G99 -> Werkbudget griffie | D102: 43812 | G102: Overige goederen en diensten | J102: 11401 | K102: 11801 | L102: =+L296 -> 12133 | M102: =+M296 -> 12504 | N102: =+N296 -> 12884 | O102: =+O296 -> 13272
G103: Totaal | J103: 22939 | K103: 23922 | L103: =SUM(L100:L102) -> 24508 | M103: =SUM(M100:M102) -> 25164 | N103: =SUM(N100:N102) -> 25835 | O103: =SUM(O100:O102) -> 26521
D105: 601003 | G105: Rekenkamerfunctie
G106: Lasten
A107: =+D105 -> 601003 | B107: =+G105 -> Rekenkamerfunctie | D107: 43812 | G107: Overige goederen en diensten | J107: 41778 | K107: 43712 | L107: =+L314 -> 45231 | M107: =+M314 -> 47118 | N107: =+N314 -> 48879.5 | O107: =+O314 -> 49890.8
G108: Totaal | J108: 41778 | K108: 43712 | L108: =SUM(L106:L107) -> 45231 | M108: =SUM(M106:M107) -> 47118 | N108: =SUM(N106:N107) -> 48879.5 | O108: =SUM(O106:O107) -> 49890.8
D110: 601004 | G110: Gemeentefinanciën
G111: Lasten
A112: =+D110 -> 601004 | B112: =+G110 -> Gemeentefinanciën | D112: 43812 | G112: Overige goederen en diensten | J112: 69833 | K112: 70000 | L112: =+L323 -> 71470 | M112: =+M323 -> 73114 | N112: =+N323 -> 74796 | O112: =+O323 -> 76516
G113: Totaal | J113: 69833 | K113: 70000 | L113: =SUM(L111:L112) -> 71470 | M113: =SUM(M111:M112) -> 73114 | N113: =SUM(N111:N112) -> 74796 | O113: =SUM(O111:O112) -> 76516
D115: 601005 | G115: Jeugdraad
G116: Lasten
A117: 601005 | B117: =+G115 -> Jeugdraad | D117: 43812 | G117: Overige goederen en diensten | J117: 1684.892 | K117: 1728.6992 | L117: =+L328 -> 1765.0019 | M117: =+M328 -> 1805.5969 | N117: =+N328 -> 1847.1256 | O117: =+O328 -> 1889.6095
G118: Totaal | J118: 1684.892 | K118: 1728.6992 | L118: =SUM(L116:L117) -> 1765.0019 | M118: =SUM(M116:M117) -> 1805.5969 | N118: =SUM(N116:N117) -> 1847.1256 | O118: =SUM(O116:O117) -> 1889.6095
D120: 601901 | G120: Directe toerekening raad
G121: Lasten
A122: =+D120 -> 601901 | B122: =+G120 -> Directe toerekening raad | D122: 41000 | G122: Jaarwedden etc. | J122: 0 | K122: 0 | L122: 0 | M122: 0 | N122: 0 | O122: 0
J123: 0 | K123: 0 | L123: =SUM(L121:L122) -> 0 | M123: =SUM(M121:M122) -> 0 | N123: =SUM(N121:N122) -> 0 | O123: =SUM(O121:O122) -> 0
D125: 601007 | G125: Gewezen burgemeester
G126: Lasten
A127: =+D125 -> 601007 | B127: =+G125 -> Gewezen burgemeester | D127: 41101 | G127: Uitkering voormalig personeel | J127: 88189 | K127: 117492 | L127: =+L333 -> 119842 | M127: =+M333 -> 50933 | N127: =+N333 -> 0 | O127: =+O333 -> 0
G128: Totaal | J128: 88189 | K128: 117492 | L128: =SUM(L127:L127) -> 119842 | M128: =SUM(M127:M127) -> 50933 | N128: =SUM(N127:N127) -> 0 | O128: =SUM(O127:O127) -> 0
D130: 601007 | G130: Gewezen college
G131: Lasten
A132: =+D130 -> 601007 | B132: =+G130 -> Gewezen college | D132: 41101 | G132: Uitkering voormalig personeel | J132: 171730 | K132: 178593 | L132: =+L340 -> 189339 | M132: =+M340 -> 195577 | N132: =+N340 -> 199488 | O132: =+O340 -> 0
G133: Totaal | J133: 171730 | K133: 178593 | L133: =SUM(L132:L132) -> 189339 | M133: =SUM(M132:M132) -> 195577 | N133: =SUM(N132:N132) -> 199488 | O133: =SUM(O132:O132) -> 0
D135: 601008 | G135: College van B&W
G136: Lasten
A137: =+D135 -> 601008 | B137: =+G135 -> College van B&W | D137: 43806 | G137: Verzekeringen | J137: 4736 | K137: 6700 | L137: =L351 -> 6841 | M137: =M351 -> 6998 | N137: =N351 -> 7158 | O137: =O351 -> 7323
A138: 601008 | B138: College van B&W | D138: 43812 | G138: Overige goederen en diensten | J138: 35193 | K138: 3276 | L138: =+L360 -> 3345 | M138: =+M360 -> 3422 | N138: =+N360 -> 3501 | O138: =+O360 -> 3582
A139: 601008 | B139: College van B&W | D139: 43819 | G139: Studie en opleiding | J139: 5701 | K139: 5849 | L139: =L355 -> 5972 | M139: =M355 -> 6109 | N139: =N355 -> 6250 | O139: =O355 -> 6394
A140: 601008 | B140: College van B&W | D140: 43818 | G140: Werkkostenregeling (reis-/verblijfskosten) | J140: 2841 | K140: 2915 | L140: =L365 -> 2976 | M140: =M365 -> 3044 | N140: =N365 -> 3114 | O140: =O365 -> 3186
G141: Totaal | J141: 48471 | K141: 18740 | L141: =SUM(L137:L140) -> 19134 | M141: =SUM(M137:M140) -> 19573 | N141: =SUM(N137:N140) -> 20023 | O141: =SUM(O137:O140) -> 20485
D143: 601011 | G143: Broodjes, bloemen ed
G144: Lasten
A145: 601011 | B145: =G143 -> Broodjes, bloemen ed | D145: 43812 | G145: Werkkostenregeling (broodjes ed) | J145: 23541 | K145: 24153 | L145: =+L397 -> 24660 | M145: =+M397 -> 25227 | N145: =+N397 -> 25807 | O145: =+O397 -> 26401
G146: Totaal | J146: 23541 | K146: 24153 | L146: =SUM(L145) -> 24660 | M146: =SUM(M145) -> 25227 | N146: =SUM(N145) -> 25807 | O146: =SUM(O145) -> 26401
D148: 601901 | G148: Directe toerekening college
G149: Lasten
A150: =+D148 -> 601901 | B150: =+G148 -> Directe toerekening college | D150: 41000 | G150: Jaarwedden etc. | J150: 0 | K150: 0 | L150: 0 | M150: 0 | N150: 0 | O150: 0
...

Sheet T02
Q1: 2024 | R1: 2025 | S1: 2026 | T1: 2027 | U1: 2028 | V1: 2029 | W1: 2030
D2: Programma | H2: 01. Algemeen Bestuur | Q2: =+Indexering!G4 -> 1.037 | R2: =+Indexering!H4 -> 1.028 | S2: =+Indexering!I4 -> 1.026 | T2: =+Indexering!J4 -> 1.021 | U2: =+Indexering!K4 -> 1.023 | V2: =+Indexering!L4 -> 1.023 | W2: =+Indexering!M4 -> 1.023
Q3: =+Indexering!G5 -> 1.052 | R3: =+Indexering!H5 -> 1.049 | S3: =+Indexering!I5 -> 1.02 | T3: =+Indexering!J5 -> 1.042 | U3: =+Indexering!K5 -> 1.037 | V3: =+Indexering!L5 -> 1.037 | W3: =+Indexering!M5 -> 1.037
S4: =+Indexering!I6 -> 1.02282 | T4: =+Indexering!J6 -> 1.03213 | U4: =+Indexering!K6 -> 1.03042 | V4: =+Indexering!L6 -> 1.03042 | W4: =+Indexering!M6 -> 1.03042
D5: Budgethouder
D6: Taakveld | H6: T02 burgerzaken
D24: In te zetten middelen
D26: Lasten in € (+) | J26: 2025 | K26: 2026 | L26: 2027 | M26: 2028 | N26: 2029 | O26: 2030
D27: =G92 -> Huwelijken (1) | J27: 2696 | K27: 2762 | L27: =L95 -> 2824 | M27: =M95 -> 2888 | N27: =N95 -> 2953 | O27: =O95 -> 2978
D28: =G97 -> Directe toerekening burgelijke stand (1) | J28: 33098 | K28: 100258.11 | L28: =L100 -> 104469 | M28: =M100 -> 108334 | N28: =N100 -> 112342 | O28: =O100 -> 116499
D29: =G102 -> Reisdocumenten (2) | J29: 151352.3 | K29: 259645.5 | L29: =L105 -> 268069 | M29: =M105 -> 277732.5 | N29: =N105 -> 287720 | O29: =O105 -> 298109
D30: =G107 -> Directe toerekening reisdocumenten (2) | J30: 203260.6 | K30: 133135.84 | L30: =L111 -> 138728 | M30: =M111 -> 143861 | N30: =N111 -> 149184 | O30: =O111 -> 154704
D31: =G113 -> Rijbewijzen (3) | J31: 50027.9 | K31: 37540 | L31: =L116 -> 38311 | M31: =M116 -> 39102 | N31: =N116 -> 40098 | O31: =O116 -> 40298
D32: =G119 -> Directe toerekening rijbewijzen (3) | J32: 165678.96 | K32: 123799.24 | L32: =L123 -> 128999 | M32: =M123 -> 133772 | N32: =N123 -> 138721 | O32: =O123 -> 143854
D33: =G125 -> Directe toerekening (uitreksels uit de) brp (4) | J33: 231741 | K33: 264213.37 | L33: =L130 -> 272276 | M33: =M130 -> 280285 | N33: =N130 -> 288543 | O33: =O130 -> 297058
D34: =G132 -> Leges overige publiekszaken (5) | J34: 47803 | K34: 67673 | L34: =L136 -> 69177 | M34: =M136 -> 70823 | N34: =N136 -> 72515 | O34: =O136 -> 74125
D35: =G138 -> Directe toerekening leges overige publiekszaken (5) | J35: 42453 | K35: 40461.45 | L35: =L141 -> 42161 | M35: =M141 -> 43721 | N35: =N141 -> 45339 | O35: =O141 -> 47017
D36: =G143 -> Verkiezingen (6) | J36: 58371 | K36: 61895 | L36: =L147 -> 62867 | M36: =M147 -> 63975 | N36: =N147 -> 65100 | O36: =O147 -> 66242
D37: =G149 -> Directe toerekening verkiezingen (6) | J37: 4666.49 | K37: 7848 | L37: =L152 -> 8178 | M37: =M152 -> 8481 | N37: =N152 -> 8795 | O37: =O152 -> 9120
D38: =G154 -> Publiekszaken (7) | J38: 8959.349 | K38: 9825 | L38: =L157 -> 10033.915 | M38: =M157 -> 10269.255 | N38: =N157 -> 10508.168 | O38: =O157 -> 10750.736
D39: =G159 -> Directe toerekening publiekszaken (7) | J39: 160917.95 | K39: 169988.77 | L39: =L163 -> 159976 | M39: =M163 -> 165895 | N39: =N163 -> 172033 | O39: =O163 -> 178398
D41: Totaal lasten | J41: 1161025.5 | K41: 1279045.3 | L41: =SUM(L27:L40) -> 1306068.9 | M41: =SUM(M27:M40) -> 1349138.8 | N41: =SUM(N27:N40) -> 1393851.2 | O41: =SUM(O27:O40) -> 1439152.7
D43: Baten in € (-) | J43: 2025 | K43: 2026 | L43: 2027 | M43: 2028 | N43: 2029 | O43: 2030
D44: =G165 -> Huwelijken (1) | J44: -67872.7 | K44: -81724.78 | L44: =L168 -> -85081.4 | M44: =M168 -> -88154.4 | N44: =N168 -> -91346.9 | O44: =O168 -> -94661.8
D45: =G170 -> Reisdocumenten (2) | J45: -312150 | K45: -464175.5 | L45: =L173 -> -473936.5 | M45: =M173 -> -484625 | N45: =N173 -> -495845 | O45: =O173 -> -507069
D46: =G175 -> Rijbewijzen (3) | J46: -153729 | K46: -112340 | L46: =L178 -> -114711 | M46: =M178 -> -117302 | N46: =N178 -> -120098 | O46: =O178 -> -122898
D47: =G180 -> (Uitreksels uit de) brp (4) | J47: -9700 | K47: -14297.5 | L47: =L183 -> -14715 | M47: =M183 -> -15132.5 | N47: =N183 -> -15550 | O47: =O183 -> -15862.5
D48: =G185 -> Leges overige publiekszaken (5) | J48: -72121.5 | K48: -96931.5 | L48: =L188 -> -99261 | M48: =M188 -> -101783 | N48: =N188 -> -104365.5 | O48: =O188 -> -106330.5
D50: Totaal baten | J50: -615573.2 | K50: -769469.28 | L50: =SUM(L44:L49) -> -787704.9 | M50: =SUM(M44:M49) -> -806996.9 | N50: =SUM(N44:N49) -> -827205.4 | O50: =SUM(O44:O49) -> -846821.8
D52: Saldo baten en lasten | J52: 545452.35 | K52: 509576 | L52: =L41+L50 -> 518364.02 | M52: =M41+M50 -> 542141.86 | N52: =N41+N50 -> 566645.77 | O52: =O41+O50 -> 592330.94
D87: Financiële toelichting
D89: Grootb/cat nummer | E89: Bbv Taakv/ | F89: Grootb/cat t/m 2019 nummer | G89: Omschrijving
E90: Bbv cat | J90: 2025 | K90: 2026 | L90: 2027 | M90: 2028 | N90: 2029 | O90: 2030
D92: 602001 | G92: Huwelijken (1)
G93: Lasten
A94: =+D92 -> 602001 | B94: =G92 -> Huwelijken (1) | D94: 43812 | G94: Overige goederen en diensten | J94: 2696 | K94: 2762 | L94: =L211 -> 2824 | M94: =M211 -> 2888 | N94: =N211 -> 2953 | O94: =O211 -> 2978
G95: Totaal | J95: 2696 | K95: 2762 | L95: =SUM(L93:L94) -> 2824 | M95: =SUM(M93:M94) -> 2888 | N95: =SUM(N93:N94) -> 2953 | O95: =SUM(O93:O94) -> 2978
D97: 602901 | G97: Directe toerekening burgelijke stand (1)
G98: Lasten
A99: =+D97 -> 602901 | B99: =G97 -> Directe toerekening burgelijke stand (1) | D99: 41100 | G99: Salarissen | J99: 33098 | K99: 100258.11 | L99: =ROUND(K99*T$3,0) -> 104469 | M99: =ROUND(L99*U$3,0) -> 108334 | N99: =ROUND(M99*V$3,0) -> 112342 | O99: =ROUND(N99*W$3,0) -> 116499
G100: Totaal | J100: 33098 | K100: 100258.11 | L100: =SUM(L98:L99) -> 104469 | M100: =SUM(M98:M99) -> 108334 | N100: =SUM(N98:N99) -> 112342 | O100: =SUM(O98:O99) -> 116499
D102: 602002 | G102: Reisdocumenten (2)
G103: Lasten
A104: =+D102 -> 602002 | B104: =G102 -> Reisdocumenten (2) | D104: 44310 | G104: Inkomensoverdrachten aan het rijk | J104: 151352.3 | K104: 259645.5 | L104: =L261 -> 268069 | M104: =M261 -> 277732.5 | N104: =N261 -> 287720 | O104: =O261 -> 298109
G105: Totaal | J105: 151352.3 | K105: 259645.5 | L105: =SUM(L104:L104) -> 268069 | M105: =SUM(M104:M104) -> 277732.5 | N105: =SUM(N104:N104) -> 287720 | O105: =SUM(O104:O104) -> 298109
D107: 602902 | G107: Directe toerekening reisdocumenten (2)
G108: Lasten
A109: =+D107 -> 602902 | B109: =G107 -> Directe toerekening reisdocumenten (2) | D109: 41100 | G109: Salarissen | J109: 188764.6 | K109: 118349.84 | L109: =ROUND(K109*T$3,0) -> 123321 | M109: =ROUND(L109*U$3,0) -> 127884 | N109: =ROUND(M109*V$3,0) -> 132616 | O109: =ROUND(N109*W$3,0) -> 137523
A110: =+D107 -> 602902 | B110: =G107 -> Directe toerekening reisdocumenten (2) | D110: 43511 | G110: Inhuur personeel | J110: 14496 | K110: 14786 | L110: =L268 -> 15407 | M110: =M268 -> 15977 | N110: =N268 -> 16568 | O110: =O268 -> 17181
G111: Totaal | J111: 203260.6 | K111: 133135.84 | L111: =SUM(L109:L110) -> 138728 | M111: =SUM(M109:M110) -> 143861 | N111: =SUM(N109:N110) -> 149184 | O111: =SUM(O109:O110) -> 154704
D113: 602003 | G113: Rijbewijzen (3)
G114: Lasten
A115: =+D113 -> 602003 | B115: =G113 -> Rijbewijzen (3) | D115: 44310 | G115: Inkomensoverdrachten aan het rijk | J115: 50027.9 | K115: 37540 | L115: =L284 -> 38311 | M115: =M284 -> 39102 | N115: =N284 -> 40098 | O115: =O284 -> 40298
G116: Totaal | J116: 50027.9 | K116: 37540 | L116: =SUM(L115:L115) -> 38311 | M116: =SUM(M115:M115) -> 39102 | N116: =SUM(N115:N115) -> 40098 | O116: =SUM(O115:O115) -> 40298
D119: 602903 | G119: Directe toerekening rijbewijzen (3)
G120: Lasten
A121: =+D119 -> 602903 | B121: =G119 -> Directe toerekening rijbewijzen (3) | D121: 41100 | G121: Salarissen | J121: 158753.96 | K121: 116735.24 | L121: =ROUND(K121*T$3,0) -> 121638 | M121: =ROUND(L121*U$3,0) -> 126139 | N121: =ROUND(M121*V$3,0) -> 130806 | O121: =ROUND(N121*W$3,0) -> 135646
A122: =+D119 -> 602903 | B122: =G119 -> Directe toerekening rijbewijzen (3) | D122: 43511 | G122: Inhuur personeel | J122: 6925 | K122: 7064 | L122: =L288 -> 7361 | M122: =M288 -> 7633 | N122: =N288 -> 7915 | O122: =O288 -> 8208
G123: Totaal | J123: 165678.96 | K123: 123799.24 | L123: =SUM(L121:L122) -> 128999 | M123: =SUM(M121:M122) -> 133772 | N123: =SUM(N121:N122) -> 138721 | O123: =SUM(O121:O122) -> 143854
D125: 602904 | G125: Directe toerekening (uitreksels uit de) brp (4)
G126: Lasten
A127: =+D125 -> 602904 | B127: =G125 -> Directe toerekening (uitreksels uit de) brp (4) | D127: 41100 | G127: Salarissen | J127: 90928 | K127: 119739.37 | L127: =ROUND(K127*T$3,0) -> 124768 | M127: =ROUND(L127*U$3,0) -> 129384 | N127: =ROUND(M127*V$3,0) -> 134171 | O127: =ROUND(N127*W$3,0) -> 139135
A128: =+D125 -> 602904 | B128: =G125 -> Directe toerekening (uitreksels uit de) brp (4) | D128: 43812 | G128: Overige goederen en diensten | J128: 140813 | K128: 144474 | L128: =L291 -> 147508 | M128: =M291 -> 150901 | N128: =N291 -> 154372 | O128: =O291 -> 157923
G130: Totaal | J130: 231741 | K130: 264213.37 | L130: =SUM(L127:L129) -> 272276 | M130: =SUM(M127:M129) -> 280285 | N130: =SUM(N127:N129) -> 288543 | O130: =SUM(O127:O129) -> 297058
D132: 602005 | G132: Leges overige publiekszaken (5)
G133: Lasten
A134: =+D132 -> 602005 | B134: =G132 -> Leges overige publiekszaken (5) | D134: 43812 | G134: Overige goederen en diensten | J134: 2355 | K134: 3250 | L134: =L296 -> 3318 | M134: =M296 -> 3394 | N134: =N296 -> 3472 | O134: =O296 -> 3552
A135: =+D132 -> 602005 | B135: =G132 -> Leges overige publiekszaken (5) | D135: 44310 | G135: Inkomensoverdrachten aan het rijk | J135: 45448 | K135: 64423 | L135: =L329 -> 65859 | M135: =M329 -> 67429 | N135: =N329 -> 69043 | O135: =O329 -> 70573
G136: Totaal | J136: 47803 | K136: 67673 | L136: =SUM(L134:L135) -> 69177 | M136: =SUM(M134:M135) -> 70823 | N136: =SUM(N134:N135) -> 72515 | O136: =SUM(O134:O135) -> 74125
D138: 602905 | G138: Directe toerekening leges overige publiekszaken (5)
G139: Lasten
A140: =+D138 -> 602905 | B140: =G138 -> Directe toerekening leges overige publiekszaken (5) | D140: 41100 | G140: Salarissen | J140: 42453 | K140: 40461.45 | L140: =ROUND(K140*T$3,0) -> 42161 | M140: =ROUND(L140*U$3,0) -> 43721 | N140: =ROUND(M140*V$3,0) -> 45339 | O140: =ROUND(N140*W$3,0) -> 47017
G141: Totaal | J141: 42453 | K141: 40461.45 | L141: =SUM(L139:L140) -> 42161 | M141: =SUM(M139:M140) -> 43721 | N141: =SUM(N139:N140) -> 45339 | O141: =SUM(O139:O140) -> 47017
D143: 602006 | G143: Verkiezingen (6)
G144: Lasten
A145: =+D143 -> 602006 | B145: =G143 -> Verkiezingen (6) | D145: 43805 | G145: Huurlasten | J145: 1100 | K145: 3100 | L145: =L346 -> 3100 | M145: =M346 -> 3100 | N145: =N346 -> 3100 | O145: =O346 -> 3100
A146: =+D143 -> 602006 | B146: =G143 -> Verkiezingen (6) | D146: 43812 | G146: Overige goederen en diensten | J146: 57271 | K146: 58795 | L146: =L364 -> 59767 | M146: =M364 -> 60875 | N146: =N364 -> 62000 | O146: =O364 -> 63142
G147: Totaal | J147: 58371 | K147: 61895 | L147: =SUM(L145:L146) -> 62867 | M147: =SUM(M145:M146) -> 63975 | N147: =SUM(N145:N146) -> 65100 | O147: =SUM(O145:O146) -> 66242
D149: 602907 | G149: Directe toerekening verkiezingen (6)
G150: Lasten
A151: =+D149 -> 602907 | B151: =+G149 -> Directe toerekening verkiezingen (6) | D151: 41100 | G151: Salarissen | J151: 4666.49 | K151: 7848 | L151: =ROUND(K151*T$3,0) -> 8178 | M151: =ROUND(L151*U$3,0) -> 8481 | N151: =ROUND(M151*V$3,0) -> 8795 | O151: =ROUND(N151*W$3,0) -> 9120
J152: 4666.49 | K152: 7848 | L152: =SUM(L150:L151) -> 8178 | M152: =SUM(M150:M151) -> 8481 | N152: =SUM(N150:N151) -> 8795 | O152: =SUM(O150:O151) -> 9120
D154: 602007 | G154: Publiekszaken (7)
G155: Lasten
A156: =+D154 -> 602007 | B156: =G154 -> Publiekszaken (7) | D156: 43812 | G156: Overige goederen en diensten | J156: 8959.349 | K156: 9825 | L156: =L378 -> 10033.915 | M156: =M378 -> 10269.255 | N156: =N378 -> 10508.168 | O156: =O378 -> 10750.736
G157: Totaal | J157: 8959.349 | K157: 9825 | L157: =SUM(L155:L156) -> 10033.915 | M157: =SUM(M155:M156) -> 10269.255 | N157: =SUM(N155:N156) -> 10508.168 | O157: =SUM(O155:O156) -> 10750.736
D159: 602906 | G159: Directe toerekening publiekszaken (7)
G160: Lasten
A161: =+D159 -> 602906 | B161: =G159 -> Directe toerekening publiekszaken (7) | D161: 41100 | G161: Salarissen | J161: 150517.95 | K161: 169988.77 | L161: =L587 -> 159976 | M161: =M587 -> 165895 | N161: =N587 -> 172033 | O161: =O587 -> 178398
A162: =D159 -> 602906 | B162: =G159 -> Directe toerekening publiekszaken (7) | D162: 43511 | G162: Inhuur | J162: 10400 | K162: 0 | L162: =L592 -> 0 | M162: =M592 -> 0 | N162: =N592 -> 0 | O162: =O592 -> 0
G163: Totaal | J163: 160917.95 | K163: 169988.77 | L163: =SUM(L161:L162) -> 159976 | M163: =SUM(M161:M162) -> 165895 | N163: =SUM(N161:N162) -> 172033 | O163: =SUM(O161:O162) -> 178398
D165: 602001 | G165: Huwelijken (1)
G166: Baten
A167: =+D165 -> 602001 | B167: =G165 -> Huwelijken (1) | D167: 83700 | G167: Leges en rechten | J167: -67872.7 | K167: -81724.78 | L167: =-L438 -> -85081.4 | M167: =-M438 -> -88154.4 | N167: =-N438 -> -91346.9 | O167: =-O438 -> -94661.8
G168: Totaal | J168: -67872.7 | K168: -81724.78 | L168: =SUM(L167) -> -85081.4 | M168: =SUM(M167) -> -88154.4 | N168: =SUM(N167) -> -91346.9 | O168: =SUM(O167) -> -94661.8
D170: 602002 | G170: Reisdocumenten (2)
G171: Baten
A172: =+D170 -> 602002 | B172: =+G170 -> Reisdocumenten (2) | D172: 83700 | G172: Leges en rechten | J172: -312150 | K172: -464175.5 | L172: =-L481 -> -473936.5 | M172: =-M481 -> -484625 | N172: =-N481 -> -495845 | O172: =-O481 -> -507069
G173: Totaal | J173: -312150 | K173: -464175.5 | L173: =SUM(L172:L172) -> -473936.5 | M173: =SUM(M172:M172) -> -484625 | N173: =SUM(N172:N172) -> -495845 | O173: =SUM(O172:O172) -> -507069
D175: 602003 | G175: Rijbewijzen (3)
...

Sheet T03
A1: Inhoudsopgave | Q1: 2024 | R1: 2025 | S1: 2026 | T1: 2027 | U1: 2028 | V1: 2029 | W1: 2030
D2: Programma | H2: 01. Algemeen Bestuur | P2: Prijzen | Q2: =+Indexering!G4 -> 1.037 | R2: =+Indexering!H4 -> 1.028 | S2: =+Indexering!I4 -> 1.026 | T2: =+Indexering!J4 -> 1.021 | U2: =+Indexering!K4 -> 1.023 | V2: =+Indexering!L4 -> 1.023 | W2: =+Indexering!M4 -> 1.023
P3: Lonen | Q3: =+Indexering!G5 -> 1.052 | R3: =+Indexering!H5 -> 1.049 | S3: =+Indexering!I5 -> 1.02 | T3: =+Indexering!J5 -> 1.042 | U3: =+Indexering!K5 -> 1.037 | V3: =+Indexering!L5 -> 1.037 | W3: =+Indexering!M5 -> 1.037
S4: =+Indexering!I6 -> 1.02282 | T4: =+Indexering!J6 -> 1.03213 | U4: =+Indexering!K6 -> 1.03042 | V4: =+Indexering!L6 -> 1.03042 | W4: =+Indexering!M6 -> 1.03042
D6: Taakveld | H6: T03 Beheer overige gebouwen en gronden
D9: 0.3 - Beheer overige gebouwen en gronden
D11: Tot dit taakveld behoren taken met betrekking tot onroerend goed dat niet in exploitatie is en niet aan een specifiek beleidsveld is toe te delen:
D12: beheer, verhuur, instandhouding van gebouwen, gronden en landerijen die de gemeente (al of niet tijdelijk) in bezit heeft en niet in exploitatie neemt.
D19: In te zetten middelen
D21: Lasten in € (+) | J21: 2025 | K21: 2026 | L21: 2027 | M21: 2028 | N21: 2029 | O21: 2030
D22: =G73 -> Strategische gronden | J22: 14373 | K22: =K80 -> 192347 | L22: =L80 -> 17711 | M22: =M80 -> 18103 | N22: =N80 -> 18503 | O22: =O80 -> 18913
D23: =G82 -> Garageboxen | J23: 690 | K23: =K87 -> 708 | L23: =L87 -> 723 | M23: =M87 -> 740 | N23: =N87 -> 758 | O23: =O87 -> 776
D24: =G89 -> Hartenvier 2 | J24: 535 | K24: =K92 -> 549 | L24: =L92 -> 561 | M24: =M92 -> 573 | N24: =N92 -> 585 | O24: =O92 -> 597
D25: =G94 -> I. van de Boschstraat 2A | J25: 7679 | K25: =K100 -> 7680 | L25: =L100 -> 7842 | M25: =M100 -> 8022 | N25: =N100 -> 8206 | O25: =O100 -> 8395
D26: =G102 -> Algemene lasten gebouwenbeheer | J26: 59007 | K26: =K105 -> 9221 | L26: =L105 -> 9415 | M26: =M105 -> 9632 | N26: =N105 -> 9854 | O26: =O105 -> 10080
D27: =G193 -> Directe toerekening vastgoed | J27: 179716 | K27: =K197 -> 208752.05 | L27: =L197 -> 203845 | M27: =M197 -> 209958 | N27: =N197 -> 216298 | O27: =O197 -> 222872
D28: Koningin Emmalaan 25 | J28: 21559 | K28: =+K115 -> 8759 | L28: =+L115 -> 8943 | M28: =+M115 -> 9149 | N28: =+N115 -> 9360 | O28: =+O115 -> 9575
D29: =G117 -> Molenstraat 1b | J29: 27044 | K29: =K126 -> 27933.465 | L29: =L126 -> 28827.953 | M29: =M126 -> 29761.734 | N29: =N126 -> 30726.631 | O29: =O126 -> 12894
D30: =G128 -> H. Hartstraat 1 | J30: 1057 | K30: =K135 -> 7585 | L30: =L135 -> 7754 | M30: =M135 -> 7940 | N30: =N135 -> 8131 | O30: =O135 -> 8318
D31: =G137 -> Spoorstraat 1 | J31: 1083 | K31: =K141 -> 1111 | L31: =L141 -> 1135 | M31: =M141 -> 1161 | N31: =N141 -> 1187 | O31: =O141 -> 1214
D32: =G143 -> Stationsstraat 19a | J32: 1017 | K32: =K147 -> 1044 | L32: =L147 -> 1065 | M32: =M147 -> 1090 | N32: =N147 -> 1115 | O32: =O147 -> 1141
D33: =G149 -> Veldweg 14 en 16 | J33: 6088 | K33: =K154 -> 6247 | L33: =L154 -> 6377 | M33: =M154 -> 6523 | N33: =N154 -> 6673 | O33: =O154 -> 6826
D34: =G156 -> Afgewikkelde complexen | J34: 58433 | K34: =K163 -> 27416 | L34: =L163 -> 27899 | M34: =M163 -> 28439 | N34: =N163 -> 28992 | O34: =O163 -> 29558
D35: =G165 -> Johannes Vermeerstraat 21 | J35: 4773 | K35: =K169 -> 10897 | L35: =L169 -> 11126 | M35: =M169 -> 11381 | N35: =N169 -> 11643 | O35: =O169 -> 11911
D36: =G171 -> Wildheuvel 21-23 (leegstand) | J36: 1964 | K36: =K175 -> 2015 | L36: =L175 -> 2058 | M36: =M175 -> 2106 | N36: =N175 -> 2154 | O36: =O175 -> 2204
D37: =G177 -> Burgemeester Notermanstraat 27/29/29A | J37: =J181 -> 0 | K37: =K181 -> 4000 | L37: =L181 -> 4084 | M37: =M181 -> 4177 | N37: =N181 -> 4273 | O37: =O181 -> 4372
D38: =G183 -> Sportlaan 10 | J38: =J185 -> 0 | K38: =K185 -> 136981 | L38: =L185 -> 0 | M38: =M185 -> 0 | N38: =N185 -> 0 | O38: =O185 -> 0
D47: Totaal lasten | J47: 385018 | K47: =SUM(K22:K46) -> 653245.52 | L47: =SUM(L22:L46) -> 339365.95 | M47: =SUM(M22:M46) -> 348755.73 | N47: =SUM(N22:N46) -> 358458.63 | O47: =SUM(O22:O46) -> 349646
D49: Baten in € (-) | J49: 2025 | K49: 2026 | L49: 2027 | M49: 2028 | N49: 2029 | O49: 2030
D50: =G187 -> Strategische gronden | J50: -161150.23 | K50: =K191 -> -166088 | L50: =L191 -> -173584.83 | M50: =M191 -> -177488.98 | N50: =N191 -> -181482.98 | O50: =O191 -> -185566.98
D51: =G199 -> Garageboxen | J51: 2779.8 | K51: =K202 -> -2880 | L51: =L202 -> -2960.39 | M51: =M202 -> -3028 | N51: =N202 -> -3098 | O51: =O202 -> -3169
D52: =G204 -> Hartevier 2 | J52: -37365 | K52: =K207 -> -39678 | L52: =L207 -> -40787.48 | M52: =M207 -> -41726 | N52: =N207 -> -42686 | O52: =O207 -> -43668
D53: =G209 -> Erfpachtovereenkomst Best Zoo | J53: -13954 | K53: =K212 -> -13927 | L53: =L212 -> -13859.26 | M53: =M212 -> -14178 | N53: =N212 -> -14504 | O53: =O212 -> -14838
D54: =G214 -> H. Hartstraat 1 | J54: -3252.02 | K54: =K217 -> -3359 | L54: =L217 -> -3453.23 | M54: =M217 -> -3533 | N54: =N217 -> -3614 | O54: =O217 -> -3697
D55: =G219 -> Spoorstraat 1 | J55: -16859 | K55: =K222 -> -17297 | L55: =L222 -> -11236.37 | M55: =M222 -> -11495 | N55: =N222 -> -11759 | O55: =O222 -> -12029
D56: =G225 -> Veldweg 14 en 16 | J56: -30866 | K56: =K228 -> -30782 | L56: =L228 -> -22279.22 | M56: =M228 -> -22792 | N56: =N228 -> -23316 | O56: =O228 -> -23852
D57: =G230 -> Afgewikkelde complexen | J57: -95900 | K57: =K233 -> -98400 | L57: =L233 -> -100500 | M57: =M233 -> -102800 | N57: =N233 -> -105200 | O57: =O233 -> -107600
D58: Burg. Notermanstraat 27-29-29a | J58: 0 | K58: 0 | L58: =L237 -> -6042.69 | M58: =M237 -> -6182 | N58: =N237 -> -6324 | O58: =O237 -> -6469
D59: =G240 -> Sportlaan 10 | J59: =J242 -> 0 | K59: =K242 -> -94164 | L59: =L242 -> 0 | M59: =M242 -> 0 | N59: =N242 -> 0 | O59: =O242 -> 0
D62: Totaal baten | J62: -356566.45 | K62: =SUM(K50:K61) -> -466575 | L62: =SUM(L50:L61) -> -374703.47 | M62: =SUM(M50:M61) -> -383222.98 | N62: =SUM(N50:N61) -> -391983.98 | O62: =SUM(O50:O61) -> -400888.98
D64: Saldo (+ = nadeel) | J64: 28451.55 | K64: =K47+K62 -> 186670.52 | L64: =L47+L62 -> -35337.517 | M64: =M47+M62 -> -34467.246 | N64: =N47+N62 -> -33525.349 | O64: =O47+O62 -> -51242.98
D69: Financiële toelichting
D71: Grootb/cat t/m 2019 | E71: Bbv Taakv/ | F71: Grootb/cat nummer | G71: Omschrijving
E72: Bbv cat | J72: 2025 | K72: 2026 | L72: 2027 | M72: 2028 | N72: 2029 | O72: 2030
D73: 603001 | G73: Strategische gronden
G74: Lasten
A75: =+D73 -> 603001 | B75: =G73 -> Strategische gronden | D75: 42100 | G75: Belastingen en heffingen (ozb) | J75: 5133 | K75: 7866 | L75: =ROUND(K75*$T$2,0) -> 8031 | M75: =ROUND(L75*$T$2,0) -> 8200 | N75: =ROUND(M75*$T$2,0) -> 8372 | O75: =ROUND(N75*$T$2,0) -> 8548
A76: 603001 | B76: =G73 -> Strategische gronden | D76: 42100 | G76: Belastingen en heffingen (waterschapslasten) | J76: 6447 | K76: 6615 | L76: =ROUND(K76*T$2,0) -> 6754 | M76: =ROUND(L76*U$2,0) -> 6909 | N76: =ROUND(M76*V$2,0) -> 7068 | O76: =ROUND(N76*W$2,0) -> 7231
A77: 603001 | B77: Strategische gronden | D77: 43806 | G77: Verzekeringen (brandverzekering) | J77: 69 | K77: 71 | L77: =ROUND(K77*T$2,0) -> 72 | M77: =ROUND(L77*U$2,0) -> 74 | N77: =ROUND(M77*V$2,0) -> 76 | O77: =ROUND(N77*W$2,0) -> 78
A78: 603001 | B78: =G73 -> Strategische gronden | D78: 43812 | G78: Overige goederen en diensten | J78: 2724 | K78: =K260 -> 177795 | L78: =L260 -> 2854 | M78: =M260 -> 2920 | N78: =N260 -> 2987 | O78: =O260 -> 3056
A79: 603001 | B79: =G73 -> Strategische gronden | D79: 42100 | G79: Betaalde rente | J79: 0 | K79: 0 | L79: =ROUND(K79*$T$2,0) -> 0 | M79: =ROUND(L79*$T$2,0) -> 0 | N79: =ROUND(M79*$T$2,0) -> 0 | O79: =ROUND(N79*$T$2,0) -> 0
G80: Totaal | J80: 14373 | K80: =SUM(K75:K79) -> 192347 | L80: =SUM(L75:L79) -> 17711 | M80: =SUM(M75:M79) -> 18103 | N80: =SUM(N75:N79) -> 18503 | O80: =SUM(O75:O79) -> 18913
D82: 603002 | G82: Garageboxen
G83: Lasten
A84: =+D82 -> 603002 | B84: =G82 -> Garageboxen | D84: 42100 | G84: Belastingen en heffingen (ozb) | J84: 74 | K84: 76 | L84: =ROUND(K84*T$2,0) -> 78 | M84: =ROUND(L84*U$2,0) -> 80 | N84: =ROUND(M84*V$2,0) -> 82 | O84: =ROUND(N84*W$2,0) -> 84
A85: 603002 | B85: =G82 -> Garageboxen | D85: 43806 | G85: Verzekeringen (brandverzekering) | J85: 22 | K85: 23 | L85: =ROUND(K85*T$2,0) -> 23 | M85: =ROUND(L85*U$2,0) -> 24 | N85: =ROUND(M85*V$2,0) -> 25 | O85: =ROUND(N85*W$2,0) -> 26
A86: 603002 | B86: =G82 -> Garageboxen | D86: 43812 | G86: Overige goederen en diensten | J86: 594 | K86: 609 | L86: =L267 -> 622 | M86: =M267 -> 636 | N86: =N267 -> 651 | O86: =O267 -> 666
G87: Totaal | J87: 690 | K87: 708 | L87: =SUM(L83:L86) -> 723 | M87: =SUM(M83:M86) -> 740 | N87: =SUM(N83:N86) -> 758 | O87: =SUM(O83:O86) -> 776
D89: 603003 | G89: Hartenvier 2
G90: Lasten
A91: =+D89 -> 603003 | B91: =G89 -> Hartenvier 2 | D91: 42100 | G91: Belastingen en heffingen (ozb) | J91: 535 | K91: 549 | L91: =ROUND(K91*$T$2,0) -> 561 | M91: =ROUND(L91*$T$2,0) -> 573 | N91: =ROUND(M91*$T$2,0) -> 585 | O91: =ROUND(N91*$T$2,0) -> 597
J92: 535 | K92: 549 | L92: =SUM(L91:L91) -> 561 | M92: =SUM(M91:M91) -> 573 | N92: =SUM(N91:N91) -> 585 | O92: =SUM(O91:O91) -> 597
D94: 603004 | G94: I. van de Boschstraat 2A
G95: Lasten
A96: 603004 | B96: =G94 -> I. van de Boschstraat 2A | D96: 42100 | G96: Belastingen en heffingen (ozb) | J96: 1574 | K96: 1615 | L96: =ROUND(K96*T$2,0) -> 1649 | M96: =ROUND(L96*U$2,0) -> 1687 | N96: =ROUND(M96*V$2,0) -> 1726 | O96: =ROUND(N96*W$2,0) -> 1766
A97: 603004 | B97: =G94 -> I. van de Boschstraat 2A | D97: 43806 | G97: Verzekeringen (brandverzekering) | J97: 2125 | K97: 2180 | L97: =ROUND(K97*T$2,0) -> 2226 | M97: =ROUND(L97*U$2,0) -> 2277 | N97: =ROUND(M97*V$2,0) -> 2329 | O97: =ROUND(N97*W$2,0) -> 2383
A98: 603004 | B98: =G94 -> I. van de Boschstraat 2A | D98: 43812 | G98: Overige goederen en diensten | J98: 3787 | K98: 3885 | L98: =ROUND(K98*T$2,0) -> 3967 | M98: =ROUND(L98*U$2,0) -> 4058 | N98: =ROUND(M98*V$2,0) -> 4151 | O98: =ROUND(N98*W$2,0) -> 4246
A99: 603004 | B99: =G94 -> I. van de Boschstraat 2A | D99: 47201 | G99: Onderhoudsvoorzieningen (O109) | J99: 193 | K99: 0 | L99: 0 | M99: 0 | N99: 0 | O99: 0
G100: Totaal | J100: 7679 | K100: 7680 | L100: =SUM(L95:L99) -> 7842 | M100: =SUM(M95:M99) -> 8022 | N100: =SUM(N95:N99) -> 8206 | O100: =SUM(O95:O99) -> 8395
D102: 603005 | G102: Algemene lasten gebouwenbeheer
G103: Lasten
A104: =+D102 -> 603005 | B104: =G102 -> Algemene lasten gebouwenbeheer | D104: 43812 | G104: Overige goederen en diensten | J104: 59007 | K104: 9221 | L104: =L279 -> 9415 | M104: =M279 -> 9632 | N104: =N279 -> 9854 | O104: =O279 -> 10080
G105: Totaal | J105: 59007 | K105: 9221 | L105: =SUM(L103:L104) -> 9415 | M105: =SUM(M103:M104) -> 9632 | N105: =SUM(N103:N104) -> 9854 | O105: =SUM(O103:O104) -> 10080
D107: 603007 | G107: Koningin Emmalaan 25
G108: Lasten
A109: 603007 | B109: Koningin Emmalaan 25 | D109: 43801 | G109: Gas | J109: 7528 | K109: 0 | L109: =ROUND(K109*T$2,0) -> 0 | M109: =ROUND(L109*U$2,0) -> 0 | N109: =ROUND(M109*V$2,0) -> 0 | O109: =ROUND(N109*W$2,0) -> 0 | P109: I.v.m. opbang niet meer begroot
A110: 603007 | B110: Koningin Emmalaan 25 | D110: 43802 | G110: Elektriciteit | J110: 4494 | K110: 0 | L110: =ROUND(K110*T$2,0) -> 0 | M110: =ROUND(L110*U$2,0) -> 0 | N110: =ROUND(M110*V$2,0) -> 0 | O110: =ROUND(N110*W$2,0) -> 0 | P110: I.v.m. opbang niet meer begroot
A111: 603007 | B111: Koningin Emmalaan 25 | D111: 42100 | G111: Onroerende zaakbelasting | J111: 2789 | K111: 4862 | L111: =ROUND(K111*T$2,0) -> 4964 | M111: =ROUND(L111*U$2,0) -> 5078 | N111: =ROUND(M111*V$2,0) -> 5195 | O111: =ROUND(N111*W$2,0) -> 5314
A112: 603007 | B112: Koningin Emmalaan 25 | D112: 43806 | G112: Brand & stormschadeverzekering | J112: 2113 | K112: 2168 | L112: =ROUND(K112*T$2,0) -> 2214 | M112: =ROUND(L112*U$2,0) -> 2265 | N112: =ROUND(M112*V$2,0) -> 2317 | O112: =ROUND(N112*W$2,0) -> 2370
A113: 603007 | B113: Koningin Emmalaan 25 | D113: 43812 | G113: Aank. niet duurzame goederen en diensten | J113: 2950 | K113: 0 | L113: =ROUND(K113*T$2,0) -> 0 | M113: =ROUND(L113*U$2,0) -> 0 | N113: =ROUND(M113*V$2,0) -> 0 | O113: =ROUND(N113*W$2,0) -> 0 | P113: I.v.m. opbang niet meer begroot
A114: 603007 | B114: Koningin Emmalaan 25 | D114: 43817 | G114: Dagelijks onderhoud | J114: 1685 | K114: 1729 | L114: =L306 -> 1765 | M114: =M306 -> 1806 | N114: =N306 -> 1848 | O114: =O306 -> 1891
G115: Totaal | J115: 21559 | K115: 8759 | L115: =SUM(L109:L114) -> 8943 | M115: =SUM(M109:M114) -> 9149 | N115: =SUM(N109:N114) -> 9360 | O115: =SUM(O109:O114) -> 9575
D117: 603008 | G117: Molenstraat 1b
G118: Lasten
A119: 603008 | B119: =G117 -> Molenstraat 1b | D119: 42100 | G119: Belastingen en heffingen (ozb) | J119: 2141 | K119: 2197 | L119: =ROUND(K119*T$2,0) -> 2243 | M119: =ROUND(L119*U$2,0) -> 2295 | N119: =ROUND(M119*V$2,0) -> 2348 | O119: =ROUND(N119*W$2,0) -> 2402
A120: 603008 | B120: =G117 -> Molenstraat 1b | D120: 43801 | G120: Gasverbruik | J120: 248 | K120: 254 | L120: =ROUND(K120*T$2,0) -> 259 | M120: =ROUND(L120*U$2,0) -> 265 | N120: =ROUND(M120*V$2,0) -> 271 | O120: =ROUND(N120*W$2,0) -> 277
A121: 603008 | B121: =G117 -> Molenstraat 1b | D121: 43802 | G121: Elektriciteit | J121: 299 | K121: 307 | L121: =ROUND(K121*T$2,0) -> 313 | M121: =ROUND(L121*U$2,0) -> 320 | N121: =ROUND(M121*V$2,0) -> 327 | O121: =ROUND(N121*W$2,0) -> 335
A122: 603008 | B122: =G117 -> Molenstraat 1b | D122: 43806 | G122: Verzekeringen (brandverzekering) | J122: 2046 | K122: 2099 | L122: =ROUND(K122*T$2,0) -> 2143 | M122: =ROUND(L122*U$2,0) -> 2192 | N122: =ROUND(M122*V$2,0) -> 2242 | O122: =ROUND(N122*W$2,0) -> 2294
A123: 603008 | B123: =G117 -> Molenstraat 1b | D123: 43817 | G123: Dagelijks onderhoud | J123: 4362 | K123: 4484 | L123: =ROUND(K123*$R$2,0) -> 4610 | M123: =ROUND(L123*$R$2,0) -> 4739 | N123: =ROUND(M123*$R$2,0) -> 4872 | O123: =ROUND(N123*$R$2,0) -> 5008
A124: 603008 | B124: =+G117 -> Molenstraat 1b | D124: 43812 | G124: Overige goederen en diensten | J124: 2246 | K124: 2309 | L124: =ROUND(K124*$R$2,0) -> 2374 | M124: =ROUND(L124*$R$2,0) -> 2440 | N124: =ROUND(M124*$R$2,0) -> 2508 | O124: =ROUND(N124*$R$2,0) -> 2578
A125: 603008 | B125: =G117 -> Molenstraat 1b | D125: 47201 | G125: Onderhoudsvoorzieningen (O134) | J125: 15702 | K125: 16283.465 | L125: 16885.953 | M125: 17510.734 | N125: 18158.631 | O125: 0
G126: Totaal | J126: 27044 | K126: 27933.465 | L126: =SUM(L119:L125) -> 28827.953 | M126: =SUM(M119:M125) -> 29761.734 | N126: =SUM(N119:N125) -> 30726.631 | O126: =SUM(O119:O125) -> 12894
D128: 603009 | G128: H. Hartstraat 1
G129: Lasten
A130: =+D128 -> 603009 | B130: =G128 -> H. Hartstraat 1 | D130: 42100 | G130: Belastingen en heffingen (ozb) | J130: 597 | K130: 613 | L130: =ROUND(K130*T$2,0) -> 626 | M130: =ROUND(L130*U$2,0) -> 640 | N130: =ROUND(M130*V$2,0) -> 655 | O130: =ROUND(N130*W$2,0) -> 670
A131: 603007 | B131: =G128 -> H. Hartstraat 1 | D131: 43801 | G131: Gas | J131: 0 | K131: 3000 | L131: =ROUND(K131*T$2,0) -> 3063 | M131: =ROUND(L131*U$2,0) -> 3133 | N131: =ROUND(M131*V$2,0) -> 3205 | O131: =ROUND(N131*W$2,0) -> 3279
A132: 603007 | B132: =G128 -> H. Hartstraat 1 | D132: 43802 | G132: Elektriciteit | J132: 0 | K132: 2000 | L132: =ROUND(K132*T$2,0) -> 2042 | M132: =ROUND(L132*U$2,0) -> 2089 | N132: =ROUND(M132*V$2,0) -> 2137 | O132: =ROUND(N132*W$2,0) -> 2186
A133: 603008 | B133: =G128 -> H. Hartstraat 1 | D133: 43817 | G133: Dagelijks onderhoud | J133: 0 | K133: 1500 | L133: =ROUND(K133*T$2,0)+9 -> 1541 | M133: =ROUND(L133*U$2,0)+9 -> 1585 | N133: =ROUND(M133*V$2,0)+9 -> 1630 | O133: =ROUND(N133*W$2,0) -> 1667
A134: =+D128 -> 603009 | B134: =G128 -> H. Hartstraat 1 | D134: 43806 | G134: Verzekeringen | J134: 460 | K134: 472 | L134: =ROUND(K134*T$2,0) -> 482 | M134: =ROUND(L134*U$2,0) -> 493 | N134: =ROUND(M134*V$2,0) -> 504 | O134: =ROUND(N134*W$2,0) -> 516
G135: Totaal | J135: 1057 | K135: 7585 | L135: =SUM(L130:L134) -> 7754 | M135: =SUM(M130:M134) -> 7940 | N135: =SUM(N130:N134) -> 8131 | O135: =SUM(O130:O134) -> 8318
...

Sheet T04L
A1: Inhoudsopgave | Q1: 2024 | R1: 2025 | S1: 2026 | T1: 2027 | U1: 2028 | V1: 2029 | W1: 2030
D2: Programma | H2: 12. Overhead | P2: Prijzen | Q2: =+Indexering!G4 -> 1.037 | R2: =+Indexering!H4 -> 1.028 | S2: =+Indexering!I4 -> 1.026 | T2: =+Indexering!J4 -> 1.021 | U2: =+Indexering!K4 -> 1.023 | V2: =+Indexering!L4 -> 1.023 | W2: =+Indexering!M4 -> 1.023
P3: Lonen | Q3: =+Indexering!G5 -> 1.052 | R3: =+Indexering!H5 -> 1.049 | S3: =+Indexering!I5 -> 1.02 | T3: =+Indexering!J5 -> 1.042 | U3: =+Indexering!K5 -> 1.037 | V3: =+Indexering!L5 -> 1.037 | W3: =+Indexering!M5 -> 1.037
D4: Taakveld | H4: T04 Overhead - onderdeel loonkosten | S4: =+Indexering!I6 -> 1.02282 | T4: =+Indexering!J6 -> 1.03213 | U4: =+Indexering!K6 -> 1.03042 | V4: =+Indexering!L6 -> 1.03042 | W4: =+Indexering!M6 -> 1.03042
D31: In te zetten middelen
D33: Lasten in € (+) | J33: 2025 | K33: 2026 | L33: 2027 | M33: 2028 | N33: 2029 | O33: 2030 | Q33: 2026 | R33: 2027 | S33: 2028
C34: 1 | D34: =G78 -> Uitkeringen voormalig personeel | J34: 12252 | K34: 12497 | L34: =L81 -> 13022 | M34: =M81 -> 13504 | N34: =N81 -> 14004 | O34: =O81 -> 14522
C35: 1 | D35: =G83 -> Overige personeelslasten - niet direct toewijsbaar | J35: 1533016 | K35: 1560677 | L35: =L108 -> 1703684 | M35: =M108 -> 1864227 | N35: =N108 -> 2034638 | O35: =O108 -> 2178921.5
C36: 1 | D36: =G110 -> Lokaal arbeidsvoorwaardenbeleid | J36: 431904 | K36: 392217 | L36: =L113 -> 410906 | M36: =M113 -> 428229 | N36: =N113 -> 446205.52 | O36: =O113 -> 464860.6
C37: 1 | D37: directe toerek overhead (incl doorbelasting naar investeringen, T21, T52, T57 en T82) | J37: 8504040.8 | K37: =K227 -> 8105954 | L37: =L227 -> 8436434 | M37: =M227 -> 8966401.2 | N37: =N227 -> 9301096.9 | O37: =O227 -> 9795314.9 | Q37: 8970431 | R37: 9214340 | S37: 9573708
C38: 1 | D38: Management Domein bedrijfsvoering | J38: 97524 | K38: 81255 | L38: =+L124 -> 82961 | M38: =+M124 -> 84869 | N38: =+N124 -> 86821 | O38: =+O124 -> 88818 | Q38: =+Q37-K37 -> 864476.98 | R38: =+R37-L37 -> 777905.97 | S38: =+S37-M37 -> 607306.83
C39: 1 | D39: =G127 -> Financiele administratie | J39: 89292 | K39: 87016 | L39: =L131 -> 89368 | M39: =M131 -> 91788 | N39: =N131 -> 94278 | O39: =O131 -> 96839
C40: 1 | D40: =G133 -> Financieel Beleid | J40: 13701 | K40: 10000 | L40: =L136 -> 10420 | M40: =M136 -> 10806 | N40: =N136 -> 11206 | O40: =O136 -> 11621
C41: 1 | D41: =G138 -> Communicatie | J41: 177867 | K41: 168830 | L41: =L141 -> 171703 | M41: =M141 -> 175183 | N41: =N141 -> 178727 | O41: =O141 -> 182334
C42: 1 | D42: =G143 -> Advertentiekosten | J42: 9388 | K42: 6765 | L42: =L146 -> 6933 | M42: =M146 -> 6969 | N42: =N146 -> 7319 | O42: =O146 -> 7384
C43: 1 | D43: =G153 -> Juridische Zaken | J43: 56624.787 | K43: 49116.542 | L43: =L157 -> 50390.535 | M43: =M157 -> 51777.842 | N43: =N157 -> 52592.146 | O43: =O157 -> 53987.717
C44: 1 | D44: =G159 -> Control & Kwaliteit | J44: 250524 | K44: 312262 | L44: =L163 -> 318819 | M44: =M163 -> 326152 | N44: =N163 -> 333654 | O44: =O163 -> 341328
C45: 1 | D45: =G165 -> Directie | J45: 12111 | K45: 10465 | L45: =L170 -> 10685 | M45: =M170 -> 10931 | N45: =N170 -> 11182 | O45: =O170 -> 11440
C46: 1 | D46: =G172 -> Ondernemingsraad | J46: 20567 | K46: 21102 | L46: =L175 -> 21545 | M46: =M175 -> 22041 | N46: =N175 -> 22548 | O46: =O175 -> 23067
C47: 1 | D47: =G182 -> Vastgoedbeheer | J47: 5007 | K47: 5147 | L47: =L185 -> 5286 | M47: =M185 -> 5440 | N47: =N185 -> 5597 | O47: =O185 -> 5726
C48: 1 | D48: Management domein omgeving | J48: 96693 | K48: 122117 | L48: =+L191 -> 124681 | M48: =+M191 -> 127549 | N48: =+N191 -> 130483 | O48: =+O191 -> 133484
C49: 1 | D49: Management domein samenleving | J49: 106955 | K49: 132521 | L49: =+L202 -> 135304 | M49: =+M202 -> 138416 | N49: =+N202 -> 141599 | O49: =+O202 -> 144856
C50: 1 | D50: Onderzoek inwoners | J50: 20000 | K50: 31806 | L50: =+L196 -> 20951 | M50: =+M196 -> 42916 | N50: =+N196 -> 21926 | O50: =+O196 -> 22430
C51: 1 | D51: Informatievrz mbt wet Woo | J51: 154451 | K51: =+K208 -> 258003 | L51: =+L208 -> 96232 | M51: =+M208 -> 98445 | N51: =+N208 -> 100709 | O51: =+O208 -> 103025
D52: Totaal lasten | J52: 11591918 | K52: =SUM(K34:K51) -> 11367751 | L52: =SUM(L34:L51) -> 11709325 | M52: =SUM(M34:M51) -> 12465644 | N52: =SUM(N34:N51) -> 12994586 | O52: =SUM(O34:O51) -> 13679959
D54: Baten in € (-) | J54: 2025 | K54: 2026 | L54: =+L33 -> 2027 | M54: =+M33 -> 2028 | N54: =+N33 -> 2029 | O54: =+O33 -> 2030
C55: 1 | D55: =G115 -> Terugontvangst salarissen en uitkeringen | J55: -11404 | K55: -11701 | L55: =L118 -> -11947 | M55: =M118 -> -12222 | N55: =N118 -> -12503 | O55: =O118 -> -12791
D67: Totaal baten | J67: -11404 | K67: =SUM(K55:K66) -> -11701 | L67: =SUM(L55:L66) -> -11947 | M67: =SUM(M55:M66) -> -12222 | N67: =SUM(N55:N66) -> -12503 | O67: =SUM(O55:O66) -> -12791 | Q67: =K52+K67 -> 11356050 | R67: =L52+L67 -> 11697378 | S67: =M52+M67 -> 12453422
D69: Saldo voor bijdragen en stortingen in reserves (+ = nadeel) | J69: 11580514 | K69: =K52+K67 -> 11356050 | L69: =L52+L67 -> 11697378 | M69: =M52+M67 -> 12453422 | N69: =N52+N67 -> 12982083 | O69: =O52+O67 -> 13667168
J72: 3076472.8 | K72: 3150095.5 | L72: =+L69-L37 -> 3260943.5 | M72: =+M69-M37 -> 3487020.8 | N72: =+N69-N37 -> 3680985.7 | O72: =+O69-O37 -> 3871852.8
D73: Financiële toelichting
D75: Grootb/cat t/m 2019 | E75: Bbv Taakv/ | F75: Grootb/cat nummer | G75: Omschrijving
E76: Bbv cat | J76: 2025 | K76: 2026 | L76: 2027 | M76: 2028 | N76: 2029 | O76: 2030
D78: 604001 | G78: Uitkeringen voormalig personeel
G79: Lasten
A80: =+D78 -> 604001 | B80: =G78 -> Uitkeringen voormalig personeel | D80: 41101 | G80: Uitkeringen voormalig personeel | J80: 12252 | K80: 12497 | L80: =+L243 -> 13022 | M80: =+M243 -> 13504 | N80: =+N243 -> 14004 | O80: =+O243 -> 14522
G81: Totaal | J81: 12252 | K81: 12497 | L81: =SUM(L80) -> 13022 | M81: =SUM(M80) -> 13504 | N81: =SUM(N80) -> 14004 | O81: =SUM(O80) -> 14522
D83: 604002 | G83: Overige personeelslasten - niet direct toewijsbaar
G84: Lasten
A85: 604002 | B85: =G83 -> Overige personeelslasten - niet direct toewijsbaar | D85: 41100 | G85: Salarissen | J85: 300000 | K85: 300000 | L85: =+L295 -> 397980 | M85: =+M295 -> 526868 | N85: =+N295 -> 666666 | O85: =+O295 -> 806771
A86: 604002 | B86: =G83 -> Overige personeelslasten - niet direct toewijsbaar | D86: 41104 | G86: Vergoeding stagiaires | J86: 11796 | K86: 12032 | L86: =+L307 -> 12537 | M86: =+M307 -> 13001 | N86: =+N307 -> 13482 | O86: =+O307 -> 13981
A87: 604002 | B87: =G83 -> Overige personeelslasten - niet direct toewijsbaar | D87: 43511 | G87: Inhuur personeel | J87: 363055 | K87: 370316 | L87: =+L317 -> 385869 | M87: =+M317 -> 400146 | N87: =+N317 -> 414952 | O87: =+O317 -> 430305
A88: 604002 | B88: =G83 -> Overige personeelslasten - niet direct toewijsbaar | D88: 43806 | G88: Verzekeringen | J88: 259157 | K88: 276699 | L88: =L332 -> 281543 | M88: =M332 -> 286961 | N88: =N332 -> 292503 | O88: =O332 -> 298174
A89: 604002 | B89: =G83 -> Overige personeelslasten - niet direct toewijsbaar | D89: 43806 | G89: Premie rechtsbijstandverzekering | J89: 0 | K89: 0 | L89: 0 | M89: 0 | N89: 0 | O89: 0
A90: 604002 | B90: =G83 -> Overige personeelslasten - niet direct toewijsbaar | D90: 43806 | G90: WA-verzekering | J90: 0 | K90: 0 | L90: 0 | M90: 0 | N90: 0 | O90: 0
A91: 604002 | B91: =G83 -> Overige personeelslasten - niet direct toewijsbaar | D91: 43806 | G91: Fraudeverzekering | J91: 0 | K91: 0 | L91: 0 | M91: 0 | N91: 0 | O91: 0
A92: 604002 | B92: =G83 -> Overige personeelslasten - niet direct toewijsbaar | D92: 43806 | G92: Premie ongevallenverzekering | J92: 0 | K92: 0 | L92: 0 | M92: 0 | N92: 0 | O92: 0
A93: 604002 | B93: =G83 -> Overige personeelslasten - niet direct toewijsbaar | D93: 43807 | G93: Geneeskundig onderzoek personeel | J93: 96749 | K93: 98514 | L93: =+L338 -> 100319 | M93: =+M338 -> 102167 | N93: =+N338 -> 102167 | O93: =+O338 -> 102167
A94: 604002 | B94: =G83 -> Overige personeelslasten - niet direct toewijsbaar | D94: 43808 | G94: Werving nieuw personeel | J94: 46014 | K94: 47337 | L94: =+L349 -> 48275 | M94: =+M349 -> 49136 | N94: =+N349 -> 50032 | O94: =+O349 -> 50606
A95: 604002 | B95: =G83 -> Overige personeelslasten - niet direct toewijsbaar | D95: 43809 | G95: Advies en ondersteuning | J95: 53614 | K95: 55008 | L95: =+L353 -> 56163 | M95: =+M353 -> 57455 | N95: =+N353 -> 58776 | O95: =+O353 -> 60128
A96: 604002 | B96: =G83 -> Overige personeelslasten - niet direct toewijsbaar | D96: 43812 | G96: Overige goederen en diensten | J96: 100178 | K96: 102434 | L96: =+L366 -> 105827 | M96: =+M366 -> 109124 | N96: =+N366 -> 112529 | O96: =+O366 -> 116046
A97: 604002 | B97: =G83 -> Overige personeelslasten - niet direct toewijsbaar | D97: 43818 | G97: Werkkostenregeling (arbo) | J97: 3538 | K97: 3630 | L97: =+L370 -> 3706 | M97: =+M370 -> 3791 | N97: =+N370 -> 3878 | O97: =+O370 -> 3967 | Q97: 85045
A98: 604002 | B98: =G83 -> Overige personeelslasten - niet direct toewijsbaar | D98: 43818 | G98: Werkkostenregeling (kerstpakketten) | J98: 14253 | K98: 14326 | L98: =+L377 -> 14386 | M98: =+M377 -> 14454 | N98: =+N377 -> 14523 | O98: =+O377 -> 14594 | Q98: 85980
A99: 604002 | B99: =G83 -> Overige personeelslasten - niet direct toewijsbaar | D99: 43818 | G99: Werkkostenregeling (dienstreizen) | J99: 4561 | K99: 4680 | L99: =+L382 -> 4778 | M99: =+M382 -> 4888 | N99: =+N382 -> 5000 | O99: =+O382 -> 5115
A100: 604002 | B100: =G83 -> Overige personeelslasten - niet direct toewijsbaar | D100: 43818 | G100: Werkkostenregeling (Afdelingsbudget) | J100: 14330 | K100: 15643 | L100: =+L392 -> 16300 | M100: =+M392 -> 16903 | N100: =+N392 -> 17335 | O100: =+O392 -> 17732.5
A101: 604002 | B101: =G83 -> Overige personeelslasten - niet direct toewijsbaar | D101: 43818 | G101: Werkkostenregeling (arbeidsvoorwaarden beleid) | J101: 48363 | K101: 49330 | L101: =+L396 -> 51402 | M101: =+M396 -> 53304 | N101: =+N396 -> 55276 | O101: =+O396 -> 57321
A102: 604002 | B102: =G83 -> Overige personeelslasten - niet direct toewijsbaar | D102: 43819 | G102: Studie en opleiding | J102: 100000 | K102: 100000 | L102: =+L419 -> 100000 | M102: =+M419 -> 100000 | N102: =+N419 -> 100000 | O102: =+O419 -> 100000
A103: 604002 | B103: =G83 -> Overige personeelslasten - niet direct toewijsbaar | D103: 43818 | G103: Werkkostenregeling (fietsproject) | J103: 63000 | K103: 63000 | L103: =L423 -> 63000 | M103: =M423 -> 63000 | N103: =N423 -> 63000 | O103: =O423 -> 63000
A104: 604002 | B104: =G83 -> Overige personeelslasten - niet direct toewijsbaar | D104: 43818 | G104: Werkkostenregeling (vergoeding schade) | J104: 1140 | K104: 1170 | L104: =+L427 -> 1195 | M104: =+M427 -> 1222 | N104: =+N427 -> 1250 | O104: =+O427 -> 1279
A105: 604002 | B105: =G83 -> Overige personeelslasten - niet direct toewijsbaar | D105: 43818 | G105: Werkkostenregeling bijdrage personeelsvereniging) | J105: 21840 | K105: 23010 | L105: =+L433 -> 23010 | M105: =+M433 -> 23010 | N105: =+N433 -> 23010 | O105: =+O433 -> 23010
A106: 604002 | B106: =G83 -> Overige personeelslasten - niet direct toewijsbaar | D106: 44360 | G106: Inkomensoverdr aan overige overheden | J106: 13130 | K106: 13471 | L106: =L442 -> 13754 | M106: =M442 -> 14070 | N106: =N442 -> 14394 | O106: =O442 -> 14725
A107: 604002 | B107: =G83 -> Overige personeelslasten - niet direct toewijsbaar | D107: 47200 | G107: Voorzieningen contante waarde | J107: 18298 | K107: 10077 | L107: =L445 -> 23640 | M107: =M445 -> 24727 | N107: =N445 -> 25865 | O107: =O445 -> 0
G108: Totaal | J108: 1533016 | K108: 1560677 | L108: =SUM(L85:L107) -> 1703684 | M108: =SUM(M85:M107) -> 1864227 | N108: =SUM(N85:N107) -> 2034638 | O108: =SUM(O85:O107) -> 2178921.5
D110: 604004 | G110: Lokaal arbeidsvoorwaardenbeleid
G111: Lasten
A112: =+D110 -> 604004 | B112: =G110 -> Lokaal arbeidsvoorwaardenbeleid | D112: 43812 | G112: Overige goederen en diensten | J112: 431904 | K112: 392217 | L112: =+L474 -> 410906 | M112: =+M474 -> 428229 | N112: =+N474 -> 446205.52 | O112: =+O474 -> 464860.6
G113: Totaal | J113: 431904 | K113: 392217 | L113: =SUM(L112) -> 410906 | M113: =SUM(M112) -> 428229 | N113: =SUM(N112) -> 446205.52 | O113: =SUM(O112) -> 464860.6
D115: 604003 | G115: Terugontvangst salarissen en uitkeringen
G116: Baten
A117: =+D115 -> 604003 | B117: =G115 -> Terugontvangst salarissen en uitkeringen | D117: 83520 | G117: Vergoedingen voor personeel | J117: -11404 | K117: -11701 | L117: =L450 -> -11947 | M117: =M450 -> -12222 | N117: =N450 -> -12503 | O117: =O450 -> -12791
G118: Totaal | J118: -11404 | K118: -11701 | L118: =SUM(L117:L117) -> -11947 | M118: =SUM(M117:M117) -> -12222 | N118: =SUM(N117:N117) -> -12503 | O118: =SUM(O117:O117) -> -12791
D120: 604058 | G120: Management domein bedrijfsvoering
G121: Lasten
A122: 604058 | B122: Management Domein bedrijfsvoering | D122: 43819 | G122: Studie en opleiding | J122: 95891 | K122: 79580 | L122: =+L479 -> 81251 | M122: =+M479 -> 83120 | N122: =+N479 -> 85032 | O122: =+O479 -> 86988
A123: 604058 | B123: Management Domein bedrijfsvoering | D123: 43812 | G123: Overige goederen en diensten | J123: 1633 | K123: 1675 | L123: =+L482 -> 1710 | M123: =+M482 -> 1749 | N123: =+N482 -> 1789 | O123: =+O482 -> 1830
G124: Totaal | J124: 97524 | K124: 81255 | L124: =SUM(L121:L123) -> 82961 | M124: =SUM(M121:M123) -> 84869 | N124: =SUM(N121:N123) -> 86821 | O124: =SUM(O121:O123) -> 88818
D127: 604027 | G127: Financiele administratie
G128: Lasten
A129: =+D127 -> 604027 | B129: =G127 -> Financiele administratie | D129: 43511 | G129: Inhuur personeel | J129: 28848 | K129: 25000 | L129: =L486 -> 26050 | M129: =M486 -> 27014 | N129: =N486 -> 28014 | O129: =O486 -> 29051
A130: =+D127 -> 604027 | B130: =G127 -> Financiele administratie | D130: 43812 | G130: Overige goederen en diensten | J130: 60444 | K130: 62016 | L130: =L493 -> 63318 | M130: =M493 -> 64774 | N130: =N493 -> 66264 | O130: =O493 -> 67788
G131: Totaal | J131: 89292 | K131: 87016 | L131: =SUM(L129:L130) -> 89368 | M131: =SUM(M129:M130) -> 91788 | N131: =SUM(N129:N130) -> 94278 | O131: =SUM(O129:O130) -> 96839
D133: 604028 | G133: Financieel Beleid
G134: Lasten
A135: =+D133 -> 604028 | B135: =G133 -> Financieel Beleid | D135: 43511 | G135: Inhuur personeel | J135: 13701 | K135: 10000 | L135: =+L498 -> 10420 | M135: =+M498 -> 10806 | N135: =+N498 -> 11206 | O135: =+O498 -> 11621
G136: Totaal | J136: 13701 | K136: 10000 | L136: =SUM(L135:L135) -> 10420 | M136: =SUM(M135:M135) -> 10806 | N136: =SUM(N135:N135) -> 11206 | O136: =SUM(O135:O135) -> 11621
D138: 604029 | G138: Communicatie
G139: Lasten
A140: =+D138 -> 604029 | B140: =G138 -> Communicatie | D140: 43812 | G140: Overige goederen en diensten | J140: 177867 | K140: 168830 | L140: =L510 -> 171703 | M140: =M510 -> 175183 | N140: =N510 -> 178727 | O140: =O510 -> 182334
G141: Totaal | J141: 177867 | K141: 168830 | L141: =SUM(L140:L140) -> 171703 | M141: =SUM(M140:M140) -> 175183 | N141: =SUM(N140:N140) -> 178727 | O141: =SUM(O140:O140) -> 182334
D143: 604030 | G143: Advertentiekosten
G144: Lasten
A145: =+D143 -> 604030 | B145: =G143 -> Advertentiekosten | D145: 43812 | G145: Overige goederen en diensten | J145: 9388 | K145: 6765 | L145: =L527 -> 6933 | M145: =M527 -> 6969 | N145: =N527 -> 7319 | O145: =O527 -> 7384
G146: Totaal | J146: 9388 | K146: 6765 | L146: =SUM(L145) -> 6933 | M146: =SUM(M145) -> 6969 | N146: =SUM(N145) -> 7319 | O146: =SUM(O145) -> 7384
D148: 604031 | G148: Digitale dienstverlening
G149: Lasten
A150: =+D148 -> 604031 | B150: =G148 -> Digitale dienstverlening | D150: 43812 | G150: Overige goederen en diensten | J150: 0 | K150: 0 | L150: 0 | M150: 0 | N150: 0 | O150: 0
G151: Totaal | J151: 0 | K151: 0 | L151: =SUM(L150) -> 0 | M151: =SUM(M150) -> 0 | N151: =SUM(N150) -> 0 | O151: =SUM(O150) -> 0
D153: 604032 | G153: Juridische Zaken
G154: Lasten
A155: =+D153 -> 604032 | B155: =G153 -> Juridische Zaken | D155: 43511 | G155: Inhuur personeel | J155: 8165 | K155: 8377 | L155: =+L533 -> 8553 | M155: =+M533 -> 8750 | N155: =+N533 -> 8951 | O155: =+O533 -> 9157
...

Sheet T04B
A1: Inhoudsopgave | Q1: 2024 | R1: 2025 | S1: 2026 | T1: 2027 | U1: 2028 | V1: 2029 | W1: 2030
D2: Programma | H2: 12. Overhead | P2: Prijzen | Q2: =+Indexering!G4 -> 1.037 | R2: =+Indexering!H4 -> 1.028 | S2: =+Indexering!I4 -> 1.026 | T2: =+Indexering!J4 -> 1.021 | U2: =+Indexering!K4 -> 1.023 | V2: =+Indexering!L4 -> 1.023 | W2: =+Indexering!M4 -> 1.023
P3: Lonen | Q3: =+Indexering!G5 -> 1.052 | R3: =+Indexering!H5 -> 1.049 | S3: =+Indexering!I5 -> 1.02 | T3: =+Indexering!J5 -> 1.042 | U3: =+Indexering!K5 -> 1.037 | V3: =+Indexering!L5 -> 1.037 | W3: =+Indexering!M5 -> 1.037
D4: Taakveld | H4: T04 Overhead - onderdeel bedrijfsvoering | S4: =+Indexering!I6 -> 1.02282 | T4: =+Indexering!J6 -> 1.03213 | U4: =+Indexering!K6 -> 1.03042 | V4: =+Indexering!L6 -> 1.03042 | W4: =+Indexering!M6 -> 1.03042
D31: In te zetten middelen
D33: Lasten in € (+) | J33: 2025 | K33: 2026 | L33: 2027 | M33: 2028 | N33: 2029 | O33: 2030 | Q33: 2026 | R33: 2027 | S33: 2028
C34: 2 | D34: =G80 -> Exploitatielasten gemeentehuis | J34: 413501.48 | K34: 426178.4 | L34: =L92 -> 438421.25 | M34: =M92 -> 451583.78 | N34: =N92 -> 465153.98 | O34: =O92 -> 295303
C35: 2 | D35: =G94 -> Dienstverleningsvisie | J35: 1108 | K35: 21108 | L35: =L97 -> 21108 | M35: =M97 -> 21108 | N35: =N97 -> 21108 | O35: =O97 -> 21108
C36: 2 | D36: directe toerek overhead (incl doorbelasting naar investeringen, T21, T52, T57 en T82) | J36: 307657.7 | K36: 197311.89 | L36: =L211 -> 416428.37 | M36: =M211 -> 420766.4 | N36: =N211 -> 389400.13 | O36: =O211 -> 136316.76
C37: 2 | D37: =G100 -> Bodediensten | J37: 4319 | K37: 4431 | L37: =L105 -> 6024 | M37: =M105 -> 4628 | N37: =N105 -> 4735 | O37: =O105 -> 4843
C38: 2 | D38: =G107 -> Keuken en keukenbenodigdheden | J38: 40948 | K38: 42013 | L38: =L112 -> 42895 | M38: =M112 -> 43883 | N38: =N112 -> 44892 | O38: =O112 -> 45924
C39: 2 | D39: =G114 -> Telefonie | J39: 103827 | K39: 106527 | L39: =L117 -> 108764 | M39: =M117 -> 111266 | N39: =N117 -> 113825 | O39: =O117 -> 116443
C40: 2 | D40: =G119 -> Huisdrukkerij | J40: 68945 | K40: 70738 | L40: =L122 -> 72223 | M40: =M122 -> 73884 | N40: =N122 -> 75583 | O40: =O122 -> 77321
C41: 2 | D41: =G124 -> Vakliteratuur | J41: 23333 | K41: 23940 | L41: =L127 -> 24443 | M41: =M127 -> 25005 | N41: =N127 -> 25580 | O41: =O127 -> 26168
C42: 2 | D42: =G129 -> Contributies en lidmaatschappen algemeen | J42: 206380.2 | K42: 214508.97 | L42: =L133 -> 222078.72 | M42: =M133 -> 231875.83 | N42: =N133 -> 241261.42 | O42: =O133 -> 247317.63
C43: 2 | D43: =G135 -> Archief | J43: 4856 | K43: 4982 | L43: =L139 -> 5087 | M43: =M139 -> 5204 | N43: =N139 -> 5324 | O43: =O139 -> 5446
C44: 2 | D44: =G141 -> Bedrijfshulpverlening / BHV | J44: 6751 | K44: 6940 | L44: =L145 -> 7134 | M44: =M145 -> 7334 | N44: =N145 -> 7539 | O44: =O145 -> 7750
C45: 2 | D45: =G147 -> Inventaris | J45: 40104 | K45: 41147 | L45: =L151 -> 42010 | M45: =M151 -> 42976 | N45: =N151 -> 43965 | O45: =O151 -> 44976
C46: 2 | D46: =G153 -> Facilitaire Zaken | J46: 59544 | K46: 61092 | L46: =+L156 -> 62375 | M46: =+M156 -> 63810 | N46: =+N156 -> 65278 | O46: =+O156 -> 66779
C47: 2 | D47: =G158 -> Automatisering | J47: 1424215 | K47: 1895465.3 | L47: =L164 -> 1925453 | M47: =M164 -> 1458671 | N47: =N164 -> 1492773 | O47: =O164 -> 1527568
C48: 2 | D48: =G166 -> Informatiemanagement | J48: 101464 | K48: 62709 | L48: =L169 -> 63964 | M48: =M169 -> 65499 | N48: =N169 -> 67069 | O48: =O169 -> 68546
C49: 2 | D49: =G171 -> Informatievoorziening | J49: 125456 | K49: 128718 | L49: =L174 -> 131421 | M49: =M174 -> 134443 | N49: =N174 -> 137535 | O49: =O174 -> 140698
C50: 2 | D50: =G176 -> Digitale basiskaart | J50: 9905 | K50: 10162 | L50: =L179 -> 10375 | M50: =M179 -> 10613.78 | N50: =N179 -> 10858.26 | O50: =O179 -> 11107.91
C51: 2 | D51: =G181 -> GBA | J51: 7116 | K51: 7301 | L51: =L184 -> 7454 | M51: =M184 -> 7625 | N51: =N184 -> 7800 | O51: =O184 -> 7979
D52: Project tijdelijke huisvesting | J52: 88000 | K52: 0 | L52: =+L203 -> 0 | M52: =+M203 -> 0 | N52: =+N203 -> 0 | O52: =+O203 -> 0
D53: Totaal lasten | J53: 2949430.4 | K53: 3325272.6 | L53: =SUM(L34:L51) -> 3607658.3 | M53: =SUM(M34:M51) -> 3180175.8 | N53: =SUM(N34:N51) -> 3219679.8 | O53: =SUM(O34:O51) -> 2851594.3
D55: Baten in € (-) | J55: 2025 | K55: 2026 | L55: =+L33 -> 2027 | M55: =+M33 -> 2028 | N55: =+N33 -> 2029 | O55: =+O33 -> 2030
C57: 2 | D57: =G191 -> Huisdrukkerij | J57: -4318 | K57: -4430 | L57: =L194 -> -4523 | M57: =M194 -> -4627 | N57: =N194 -> -4733 | O57: =O194 -> -4842
C58: 2 | D58: =G196 -> Archief | J58: -4051 | K58: -4156 | L58: =L199 -> -4243 | M58: =M199 -> -4341 | N58: =N199 -> -4441 | O58: =O199 -> -4543
D69: Totaal baten | J69: -8369 | K69: -8586 | L69: =SUM(L56:L68) -> -8766 | M69: =SUM(M56:M68) -> -8968 | N69: =SUM(N56:N68) -> -9174 | O69: =SUM(O56:O68) -> -9385
D71: Saldo voor bijdragen en stortingen in reserves (+ = nadeel) | J71: 2941061.4 | K71: 3316686.6 | L71: =L53+L69 -> 3598892.3 | M71: =M53+M69 -> 3171207.8 | N71: =N53+N69 -> 3210505.8 | O71: =O53+O69 -> 2842209.3
J74: 2633403.7 | K74: 3119374.7 | L74: =+L71-L36 -> 3182464 | M74: =+M71-M36 -> 2750441.4 | N74: =+N71-N36 -> 2821105.7 | O74: =+O71-O36 -> 2705892.5
D75: Financiële toelichting
D77: Grootb/cat t/m 2019 | E77: Bbv Taakv/ | F77: Grootb/cat nummer | G77: Omschrijving
E78: Bbv cat | J78: 2025 | K78: 2026 | L78: 2027 | M78: 2028 | N78: 2029 | O78: 2030
D80: 604006 | G80: Exploitatielasten gemeentehuis
G81: Lasten
A82: 604006 | B82: =G80 -> Exploitatielasten gemeentehuis | D82: 42100 | G82: Belastingen en heffingen (waterschapslasten) | J82: 4380 | K82: 4503 | L82: =ROUND(K82*T$2,0)+27 -> 4625 | M82: =ROUND(L82*U$2,0)+28 -> 4759 | N82: =ROUND(M82*V$2,0)+28 -> 4896 | O82: =ROUND(N82*W$2,0) -> 5009
A83: 604006 | B83: =G80 -> Exploitatielasten gemeentehuis | D83: 42100 | G83: Belastingen en heffingen (afvalstoffenheffing) | J83: 2463 | K83: 2532 | L83: =ROUND(K83*T$2,0)+15 -> 2600 | M83: =ROUND(L83*U$2,0)+16 -> 2676 | N83: =ROUND(M83*V$2,0)+16 -> 2754 | O83: =ROUND(N83*W$2,0) -> 2817
A84: 604006 | B84: =G80 -> Exploitatielasten gemeentehuis | D84: 42100 | G84: Belastingen en heffingen (rioolrecht) | J84: 891 | K84: 916 | L84: =ROUND(K84*T$2,0)+6 -> 941 | M84: =ROUND(L84*U$2,0)+5 -> 968 | N84: =ROUND(M84*V$2,0)+6 -> 996 | O84: =ROUND(N84*W$2,0) -> 1019
A85: 604006 | B85: =G80 -> Exploitatielasten gemeentehuis | D85: 43801 | G85: Gasverbruik | J85: 44054 | K85: 45288 | L85: =L225 -> 46511 | M85: =M225 -> 47861 | N85: =N225 -> 49249 | O85: =O225 -> 50382
A86: 604006 | B86: =G80 -> Exploitatielasten gemeentehuis | D86: 43802 | G86: Elektriciteit | J86: 51400 | K86: 52839 | L86: =L229 -> 54266 | M86: =M229 -> 55840 | N86: =N229 -> 57459 | O86: =O229 -> 58781
A87: 604006 | B87: =G80 -> Exploitatielasten gemeentehuis | D87: 43806 | G87: Verzekeringen (brandverzekering) | J87: 19825 | K87: 20380 | L87: =ROUND(K87*T$2,0)+123 -> 20931 | M87: =ROUND(L87*U$2,0)+126 -> 21538 | N87: =ROUND(M87*V$2,0)+129 -> 22162 | O87: =ROUND(N87*W$2,0) -> 22672
A88: 604006 | B88: =G80 -> Exploitatielasten gemeentehuis | D88: 43812 | G88: Overige goederen en diensten | J88: 76581 | K88: 78572 | L88: =L246 -> 80222 | M88: =M246 -> 82067 | N88: =N246 -> 83955 | O88: =O246 -> 85886
A89: 604006 | B89: =G80 -> Exploitatielasten gemeentehuis | D89: 43812 | G89: Water | J89: 1416 | K89: 1453 | L89: =L248 -> 1484 | M89: =M248 -> 1518 | N89: =N248 -> 1553 | O89: =O248 -> 1589
A90: 604006 | B90: =G80 -> Exploitatielasten gemeentehuis | D90: 43817 | G90: Exploitatielasten vastgoed (contracten vastgoed) | J90: 59872 | K90: 61429 | L90: =L254 -> 62719 | M90: =M254 -> 64162 | N90: =N254 -> 65638 | O90: =O254 -> 67148
A91: 604006 | B91: =G80 -> Exploitatielasten gemeentehuis | D91: 47201 | G91: Onderhoudsvoorzieningen (O101) | J91: 152619.48 | K91: 158266.4 | L91: 164122.25 | M91: 170194.78 | N91: 176491.98 | O91: 0
G92: Totaal | J92: 413501.48 | K92: 426178.4 | L92: =SUM(L82:L91) -> 438421.25 | M92: =SUM(M82:M91) -> 451583.78 | N92: =SUM(N82:N91) -> 465153.98 | O92: =SUM(O82:O91) -> 295303
D94: 604007 | G94: Dienstverleningsvisie
G95: Lasten
A96: =+D94 -> 604007 | B96: =G94 -> Dienstverleningsvisie | D96: 43812 | G96: Overige goederen en diensten | J96: 1108 | K96: 21108 | L96: =L273 -> 21108 | M96: =M273 -> 21108 | N96: =N273 -> 21108 | O96: =O273 -> 21108
G97: Totaal | J97: 1108 | K97: 21108 | L97: =SUM(L95:L96) -> 21108 | M97: =SUM(M95:M96) -> 21108 | N97: =SUM(N95:N96) -> 21108 | O97: =SUM(O95:O96) -> 21108
D100: 604008 | G100: Bodediensten
G101: Lasten
A102: 604008 | B102: =G100 -> Bodediensten | D102: 43201 | G102: Duurzame roerende goederen | J102: 1401 | K102: 1437 | L102: =L283 -> 2967 | M102: =M283 -> 1501 | N102: =N283 -> 1536 | O102: =O283 -> 1571
A103: 604008 | B103: =G100 -> Bodediensten | D103: 43818 | G103: Werkkostenregeling (kleding zonder logo) | J103: 1750 | K103: 1796 | L103: =L286 -> 1834 | M103: =M286 -> 1876 | N103: =N286 -> 1919 | O103: =O286 -> 1963
A104: 604008 | B104: =G100 -> Bodediensten | D104: 43818 | G104: Werkkostenregeling (reparatie kleding zonder logo) | J104: 1168 | K104: 1198 | L104: =L289 -> 1223 | M104: =M289 -> 1251 | N104: =N289 -> 1280 | O104: =O289 -> 1309
G105: Totaal | J105: 4319 | K105: 4431 | L105: =SUM(L102:L104) -> 6024 | M105: =SUM(M102:M104) -> 4628 | N105: =SUM(N102:N104) -> 4735 | O105: =SUM(O102:O104) -> 4843
D107: 604009 | G107: Keuken en keukenbenodigdheden
G108: Lasten
A109: 604009 | B109: =G107 -> Keuken en keukenbenodigdheden | D109: 43201 | G109: Duurzame roerende goederen | J109: 992 | K109: 1018 | L109: =L303 -> 1039 | M109: =M303 -> 1063 | N109: =N303 -> 1087 | O109: =O303 -> 1112
A110: 604009 | B110: =G107 -> Keuken en keukenbenodigdheden | D110: 43511 | G110: Inhuur personeel | J110: 525 | K110: 539 | L110: =L297 -> 550 | M110: =M297 -> 563 | N110: =N297 -> 576 | O110: =O297 -> 589
A111: 604009 | B111: =G107 -> Keuken en keukenbenodigdheden | D111: 43812 | G111: Overige goederen en diensten | J111: 39431 | K111: 40456 | L111: =L314 -> 41306 | M111: =M314 -> 42257 | N111: =N314 -> 43229 | O111: =O314 -> 44223
G112: Totaal | J112: 40948 | K112: 42013 | L112: =SUM(L109:L111) -> 42895 | M112: =SUM(M109:M111) -> 43883 | N112: =SUM(N109:N111) -> 44892 | O112: =SUM(O109:O111) -> 45924
D114: 604010 | G114: Telefonie
G115: Lasten
A116: 604010 | B116: =G114 -> Telefonie | D116: 43818 | G116: Werkkostenregeling (telefonie) | J116: 103827 | K116: 106527 | L116: =L327 -> 108764 | M116: =M327 -> 111266 | N116: =N327 -> 113825 | O116: =O327 -> 116443
G117: Totaal | J117: 103827 | K117: 106527 | L117: =SUM(L116:L116) -> 108764 | M117: =SUM(M116:M116) -> 111266 | N117: =SUM(N116:N116) -> 113825 | O117: =SUM(O116:O116) -> 116443
D119: 604011 | G119: Huisdrukkerij
G120: Lasten
A121: =+D119 -> 604011 | B121: =G119 -> Huisdrukkerij | D121: 43812 | G121: Overige goederen en diensten | J121: 68945 | K121: 70738 | L121: =L350 -> 72223 | M121: =M350 -> 73884 | N121: =N350 -> 75583 | O121: =O350 -> 77321
G122: Totaal | J122: 68945 | K122: 70738 | L122: =SUM(L120:L121) -> 72223 | M122: =SUM(M120:M121) -> 73884 | N122: =SUM(N120:N121) -> 75583 | O122: =SUM(O120:O121) -> 77321
D124: 604012 | G124: Vakliteratuur
G125: Lasten
A126: =+D124 -> 604012 | B126: =G124 -> Vakliteratuur | D126: 43818 | G126: Werkkostenregeling (vakliteratuur) | J126: 23333 | K126: 23940 | L126: =L356 -> 24443 | M126: =M356 -> 25005 | N126: =N356 -> 25580 | O126: =O356 -> 26168
G127: Totaal | J127: 23333 | K127: 23940 | L127: =SUM(L126) -> 24443 | M127: =SUM(M126) -> 25005 | N127: =SUM(N126) -> 25580 | O127: =SUM(O126) -> 26168
D129: 604023 | G129: Contributies en lidmaatschappen algemeen
G130: Lasten
A131: =+D129 -> 604023 | B131: =G129 -> Contributies en lidmaatschappen algemeen | D131: 43812 | G131: Overige goederen en diensten | J131: 4516 | K131: 4633 | L131: =L368 -> 4730 | M131: =M368 -> 4839 | N131: =N368 -> 4950 | O131: =O368 -> 5064
A132: =+D129 -> 604023 | B132: =G129 -> Contributies en lidmaatschappen algemeen | D132: 44360 | G132: Inkomensoverdrachten ov overheden | J132: 201864.2 | K132: 209875.97 | L132: =L394 -> 217348.72 | M132: =M394 -> 227036.83 | N132: =N394 -> 236311.42 | O132: =O394 -> 242253.63
G133: Totaal | J133: 206380.2 | K133: 214508.97 | L133: =SUM(L131:L132) -> 222078.72 | M133: =SUM(M131:M132) -> 231875.83 | N133: =SUM(N131:N132) -> 241261.42 | O133: =SUM(O131:O132) -> 247317.63
D135: 604013 | G135: Archief
G136: Lasten
A137: 604013 | B137: =G135 -> Archief | D137: 43806 | G137: Verzekeringen | J137: 0 | K137: 0 | L137: =ROUND(K137*T$2,0) -> 0 | M137: =ROUND(L137*U$2,0) -> 0 | N137: =ROUND(M137*V$2,0) -> 0 | O137: =ROUND(N137*W$2,0) -> 0
A138: 604013 | B138: =G135 -> Archief | D138: 43812 | G138: Overige goederen en diensten | J138: 4856 | K138: 4982 | L138: =L410 -> 5087 | M138: =M410 -> 5204 | N138: =N410 -> 5324 | O138: =O410 -> 5446
G139: Totaal | J139: 4856 | K139: 4982 | L139: =SUM(L137:L138) -> 5087 | M139: =SUM(M137:M138) -> 5204 | N139: =SUM(N137:N138) -> 5324 | O139: =SUM(O137:O138) -> 5446
D141: 604014 | G141: Bedrijfshulpverlening / BHV
G142: Lasten
A143: 604014 | B143: =G141 -> Bedrijfshulpverlening / BHV | D143: 43812 | G143: Overige goederen en diensten | J143: 6216 | K143: 6390 | L143: =ROUND(K143*$R$2,0) -> 6569 | M143: =ROUND(L143*$R$2,0) -> 6753 | N143: =ROUND(M143*$R$2,0) -> 6942 | O143: =ROUND(N143*$R$2,0) -> 7136
A144: 604014 | B144: =G141 -> Bedrijfshulpverlening / BHV | D144: 43818 | G144: Werkkostenregeling (BHV uitje) | J144: 535 | K144: 550 | L144: =ROUND(K144*$R$2,0) -> 565 | M144: =ROUND(L144*$R$2,0) -> 581 | N144: =ROUND(M144*$R$2,0) -> 597 | O144: =ROUND(N144*$R$2,0) -> 614
G145: Totaal | J145: 6751 | K145: 6940 | L145: =SUM(L143:L144) -> 7134 | M145: =SUM(M143:M144) -> 7334 | N145: =SUM(N143:N144) -> 7539 | O145: =SUM(O143:O144) -> 7750
D147: 604015 | G147: Inventaris
G148: Lasten
A149: 604015 | B149: =G147 -> Inventaris | D149: 43201 | G149: Duurzame roerende goederen | J149: 8517 | K149: 8738 | L149: =ROUND(K149*T$2,0) -> 8921 | M149: =ROUND(L149*U$2,0) -> 9126 | N149: =ROUND(M149*V$2,0) -> 9336 | O149: =ROUND(N149*W$2,0) -> 9551
A150: 604015 | B150: =G147 -> Inventaris | D150: 43812 | G150: Overige goederen en diensten | J150: 31587 | K150: 32409 | L150: =L427 -> 33089 | M150: =M427 -> 33850 | N150: =N427 -> 34629 | O150: =O427 -> 35425
G151: Totaal | J151: 40104 | K151: 41147 | L151: =SUM(L149:L150) -> 42010 | M151: =SUM(M149:M150) -> 42976 | N151: =SUM(N149:N150) -> 43965 | O151: =SUM(O149:O150) -> 44976
D153: 604016 | G153: Facilitaire Zaken
G154: Lasten
A155: =+D153 -> 604016 | B155: =+G153 -> Facilitaire Zaken | D155: 43812 | G155: Overige goederen en diensten | J155: 59544 | K155: 61092 | L155: =+L339 -> 62375 | M155: =+M339 -> 63810 | N155: =+N339 -> 65278 | O155: =+O339 -> 66779
G156: Totaal | J156: 59544 | K156: 61092 | L156: =SUM(L155:L155) -> 62375 | M156: =SUM(M155:M155) -> 63810 | N156: =SUM(N155:N155) -> 65278 | O156: =SUM(O155:O155) -> 66779
...

Sheet T04W
A1: Inhoudsopgave | Q1: 2024 | R1: 2025 | S1: 2026 | T1: 2027 | U1: 2028 | V1: 2029 | W1: 2030
D2: Programma | H2: 12. Overhead | P2: Prijzen | Q2: =+Indexering!G4 -> 1.037 | R2: =+Indexering!H4 -> 1.028 | S2: =+Indexering!I4 -> 1.026 | T2: =+Indexering!J4 -> 1.021 | U2: =+Indexering!K4 -> 1.023 | V2: =+Indexering!L4 -> 1.023 | W2: =+Indexering!M4 -> 1.023
P3: Lonen | Q3: =+Indexering!G5 -> 1.052 | R3: =+Indexering!H5 -> 1.049 | S3: =+Indexering!I5 -> 1.02 | T3: =+Indexering!J5 -> 1.042 | U3: =+Indexering!K5 -> 1.037 | V3: =+Indexering!L5 -> 1.037 | W3: =+Indexering!M5 -> 1.037
D4: Taakveld | H4: T04 Overhead, doorbelasting werf en vervoermiddelen | S4: =+Indexering!I6 -> 1.02282 | T4: =+Indexering!J6 -> 1.03213 | U4: =+Indexering!K6 -> 1.03042 | V4: =+Indexering!L6 -> 1.03042 | W4: =+Indexering!M6 -> 1.03042
D25: Dit onderdeel wordt gebruikt als hulpmiddel om algemene kosten vanwege de gemeentewerf, vervoermiddelen te verzamelen. Vervolgens worden alle lasten
D26: via een verdeelsleutel doorbelast naar de taakvelden die van toepassing zijn. Het saldo van baten -/- lasten in dit taakveld is elk jaar altijd 0.
D31: In te zetten middelen
D33: Lasten in € (+) | J33: 2025 | K33: 2026 | L33: 2027 | M33: 2028 | N33: 2029 | O33: 2030 | Q33: 2026 | R33: 2027 | S33: 2028
C34: 3 | D34: Vijverweg 1 (werf) | J34: 131540 | K34: 137598.14 | L34: =+L91 -> 140429.05 | M34: =+M91 -> 143526.4 | N34: =+N91 -> 146724.87 | O34: =+O91 -> 92967.42
C35: 3 | D35: =G93 -> Gereedschappen | J35: 27348 | K35: 28059 | L35: =+L100 -> 28648 | M35: =+M100 -> 29307 | N35: =+N100 -> 29982 | O35: =+O100 -> 30671
C36: 3 | D36: =G102 -> Vervoermiddelen (algemeen) | J36: 114168 | K36: 78971 | L36: =+L111 -> 86044 | M36: =+M111 -> 93664 | N36: =+N111 -> 95116 | O36: =+O111 -> 66805
C37: 3 | D37: Doorberekening werf aan T21 (wegen), T52 (sport) en T57 (groen) | J37: -131540 | K37: -137598.14 | L37: =+L201 -> -140429.05 | M37: =+M201 -> -143526.4 | N37: =+N201 -> -146724.87 | O37: =+O201 -> -92967.42
C38: 3 | D38: Doorberekening gereedschappen aan T21 (wegen), T52 (sport) en T57 (groen) | J38: -27348 | K38: -28059 | L38: =+L232 -> -28648 | M38: =+M232 -> -29307 | N38: =+N232 -> -29982 | O38: =+O232 -> -30671
C39: 3 | D39: Doorberekening vervoermiddelen aan T21 (wegen), T52 (sport) en T57 (groen) | J39: -114168 | K39: -78971 | L39: =+L274 -> -86044 | M39: =+M274 -> -93664 | N39: =+N274 -> -95116 | O39: =+O274 -> -66805 | Q39: =SUM(K34:K39) -> 0 | R39: =SUM(L34:L39) -> 0 | S39: =SUM(M34:M39) -> 0
D41: Totaal lasten | J41: 0 | K41: =SUM(K34:K39) -> 0 | L41: =SUM(L34:L39) -> 0 | M41: =SUM(M34:M39) -> 0 | N41: =SUM(N34:N39) -> 0 | O41: =SUM(O34:O39) -> 0 | Q41: =SUM(K34:K40) -> 0 | R41: =SUM(L34:L40) -> 0 | S41: =SUM(M34:M40) -> 0
D43: Baten in € (-) | J43: 2025 | K43: 2026 | L43: =+L33 -> 2027 | M43: =+M33 -> 2028 | N43: =+N33 -> 2029 | O43: =+O33 -> 2030
D54: Totaal baten | J54: 0 | K54: =SUM(K44:K53) -> 0 | L54: =SUM(L44:L53) -> 0 | M54: =SUM(M44:M53) -> 0 | N54: =SUM(N44:N53) -> 0 | O54: =SUM(O44:O53) -> 0
D56: Saldo voor bijdragen en stortingen in reserves (+ = nadeel) | J56: 0 | K56: 0 | L56: =L41+L54 -> 0 | M56: =M41+M54 -> 0 | N56: =N41+N54 -> 0 | O56: =O41+O54 -> 0
D60: Financiële toelichting
D62: Grootb/cat t/m 2019 | E62: Bbv Taakv/ | F62: Grootb/cat nummer | G62: Omschrijving
E63: Bbv cat | J63: 2025 | K63: 2026 | L63: 2027 | M63: 2028 | N63: 2029 | O63: 2030
D65: 604041 | G65: TIC/KCC
G66: Totaal | J66: 0 | K66: 0 | L66: =+L65 -> 0 | M66: =+M65 -> 0 | N66: =+N65 -> 0 | O66: =+O65 -> 0
D68: 604043 | G68: Flexibele schil 2e lijn
G69: Lasten
A70: =+D68 -> 604043 | B70: =G68 -> Flexibele schil 2e lijn | D70: 43511 | G70: Salarissen etc | J70: 0 | K70: 0 | L70: 0 | M70: 0 | N70: 0 | O70: 0
G71: Totaal | J71: 0 | K71: 0 | L71: =SUM(L70) -> 0 | M71: =SUM(M70) -> 0 | N71: =SUM(N70) -> 0 | O71: =SUM(O70) -> 0
D73: 604045 | G73: Vijverweg 1 (werf)
G74: Lasten
A75: 604045 | B75: =G73 -> Vijverweg 1 (werf) | D75: 42100 | G75: Belastingen en heffingen (ozb) | J75: 8330 | K75: 8563 | L75: =ROUND(K75*T$2,0) -> 8743 | M75: =ROUND(L75*U$2,0) -> 8944 | N75: =ROUND(M75*V$2,0) -> 9150 | O75: =ROUND(N75*W$2,0) -> 9360
A76: 604045 | B76: =G73 -> Vijverweg 1 (werf) | D76: 42100 | G76: Belastingen en heffingen (waterschapslasten) | J76: 1422 | K76: 1462 | L76: =ROUND(K76*T$2,0) -> 1493 | M76: =ROUND(L76*U$2,0) -> 1527 | N76: =ROUND(M76*V$2,0) -> 1562 | O76: =ROUND(N76*W$2,0) -> 1598
A77: 604045 | B77: =G73 -> Vijverweg 1 (werf) | D77: 42100 | G77: Belastingen en heffingen (rioolrecht) | J77: 190 | K77: 195 | L77: =ROUND(K77*T$2,0) -> 199 | M77: =ROUND(L77*U$2,0) -> 204 | N77: =ROUND(M77*V$2,0) -> 209 | O77: =ROUND(N77*W$2,0) -> 214
A78: 604045 | B78: =G73 -> Vijverweg 1 (werf) | D78: 43511 | G78: Inhuur personeel | J78: 20081 | K78: 20606 | L78: =L289 -> 21034 | M78: =M289 -> 21516 | N78: =N289 -> 22009.05 | O78: =O289 -> 22512.42
